Workbook

Sheet GENERAL
B2: INVERSIÓN PORTAFOLIO | C2: =SUM(L:L) -> 11000.586 | E2: PLUSVALÍA (%) | G2: =SUM(AB13:AB1001) -> 1.3016213 | J2: DIVIDENDO ANUAL BRUTO | N2: =SUM(AP13:AP1001) -> 0.049689274 | R2: RENTAS ANUALES BRUTAS | V2: =SUM(AN13:AN1001) -> 360.10094 | Z2: RENTAS REALES BRUTAS | AD2: =SUM(DIVIDENDOS!D:D) -> 39.773589 | AI2: % RENTAS PORTAFOLIO BRUTAS | AN2: =((V2*100)/C2)/100 -> 0.032734704
B5: VALOR PORTAFOLIO | C5: =SUM(M:M) -> #N/A | E5: GANANCIA ($) | G5: =SUM(AD13:AD1001) -> 1205.8738 | H5: =SUM(COMPRAS!I:I) -> -34.0099 | I5: =G5+H5 -> 1171.8639 | J5: DIVIDENDO ANUAL NETO | N5: =N2*0.7 -> 0.034782492 | R5: RENTAS ANUALES NETAS | V5: =V2*0.7 -> 252.07066 | Z5: RENTAS REALES NETAS | AD5: =SUM(DIVIDENDOS!E:E) -> 31.039583 | AI5: % RENTAS | AN5: =((V5*100)/C2)/100 -> 0.022914293
A8: CLAVE | B8: FIBRA | C8: Última información | D8: % Portafolio | E8: INFORMACIÓN BURSÁTIL | N8: INFORMACIÓN FUNDAMENTAL | AB8: RENTABILIDAD
B9: FIBRA | E9: Número de Títulos | F9: Costo promedio | G9: Precio de Mercado | H9: AVG Precio de Mercado 52S | I9: Cambio vs dia anterior (%) | J9: Volumen | K9: Costo Total Promedio | L9: Costo Total Compra | M9: Valor de Mercado | N9: Cap Rate Implícito | O9: AVG Cap Rate Implícito | P9: NAV por CBFI | Q9: AVG NAV por CBFI | R9: Distribución Trimestral por CBFI | S9: AVG Distribución Trimestral por CBFI | T9: Distribución Anual por CBFI | U9: AGV Distribución Anual por CBFI | V9: Loan To Value | W9: AVG Loan To Value | X9: Margen NOI | Y9: AVG Margen NOI | Z9: Margen FFO | AA9: AVG Margen FFO | AB9: Portafolio Plusvalía (%) | AC9: AVG Plusvalía (%) | AD9: Portafolio Ganancia ($) | AE9: AVG Ganancia ($) | AF9: NAV vs Precio Mercado | AG9: Dividend Yield Calculado | AH9: AVG Dividend Yield Calculado | AI9: Dividend Yield Decretado | AJ9: AVG Dividend Yield Decretado | AK9: AVG Dividend Yield | AL9: Renta Trimestral | AM9: AVG Renta Trimestral | AN9: Renta Anual | AO9: AVG Renta Anual | AP9: Dividendo Ponderado Bruto
A10: FHIPO14 | B10: FIBRA HIPOTECARIA | C10: {=IF(INDIRECT("'"&A$10&"'!"&"B10") ="",INDIRECT("'"&A$10&"'!"&"C1"),INDIRECT("'"&A$10&"'!"&"B1"))} -> 2023 Q1 | D10: =IFERROR(E10/SUM(E13:E35),0) -> 0.11079545 | E10: =SUMIFS(COMPRAS!B:B,COMPRAS!A:A,B10) -> 39 | F10: =IFERROR(AVERAGEIFS(COMPRAS!C:C,COMPRAS!A:A,B10),0) -> 16.5425 | G10: =IFERROR(yahooF(A10&".MX",1),F10) -> 16.5425 | H10: =IFERROR(__xludf.DUMMYFUNCTION("IFERROR(G10,(GOOGLEFINANCE(A10,""high52"") + GOOGLEFINANCE(A10,""low52""))/2)"),16.5425) -> 16.5425 | I10: =yahooF(A10&".MX",2) -> #ERROR! | J10: 7784 | K10: =E10*F10 -> 645.1575 | L10: =IFERROR(SUMIFS(COMPRAS!G:G,COMPRAS!A:A,B10),0) -> 637.94151 | M10: =E10*G10 -> 645.1575 | N10: {=IF(INDIRECT("'"&A$10&"'!"&"B12") ="",INDIRECT("'"&A$10&"'!"&"C12"),INDIRECT("'"&A$10&"'!"&"B12"))} | O10: {=IFERROR(AVERAGE(INDIRECT("'"&A$10&"'!"&"B12:F12")),"")} | P10: {=IF(INDIRECT("'"&A$10&"'!"&"B17") ="",INDIRECT("'"&A$10&"'!"&"C17"),INDIRECT("'"&A$10&"'!"&"B17"))} | Q10: {=IFERROR(AVERAGE(INDIRECT("'"&A$10&"'!"&"B17:F17")),"")} | R10: {=IF(INDIRECT("'"&A$10&"'!"&"B10") ="",INDIRECT("'"&A$10&"'!"&"C10"),INDIRECT("'"&A$10&"'!"&"B10"))} -> 0.2566 | S10: {=IFERROR(AVERAGE(INDIRECT("'"&A$10&"'!"&"B10:F10")),"")} -> 0.5060862 | T10: =R10*4 -> 1.0264 | U10: =S10*4 -> 2.0243448 | V10: {=IF(INDIRECT("'"&A$10&"'!"&"B15") ="",INDIRECT("'"&A$10&"'!"&"C15"),INDIRECT("'"&A$10&"'!"&"B15"))} | W10: {=IFERROR(AVERAGE(INDIRECT("'"&A$10&"'!"&"B15:F15")),"")} | X10: {=IF(INDIRECT("'"&A$10&"'!"&"B5") ="",INDIRECT("'"&A$10&"'!"&"C5"),INDIRECT("'"&A$10&"'!"&"B5"))} | Y10: {=IFERROR(AVERAGE(INDIRECT("'"&A$10&"'!"&"B5:F5")),"")} | Z10: {=IF(INDIRECT("'"&A$10&"'!"&"B7") ="",INDIRECT("'"&A$10&"'!"&"C7"),INDIRECT("'"&A$10&"'!"&"B7"))} | AA10: {=IFERROR(AVERAGE(INDIRECT("'"&A$10&"'!"&"B7:F7")),"")} | AB10: =IFERROR((G10/(L10/E10))-1,"") -> 0.011311371 | AC10: =IFERROR(U10/G10,"") -> 0.12237236 | AD10: =IFERROR(IF(M10-L10=0,"",M10-L10),"") -> 7.215993 | AE10: =IFERROR(IF(M10-K10=0,"",M10-K10),"") | AF10: =IF(P10>0,IFERROR((P10/G10)-1,""),"") | AG10: =IFERROR(T10/G10,"") -> 0.062046245 | AI10: {=IF(INDIRECT("'"&A$10&"'!"&"B16") ="",INDIRECT("'"&A$10&"'!"&"C16"),INDIRECT("'"&A$10&"'!"&"B16"))} | AJ10: {=IFERROR(AVERAGE(INDIRECT("'"&A$10&"'!"&"B16:F16")),"")} | AK10: =AVERAGE(AG10:AJ10) -> 0.062046245 | AL10: =IFERROR(IF(R10*E10=0,"",R10*E10),"") -> 10.0074 | AM10: =IFERROR(IF(S10*E10=0,"",S10*E10),"") -> 19.737362 | AN10: =IFERROR(IF(T10*E10=0,"",T10*E10),"") -> 40.0296 | AO10: =IFERROR(IF(U10*E10=0,"",U10*E10),"") -> 78.949447 | AP10: =IF(AC10*D10=0,"",AC10*D10) -> 0.013558301
A11: FCFE18 | B11: FIBRA CFE | C11: {=IF(INDIRECT("'"&A$11&"'!"&"B10") ="",INDIRECT("'"&A$11&"'!"&"C1"),INDIRECT("'"&A$11&"'!"&"B1"))} -> 2023 Q1 | D11: =IFERROR(E11/SUM(E13:E35),0) -> 0.13352273 | E11: =SUMIFS(COMPRAS!B:B,COMPRAS!A:A,B11) -> 47 | F11: =IFERROR(AVERAGEIFS(COMPRAS!C:C,COMPRAS!A:A,B11),0) -> 27.336667 | G11: =IFERROR(__xludf.DUMMYFUNCTION("GOOGLEFINANCE(A11,""price"")"),23.84) -> 23.84 | H11: =IFERROR(__xludf.DUMMYFUNCTION("(GOOGLEFINANCE(A11,""high52"") + GOOGLEFINANCE(A11,""low52""))/2"),23.03) -> 23.03 | I11: =IFERROR(__xludf.DUMMYFUNCTION("GOOGLEFINANCE(A11,""changepct"")"),0.17) -> 0.17 | J11: =IFERROR(__xludf.DUMMYFUNCTION("GOOGLEFINANCE(A11,""volume"")"),139923.0) -> 139923 | K11: =E11*F11 -> 1284.8233 | L11: =IFERROR(SUMIFS(COMPRAS!G:G,COMPRAS!A:A,B11),0) -> 1282.995 | M11: =E11*G11 -> 1120.48 | N11: {=IF(INDIRECT("'"&A$11&"'!"&"B12") ="",INDIRECT("'"&A$11&"'!"&"C12"),INDIRECT("'"&A$11&"'!"&"B12"))} | O11: {=IFERROR(AVERAGE(INDIRECT("'"&A$11&"'!"&"B12:F12")),"")} | P11: {=IF(INDIRECT("'"&A$11&"'!"&"B17") ="",INDIRECT("'"&A$11&"'!"&"C17"),INDIRECT("'"&A$11&"'!"&"B17"))} | Q11: {=IFERROR(AVERAGE(INDIRECT("'"&A$11&"'!"&"B17:F17")),"")} | R11: {=IF(INDIRECT("'"&A$11&"'!"&"B10") ="",INDIRECT("'"&A$11&"'!"&"C10"),INDIRECT("'"&A$11&"'!"&"B10"))} -> 0.575 | S11: {=IFERROR(AVERAGE(INDIRECT("'"&A$11&"'!"&"B10:F10")),0)} -> 0.7700312 | T11: =R11*4 -> 2.3 | U11: =S11*4 -> 3.0801248 | V11: {=IF(INDIRECT("'"&A$11&"'!"&"B15") ="",INDIRECT("'"&A$11&"'!"&"C15"),INDIRECT("'"&A$11&"'!"&"B15"))} | W11: {=IFERROR(AVERAGE(INDIRECT("'"&A$11&"'!"&"B15:F15")),"")} | X11: {=IF(INDIRECT("'"&A$11&"'!"&"B5") ="",INDIRECT("'"&A$11&"'!"&"C5"),INDIRECT("'"&A$11&"'!"&"B5"))} | Y11: {=IFERROR(AVERAGE(INDIRECT("'"&A$11&"'!"&"B5:F5")),0)} -> 0 | Z11: {=IF(INDIRECT("'"&A$11&"'!"&"B7") ="",INDIRECT("'"&A$11&"'!"&"C7"),INDIRECT("'"&A$11&"'!"&"B7"))} | AA11: {=IFERROR(AVERAGE(INDIRECT("'"&A$11&"'!"&"B7:F7")),0)} -> 0 | AB11: =IFERROR((G11/(L11/E11))-1,"") -> -0.12666845 | AC11: =IFERROR(U11/G11,"") -> 0.12919987 | AD11: =IFERROR(IF(M11-L11=0,"",M11-L11),"") -> -162.51499 | AE11: =IFERROR(IF(M11-K11=0,"",M11-K11),"") -> -164.34333 | AF11: =IF(P11>0,IFERROR((P11/G11)-1,""),"") | AG11: =IFERROR(T11/G11,"") -> 0.09647651 | AI11: {=IF(INDIRECT("'"&A$11&"'!"&"B16") ="",INDIRECT("'"&A$11&"'!"&"C16"),INDIRECT("'"&A$11&"'!"&"B16"))} | AJ11: {=IFERROR(AVERAGE(INDIRECT("'"&A$11&"'!"&"B16:F16")),"")} | AK11: =AVERAGE(AG11:AJ11) -> 0.09647651 | AL11: =IFERROR(IF(R11*E11=0,"",R11*E11),"") -> 27.025 | AM11: =IFERROR(IF(S11*E11=0,"",S11*E11),"") -> 36.191466 | AN11: =IFERROR(IF(T11*E11=0,"",T11*E11),"") -> 108.1 | AO11: =IFERROR(IF(U11*E11=0,"",U11*E11),"") -> 144.76587 | AP11: =IF(AC11*D11=0,"",AC11*D11) -> 0.017251118
A12: =DANHOS13!A1 -> DANHOS13 | B12: FIBRA DAHNOS | C12: {=IF(INDIRECT("'"&A$12&"'!"&"B10") ="",INDIRECT("'"&A$12&"'!"&"C1"),INDIRECT("'"&A$12&"'!"&"B1"))} -> 2023 Q1 | D12: =IFERROR(E12/SUM(E13:E35),0) -> 0.28409091 | E12: =SUMIFS(COMPRAS!B:B,COMPRAS!A:A,B12) -> 100 | F12: =IFERROR(AVERAGEIFS(COMPRAS!C:C,COMPRAS!A:A,B12),0) -> 21.99 | G12: =IFERROR(__xludf.DUMMYFUNCTION("GOOGLEFINANCE(A12,""price"")"),27.34) -> 27.34 | H12: =IFERROR(__xludf.DUMMYFUNCTION("(GOOGLEFINANCE(A12,""high52"") + GOOGLEFINANCE(A12,""low52""))/2"),28.07) -> 28.07 | I12: =IFERROR(__xludf.DUMMYFUNCTION("GOOGLEFINANCE(A12,""changepct"")"),-0.83) -> -0.83 | J12: =IFERROR(__xludf.DUMMYFUNCTION("GOOGLEFINANCE(A12,""volume"")"),514835.0) -> 514835 | K12: =E12*F12 -> 2199 | L12: =IFERROR(SUMIFS(COMPRAS!G:G,COMPRAS!A:A,B12),0) -> 2230.4731 | M12: =E12*G12 -> 2734 | N12: {=IF(INDIRECT("'"&A$12&"'!"&"B12") ="",INDIRECT("'"&A$12&"'!"&"C12"),INDIRECT("'"&A$12&"'!"&"B12"))} -> 0.069 | O12: {=IFERROR(AVERAGE(INDIRECT("'"&A$12&"'!"&"B12:F12")),"")} -> 0.068433333 | P12: {=IF(INDIRECT("'"&A$12&"'!"&"B17") ="",INDIRECT("'"&A$12&"'!"&"C17"),INDIRECT("'"&A$12&"'!"&"B17"))} -> 39.79 | Q12: {=IFERROR(AVERAGE(INDIRECT("'"&A$12&"'!"&"B17:F17")),0)} -> 39.786667 | R12: {=IF(INDIRECT("'"&A$12&"'!"&"B10") ="",INDIRECT("'"&A$12&"'!"&"C10"),INDIRECT("'"&A$12&"'!"&"B10"))} -> 0.6 | S12: {=IFERROR(AVERAGE(INDIRECT("'"&A$12&"'!"&"B10:F10")),0)} -> 0.6 | T12: =R12*4 -> 2.4 | U12: =S12*4 -> 2.4 | V12: {=IF(INDIRECT("'"&A$12&"'!"&"B15") ="",INDIRECT("'"&A$12&"'!"&"C15"),INDIRECT("'"&A$12&"'!"&"B15"))} -> 0.0926 | W12: {=IFERROR(AVERAGE(INDIRECT("'"&A$12&"'!"&"B15:F15")),"")} -> 0.0885 | X12: {=IF(INDIRECT("'"&A$12&"'!"&"B5") ="",INDIRECT("'"&A$12&"'!"&"c5"),INDIRECT("'"&A$12&"'!"&"B5"))} -> 0.753 | Y12: {=IFERROR(AVERAGE(INDIRECT("'"&A$12&"'!"&"B5:F5")),0)} -> 0.78515 | Z12: {=IF(INDIRECT("'"&A$12&"'!"&"B7") ="",INDIRECT("'"&A$12&"'!"&"C7"),INDIRECT("'"&A$12&"'!"&"B7"))} -> 0.5305 | AA12: {=IFERROR(AVERAGE(INDIRECT("'"&A$12&"'!"&"B7:F7")),0)} -> 0.5749 | AB12: =IFERROR((G12/(L12/E12))-1,"") -> 0.22574892 | AC12: =IFERROR(U12/G12,"") -> 0.087783467 | AD12: =IFERROR(IF(M12-L12=0,"",M12-L12),"") -> 503.5269 | AE12: =IFERROR(IF(M12-K12=0,"",M12-K12),"") -> 535 | AF12: =IF(P12>0,IFERROR((P12/G12)-1,""),"") -> 0.45537674 | AG12: =IFERROR(T12/G12,"") -> 0.087783467 | AI12: {=IF(INDIRECT("'"&A$12&"'!"&"B16") ="",INDIRECT("'"&A$12&"'!"&"C16"),INDIRECT("'"&A$12&"'!"&"B16"))} -> 0.09 | AJ12: {=AVERAGE(INDIRECT("'"&A$12&"'!"&"B16:F16"))} -> 0.092366667 | AK12: =AVERAGE(AG12:AJ12) -> 0.090050045 | AL12: =IFERROR(IF(R12*E12=0,"",R12*E12),"") -> 60 | AM12: =IFERROR(IF(S12*E12=0,"",S12*E12),"") -> 60 | AN12: =IFERROR(IF(T12*E12=0,"",T12*E12),"") -> 240 | AO12: =IFERROR(IF(U12*E12=0,"",U12*E12),"") -> 240 | AP12: =IF(AC12*D12=0,"",AC12*D12) -> 0.024938485
A13: =FUNO11!A1 -> FUNO11 | B13: FIBRA UNO | C13: {=IF(INDIRECT("'"&A$13&"'!"&"B10") ="",INDIRECT("'"&A$13&"'!"&"C1"),INDIRECT("'"&A$13&"'!"&"B1"))} -> 2023 Q1 | D13: =IFERROR(E13/SUM(E13:E35),0) -> 0.17045455 | E13: =SUMIFS(COMPRAS!B:B,COMPRAS!A:A,B13) -> 60 | F13: =IFERROR(AVERAGEIFS(COMPRAS!C:C,COMPRAS!A:A,B13),0) -> 24.48 | G13: =IFERROR(__xludf.DUMMYFUNCTION("GOOGLEFINANCE(A13,""price"")"),29.73) -> 29.73 | H13: =IFERROR(__xludf.DUMMYFUNCTION("(GOOGLEFINANCE(A13,""high52"") + GOOGLEFINANCE(A13,""low52""))/2"),28.21) -> 28.21 | I13: =IFERROR(__xludf.DUMMYFUNCTION("GOOGLEFINANCE(A13,""changepct"")"),-0.03) -> -0.03 | J13: =IFERROR(__xludf.DUMMYFUNCTION("GOOGLEFINANCE(A13,""volume"")"),2305818.0) -> 2305818 | K13: =E13*F13 -> 1468.8 | L13: =IFERROR(SUMIFS(COMPRAS!G:G,COMPRAS!A:A,B13),0) -> 1472.0693 | M13: =E13*G13 -> 1783.8 | N13: {=IF(INDIRECT("'"&A$13&"'!"&"B12") ="",INDIRECT("'"&A$13&"'!"&"C12"),INDIRECT("'"&A$13&"'!"&"B12"))} -> 0.0636 | O13: {=IFERROR(AVERAGE(INDIRECT("'"&A$13&"'!"&"B12:F12")),"")} -> 0.062733333 | P13: {=IF(INDIRECT("'"&A$13&"'!"&"B17") ="",INDIRECT("'"&A$13&"'!"&"C17"),INDIRECT("'"&A$13&"'!"&"B17"))} -> 50.02 | Q13: {=IFERROR(AVERAGE(INDIRECT("'"&A$13&"'!"&"B17:F17")),0)} -> 48.543333 | R13: {=IF(INDIRECT("'"&A$13&"'!"&"B10") ="",INDIRECT("'"&A$13&"'!"&"C10"),INDIRECT("'"&A$13&"'!"&"B10"))} -> 0.389133 | S13: {=IFERROR(AVERAGE(INDIRECT("'"&A$13&"'!"&"B10:F10")),0)} -> 0.6180646 | T13: =R13*4 -> 1.556532 | U13: =S13*4 -> 2.4722584 | V13: {=IF(INDIRECT("'"&A$13&"'!"&"B15") ="",INDIRECT("'"&A$13&"'!"&"C15"),INDIRECT("'"&A$13&"'!"&"B15"))} -> 0.4 | W13: {=IFERROR(AVERAGE(INDIRECT("'"&A$13&"'!"&"B15:F15")),"")} -> 0.4163 | X13: {=IF(INDIRECT("'"&A$13&"'!"&"B5") ="",INDIRECT("'"&A$13&"'!"&"C5"),INDIRECT("'"&A$13&"'!"&"B5"))} -> 0.784 | Y13: {=IFERROR(AVERAGE(INDIRECT("'"&A$13&"'!"&"B5:F5")),0)} -> 0.78674 | Z13: {=IF(INDIRECT("'"&A$13&"'!"&"B7") ="",INDIRECT("'"&A$13&"'!"&"C7"),INDIRECT("'"&A$13&"'!"&"B7"))} -> 0.348 | AA13: {=IFERROR(AVERAGE(INDIRECT("'"&A$13&"'!"&"B7:F7")),0)} -> 0.37968 | AB13: =IFERROR((G13/(L13/E13))-1,"") -> 0.21176359 | AC13: =IFERROR(U13/G13,"") -> 0.083157027 | AD13: =IFERROR(IF(M13-L13=0,"",M13-L13),"") -> 311.73069 | AE13: =IFERROR(IF(M13-K13=0,"",M13-K13),"") -> 315 | AF13: =IF(P13>0,IFERROR((P13/G13)-1,""),"") -> 0.68247561 | AG13: =IFERROR(T13/G13,"") -> 0.0523556 | AI13: {=IF(INDIRECT("'"&A$13&"'!"&"B16") ="",INDIRECT("'"&A$13&"'!"&"C16"),INDIRECT("'"&A$13&"'!"&"B16"))} -> 0.0607 | AJ13: {=AVERAGE(INDIRECT("'"&A$13&"'!"&"B16:F16"))} -> 0.071766667 | AK13: =AVERAGE(AG13:AJ13) -> 0.061607422 | AL13: =IFERROR(IF(R13*E13=0,"",R13*E13),"") -> 23.34798 | AM13: =IFERROR(IF(S13*E13=0,"",S13*E13),"") -> 37.083876 | AN13: =IFERROR(IF(T13*E13=0,"",T13*E13),"") -> 93.39192 | AO13: =IFERROR(IF(U13*E13=0,"",U13*E13),"") -> 148.3355 | AP13: =IF(AC13*D13=0,"",AC13*D13) -> 0.014174493
A14: =FMTY14!A1 -> FMTY14 | B14: FIBRA MONTEREY | C14: {=IF(INDIRECT("'"&A$14&"'!"&"B10") ="",INDIRECT("'"&A$14&"'!"&"C1"),INDIRECT("'"&A$14&"'!"&"B1"))} -> 2023 Q1 | D14: =IFERROR(E14/SUM(E13:E35),0) -> 0.4375 | E14: =SUMIFS(COMPRAS!B:B,COMPRAS!A:A,B14) -> 154 | F14: =IFERROR(AVERAGEIFS(COMPRAS!C:C,COMPRAS!A:A,B14),0) -> 11.921 | G14: =IFERROR(__xludf.DUMMYFUNCTION("GOOGLEFINANCE(A14,""price"")"),14.61) -> 14.61 | H14: =IFERROR(__xludf.DUMMYFUNCTION("(GOOGLEFINANCE(A14,""high52"") + GOOGLEFINANCE(A14,""low52""))/2"),14.395) -> 14.395 | I14: =IFERROR(__xludf.DUMMYFUNCTION("GOOGLEFINANCE(A14,""changepct"")"),0.69) -> 0.69 | J14: =IFERROR(__xludf.DUMMYFUNCTION("GOOGLEFINANCE(A14,""volume"")"),6200822.0) -> 6200822 | K14: =E14*F14 -> 1835.834 | L14: =IFERROR(SUMIFS(COMPRAS!G:G,COMPRAS!A:A,B14),0) -> 1798.4981 | M14: =E14*G14 -> 2249.94 | N14: {=IF(INDIRECT("'"&A$14&"'!"&"B12")="",INDIRECT("'"&A$14&"'!"&"C12"),INDIRECT("'"&A$14&"'!"&"B12"))} -> 0.0475 | O14: {=IFERROR(AVERAGE(INDIRECT("'"&A$14&"'!"&"B12:F12")),"")} -> 0.064433333 | P14: {=IF(INDIRECT("'"&A$14&"'!"&"B17") ="",INDIRECT("'"&A$14&"'!"&"C17"),INDIRECT("'"&A$14&"'!"&"B17"))} -> 12.08 | Q14: {=IFERROR(AVERAGE(INDIRECT("'"&A$14&"'!"&"B17:F17")),0)} -> 12.773333 | R14: {=IF(INDIRECT("'"&A$14&"'!"&"B10") ="",INDIRECT("'"&A$14&"'!"&"C10"),INDIRECT("'"&A$14&"'!"&"B10"))} -> 0 | S14: {=IFERROR(AVERAGE(INDIRECT("'"&A$14&"'!"&"B10:F10")),0)} -> 0.2125466 | T14: =R14*4 -> 0 | U14: =S14*4 -> 0.8501864 | V14: {=IF(INDIRECT("'"&A$14&"'!"&"B15") ="",INDIRECT("'"&A$14&"'!"&"C15"),INDIRECT("'"&A$14&"'!"&"B15"))} -> 0.3685 | W14: {=IFERROR(AVERAGE(INDIRECT("'"&A$14&"'!"&"B15:F15")),"")} -> 0.2816 | X14: {=IF(INDIRECT("'"&A$14&"'!"&"B5") ="",INDIRECT("'"&A$14&"'!"&"C5"),INDIRECT("'"&A$14&"'!"&"B5"))} -> 0.8872 | Y14: {=IFERROR(AVERAGE(INDIRECT("'"&A$14&"'!"&"B5:F5")),0)} -> 0.88378 | Z14: {=IF(INDIRECT("'"&A$14&"'!"&"B7") ="",INDIRECT("'"&A$14&"'!"&"C7"),INDIRECT("'"&A$14&"'!"&"B7"))} -> 0.9334 | AA14: {=IFERROR(AVERAGE(INDIRECT("'"&A$14&"'!"&"B7:F7")),0)} -> 0.77808 | AB14: =IFERROR((G14/(L14/E14))-1,"") -> 0.25101049 | AC14: =IFERROR(U14/G14,"") -> 0.058192088 | AD14: =IFERROR(IF(M14-L14=0,"",M14-L14),"") -> 451.44189 | AE14: =IFERROR(IF(M14-K14=0,"",M14-K14),"") -> 414.106 | AF14: =IF(P14>0,IFERROR((P14/G14)-1,""),"") -> -0.17316906 | AG14: =IFERROR(T14/G14,"") -> 0 | AI14: {=IF(INDIRECT("'"&A$14&"'!"&"B16") ="",INDIRECT("'"&A$14&"'!"&"C16"),INDIRECT("'"&A$14&"'!"&"B16"))} -> 0.0735 | AJ14: {=AVERAGE(INDIRECT("'"&A$14&"'!"&"B16:F16"))} -> 0.0777 | AK14: =AVERAGE(AG14:AJ14) -> 0.0504 | AL14: =IFERROR(IF(R14*E14=0,"",R14*E14),"") | AM14: =IFERROR(IF(S14*E14=0,"",S14*E14),"") -> 32.732176 | AN14: =IFERROR(IF(T14*E14=0,"",T14*E14),"") | AO14: =IFERROR(IF(U14*E14=0,"",U14*E14),"") -> 130.92871 | AP14: =IF(AC14*D14=0,"",AC14*D14) -> 0.025459038
A15: FNOVA17 | B15: FIBRA NOVA | C15: {=IF(INDIRECT("'"&A$15&"'!"&"B10") ="",INDIRECT("'"&A$15&"'!"&"C1"),INDIRECT("'"&A$15&"'!"&"B1"))} -> 2023 Q1 | D15: =IFERROR(E15/SUM(E13:E35),0) -> 0.21022727 | E15: =SUMIFS(COMPRAS!B:B,COMPRAS!A:A,B15) -> 74 | F15: =IFERROR(AVERAGEIFS(COMPRAS!C:C,COMPRAS!A:A,B15),0) -> 29.7325 | G15: =IFERROR(__xludf.DUMMYFUNCTION("GOOGLEFINANCE(A15,""price"")"),"#N/A") -> #N/A | H15: =IFERROR(__xludf.DUMMYFUNCTION("(GOOGLEFINANCE(A15,""high52"") + GOOGLEFINANCE(A15,""low52""))/2"),"#N/A") -> #N/A | I15: =IFERROR(__xludf.DUMMYFUNCTION("GOOGLEFINANCE(A15,""changepct"")"),"#N/A") -> #N/A | J15: =IFERROR(__xludf.DUMMYFUNCTION("GOOGLEFINANCE(A15,""volume"")"),"#N/A") -> #N/A | K15: =E15*F15 -> 2200.205 | L15: =IFERROR(SUMIFS(COMPRAS!G:G,COMPRAS!A:A,B15),0) -> 2168.2007 | M15: =E15*G15 -> #N/A | N15: {=IF(INDIRECT("'"&A$15&"'!"&"B12") ="",INDIRECT("'"&A$15&"'!"&"C12"),INDIRECT("'"&A$15&"'!"&"B12"))} -> 0.0762 | O15: {=IFERROR(AVERAGE(INDIRECT("'"&A$15&"'!"&"B12:F12")),"")} -> 0.076833333 | P15: {=IF(INDIRECT("'"&A$15&"'!"&"B17") ="",INDIRECT("'"&A$15&"'!"&"C17"),INDIRECT("'"&A$15&"'!"&"B17"))} -> 20.41 | Q15: {=IFERROR(AVERAGE(INDIRECT("'"&A$15&"'!"&"B17:F17")),0)} -> 21.346667 | R15: {=IF(INDIRECT("'"&A$15&"'!"&"B10") ="",INDIRECT("'"&A$15&"'!"&"C10"),INDIRECT("'"&A$15&"'!"&"B10"))} -> 0.5797 | S15: {=IFERROR(AVERAGE(INDIRECT("'"&A$15&"'!"&"B10:F10")),0)} -> 0.4594304 | T15: =R15*4 -> 2.3188 | U15: =S15*4 -> 1.8377216 | V15: {=IF(INDIRECT("'"&A$15&"'!"&"B15") ="",INDIRECT("'"&A$15&"'!"&"C15"),INDIRECT("'"&A$15&"'!"&"B15"))} -> 0.4783 | W15: {=IFERROR(AVERAGE(INDIRECT("'"&A$15&"'!"&"B15:F15")),"")} -> 0.46003333 | X15: {=IF(INDIRECT("'"&A$15&"'!"&"B5") ="",INDIRECT("'"&A$15&"'!"&"C5"),INDIRECT("'"&A$15&"'!"&"B5"))} -> 0.9727 | Y15: {=IFERROR(AVERAGE(INDIRECT("'"&A$15&"'!"&"B5:F5")),0)} -> 0.97156 | Z15: {=IF(INDIRECT("'"&A$15&"'!"&"B7") ="",INDIRECT("'"&A$15&"'!"&"C7"),INDIRECT("'"&A$15&"'!"&"B7"))} -> 0.8104 | AA15: {=IFERROR(AVERAGE(INDIRECT("'"&A$15&"'!"&"B7:F7")),0)} -> 0.80972 | AB15: =IFERROR((G15/(L15/E15))-1,"") | AC15: =IFERROR(U15/G15,"") | AD15: =IFERROR(IF(M15-L15=0,"",M15-L15),"") | AE15: =IFERROR(IF(M15-K15=0,"",M15-K15),"") | AF15: =IF(P15>0,IFERROR((P15/G15)-1,""),"") | AG15: =IFERROR(T15/G15,"") | AI15: {=IF(INDIRECT("'"&A$15&"'!"&"B16") ="",INDIRECT("'"&A$15&"'!"&"C16"),INDIRECT("'"&A$15&"'!"&"B16"))} -> 0.0756 | AJ15: {=IFERROR(AVERAGE(INDIRECT("'"&A$15&"'!"&"B16:F16")),"")} -> 0.070866667 | AK15: =AVERAGE(AG15:AJ15) -> 0.073233333 | AL15: =IFERROR(IF(R15*E15=0,"",R15*E15),"") -> 42.8978 | AM15: =IFERROR(IF(S15*E15=0,"",S15*E15),"") -> 33.99785 | AN15: =IFERROR(IF(T15*E15=0,"",T15*E15),"") -> 171.5912 | AO15: =IFERROR(IF(U15*E15=0,"",U15*E15),"") -> 135.9914 | AP15: =IF(AC15*D15=0,"",AC15*D15)
A16: =FIBRAMQ12!A1 -> FIBRAMQ12 | B16: FIBRA MACQUARIE | C16: {=IF(INDIRECT("'"&A$16&"'!"&"B10") ="",INDIRECT("'"&A$16&"'!"&"C1"),INDIRECT("'"&A$16&"'!"&"B1"))} -> 2023 Q1 | D16: =IFERROR(E16/SUM(E13:E35),0) -> 0.090909091 | E16: =SUMIFS(COMPRAS!B:B,COMPRAS!A:A,B16) -> 32 | F16: =IFERROR(AVERAGEIFS(COMPRAS!C:C,COMPRAS!A:A,B16),0) -> 28.745714 | G16: =IFERROR(__xludf.DUMMYFUNCTION("GOOGLEFINANCE(A16,""price"")"),43.51) -> 43.51 | H16: =IFERROR(__xludf.DUMMYFUNCTION("(GOOGLEFINANCE(A16,""high52"") + GOOGLEFINANCE(A16,""low52""))/2"),37.415) -> 37.415 | I16: =IFERROR(__xludf.DUMMYFUNCTION("GOOGLEFINANCE(A16,""changepct"")"),0.97) -> 0.97 | J16: =IFERROR(__xludf.DUMMYFUNCTION("GOOGLEFINANCE(A16,""volume"")"),814553.0) -> 814553 | K16: =E16*F16 -> 919.86286 | L16: =IFERROR(SUMIFS(COMPRAS!G:G,COMPRAS!A:A,B16),0) -> 921.52791 | M16: =E16*G16 -> 1392.32 | N16: {=IF(INDIRECT("'"&A$16&"'!"&"B12") ="",INDIRECT("'"&A$16&"'!"&"C12"),INDIRECT("'"&A$16&"'!"&"B12"))} -> 0.0693 | O16: {=IFERROR(AVERAGE(INDIRECT("'"&A$16&"'!"&"B12:F12")),"")} -> 0.06895 | P16: {=IF(INDIRECT("'"&A$16&"'!"&"B17") ="",INDIRECT("'"&A$16&"'!"&"C17"),INDIRECT("'"&A$16&"'!"&"B17"))} -> 45.39 | Q16: {=IFERROR(AVERAGE(INDIRECT("'"&A$16&"'!"&"B17:F17")),0)} -> 45.81 | R16: {=IF(INDIRECT("'"&A$16&"'!"&"B10") ="",INDIRECT("'"&A$16&"'!"&"C10"),INDIRECT("'"&A$16&"'!"&"B10"))} -> 0.525 | S16: {=IFERROR(AVERAGE(INDIRECT("'"&A$16&"'!"&"B10:F10")),0)} -> 0.6807648 | T16: =R16*4 -> 2.1 | U16: =S16*4 -> 2.7230592 | V16: {=IF(INDIRECT("'"&A$16&"'!"&"B15") ="",INDIRECT("'"&A$16&"'!"&"C15"),INDIRECT("'"&A$16&"'!"&"B15"))} -> 0.3167 | W16: {=IFERROR(AVERAGE(INDIRECT("'"&A$16&"'!"&"B15:F15")),"")} -> 0.3185 | X16: {=IF(INDIRECT("'"&A$16&"'!"&"B5") ="",INDIRECT("'"&A$16&"'!"&"C5"),INDIRECT("'"&A$16&"'!"&"B5"))} -> 0.9013 | Y16: {=IFERROR(AVERAGE(INDIRECT("'"&A$16&"'!"&"B5:F5")),0)} -> 0.920675 | Z16: {=IF(INDIRECT("'"&A$16&"'!"&"B7") ="",INDIRECT("'"&A$16&"'!"&"C7"),INDIRECT("'"&A$16&"'!"&"B7"))} -> 0.6011 | AA16: {=IFERROR(AVERAGE(INDIRECT("'"&A$16&"'!"&"B7:F7")),0)} -> 0.618525 | AB16: =IFERROR((G16/(L16/E16))-1,"") -> 0.51088208 | AC16: =IFERROR(U16/G16,"") -> 0.062584675 | AD16: =IFERROR(IF(M16-L16=0,"",M16-L16),"") -> 470.79209 | AE16: =IFERROR(IF(M16-K16=0,"",M16-K16),"") -> 472.45714 | AF16: =IF(P16>0,IFERROR((P16/G16)-1,""),"") -> 0.043208458 | AG16: =IFERROR(T16/G16,"") -> 0.048264767 | AI16: {=IF(INDIRECT("'"&A$16&"'!"&"B16") ="",INDIRECT("'"&A$16&"'!"&"C16"),INDIRECT("'"&A$16&"'!"&"B16"))} -> 0.0643 | AJ16: {=AVERAGE(INDIRECT("'"&A$16&"'!"&"B16:F16"))} -> 0.06805 | AK16: =AVERAGE(AG16:AJ16) -> 0.060204922 | AL16: =IFERROR(IF(R16*E16=0,"",R16*E16),"") -> 16.8 | AM16: =IFERROR(IF(S16*E16=0,"",S16*E16),"") -> 21.784474 | AN16: =IFERROR(IF(T16*E16=0,"",T16*E16),"") -> 67.2 | AO16: =IFERROR(IF(U16*E16=0,"",U16*E16),"") -> 87.137894 | AP16: =IF(AC16*D16=0,"",AC16*D16) -> 0.0056895159
A17: FIBRAUP18 | B17: FIBRA UPSITE | C17: {=IF(INDIRECT("'"&A$17&"'!"&"B10") ="",INDIRECT("'"&A$17&"'!"&"C1"),INDIRECT("'"&A$17&"'!"&"B1"))} -> 2022 Q4 | D17: =IFERROR(E17/SUM(E13:E35),0) -> 0 | E17: =SUMIFS(COMPRAS!B:B,COMPRAS!A:A,B17) -> 0 | F17: =IFERROR(AVERAGEIFS(COMPRAS!C:C,COMPRAS!A:A,B17),0) -> 0 | G17: =IFERROR(__xludf.DUMMYFUNCTION("GOOGLEFINANCE(A17,""price"")"),38.8) -> 38.8 | H17: =IFERROR(__xludf.DUMMYFUNCTION("(GOOGLEFINANCE(A17,""high52"") + GOOGLEFINANCE(A17,""low52""))/2"),36.0) -> 36 | I17: =IFERROR(__xludf.DUMMYFUNCTION("GOOGLEFINANCE(A17,""changepct"")"),0.0) -> 0 | J17: =IFERROR(__xludf.DUMMYFUNCTION("GOOGLEFINANCE(A17,""volume"")"),17.0) -> 17 | K17: =E17*F17 -> 0 | L17: =IFERROR(SUMIFS(COMPRAS!G:G,COMPRAS!A:A,B17),0) -> 0 | M17: =E17*G17 -> 0 | N17: {=IF(INDIRECT("'"&A$17&"'!"&"B12") ="",INDIRECT("'"&A$17&"'!"&"C12"),INDIRECT("'"&A$17&"'!"&"B12"))} -> 0.0427 | O17: {=IFERROR(AVERAGE(INDIRECT("'"&A$17&"'!"&"B12:F12")),"")} -> 0.0409 | P17: {=IF(INDIRECT("'"&A$17&"'!"&"B17") ="",INDIRECT("'"&A$17&"'!"&"C17"),INDIRECT("'"&A$17&"'!"&"B17"))} -> 53.82 | Q17: {=IFERROR(AVERAGE(INDIRECT("'"&A$17&"'!"&"B17:F17")),0)} -> 53.215 | R17: {=IF(INDIRECT("'"&A$17&"'!"&"B10") ="",INDIRECT("'"&A$17&"'!"&"C10"),INDIRECT("'"&A$17&"'!"&"B10"))} -> 0 | S17: {=IFERROR(AVERAGE(INDIRECT("'"&A$17&"'!"&"B10:F10")),0)} -> 0 | T17: =R17*4 -> 0 | U17: =S17*4 -> 0 | V17: {=IF(INDIRECT("'"&A$17&"'!"&"B15") ="",INDIRECT("'"&A$17&"'!"&"C15"),INDIRECT("'"&A$17&"'!"&"B15"))} -> 0.2454 | W17: {=IFERROR(AVERAGE(INDIRECT("'"&A$17&"'!"&"B15:F15")),"")} -> 0.25075 | X17: {=IF(INDIRECT("'"&A$17&"'!"&"B5") ="",INDIRECT("'"&A$17&"'!"&"C5"),INDIRECT("'"&A$17&"'!"&"B5"))} -> 0.8022 | Y17: {=IFERROR(AVERAGE(INDIRECT("'"&A$17&"'!"&"B5:F5")),0)} -> 0.811475 | Z17: {=IF(INDIRECT("'"&A$17&"'!"&"B7") ="",INDIRECT("'"&A$17&"'!"&"C7"),INDIRECT("'"&A$17&"'!"&"B7"))} -> 0.1631 | AA17: {=IFERROR(AVERAGE(INDIRECT("'"&A$17&"'!"&"B7:F7")),0)} -> -0.818725 | AB17: =IFERROR((G17/(L17/E17))-1,"") | AC17: =IFERROR(U17/G17,"") -> 0 | AD17: =IFERROR(IF(M17-L17=0,"",M17-L17),"") | AE17: =IFERROR(IF(M17-K17=0,"",M17-K17),"") | AF17: =IF(P17>0,IFERROR((P17/G17)-1,""),"") -> 0.3871134 | AG17: =IFERROR(T17/G17,"") -> 0 | AI17: {=IF(INDIRECT("'"&A$17&"'!"&"B16") ="",INDIRECT("'"&A$17&"'!"&"C16"),INDIRECT("'"&A$17&"'!"&"B16"))} -> 0 | AJ17: {=IFERROR(AVERAGE(INDIRECT("'"&A$17&"'!"&"B16:F16")),"")} -> 0 | AK17: =AVERAGE(AG17:AJ17) -> 0 | AL17: =IFERROR(IF(R17*E17=0,"",R17*E17),"") | AM17: =IFERROR(IF(S17*E17=0,"",S17*E17),"") | AN17: =IFERROR(IF(T17*E17=0,"",T17*E17),"") | AO17: =IFERROR(IF(U17*E17=0,"",U17*E17),"") | AP17: =IF(AC17*D17=0,"",AC17*D17)
A18: FVIA16 | B18: FIBRA VIA | C18: {=IF(INDIRECT("'"&A$18&"'!"&"B10") ="",INDIRECT("'"&A$18&"'!"&"C1"),INDIRECT("'"&A$18&"'!"&"B1"))} -> 2022 Q4 | D18: =IFERROR(E18/SUM(E13:E35),0) -> 0.039772727 | E18: =SUMIFS(COMPRAS!B:B,COMPRAS!A:A,B18) -> 14 | F18: =IFERROR(AVERAGEIFS(COMPRAS!C:C,COMPRAS!A:A,B18),0) -> 25.45 | G18: =IFERROR(__xludf.DUMMYFUNCTION("GOOGLEFINANCE(A18,""price"")"),19.5) -> 19.5 | H18: =IFERROR(__xludf.DUMMYFUNCTION("IFERROR(G18,(GOOGLEFINANCE(A18,""high52"") + GOOGLEFINANCE(A18,""low52""))/2)"),19.5) -> 19.5 | I18: =IFERROR(__xludf.DUMMYFUNCTION("GOOGLEFINANCE(A18,""changepct"")"),2.63) -> 2.63 | J18: =IFERROR(__xludf.DUMMYFUNCTION("GOOGLEFINANCE(A18,""volume"")"),706.0) -> 706 | K18: =E18*F18 -> 356.3 | L18: =IFERROR(SUMIFS(COMPRAS!G:G,COMPRAS!A:A,B18),0) -> 357.40453 | M18: =E18*G18 -> 273 | N18: {=IF(INDIRECT("'"&A$18&"'!"&"B12") ="",INDIRECT("'"&A$18&"'!"&"C12"),INDIRECT("'"&A$18&"'!"&"B12"))} | O18: {=IFERROR(AVERAGE(INDIRECT("'"&A$18&"'!"&"B12:F12")),"")} | P18: {=IF(INDIRECT("'"&A$18&"'!"&"B17") ="",INDIRECT("'"&A$18&"'!"&"C17"),INDIRECT("'"&A$18&"'!"&"B17"))} | Q18: {=IFERROR(AVERAGE(INDIRECT("'"&A$18&"'!"&"B17:F17")),"")} | R18: {=IF(INDIRECT("'"&A$18&"'!"&"B10") ="",INDIRECT("'"&A$18&"'!"&"C10"),INDIRECT("'"&A$18&"'!"&"B10"))} -> 0.480904 | S18: {=IFERROR(AVERAGE(INDIRECT("'"&A$18&"'!"&"B10:F10")),"")} -> 0.4712025 | T18: =R18*4 -> 1.923616 | U18: =S18*4 -> 1.88481 | V18: {=IF(INDIRECT("'"&A$18&"'!"&"B15") ="",INDIRECT("'"&A$18&"'!"&"C15"),INDIRECT("'"&A$18&"'!"&"B15"))} | W18: {=IFERROR(AVERAGE(INDIRECT("'"&A$18&"'!"&"B15:F15")),"")} | X18: {=IF(INDIRECT("'"&A$18&"'!"&"B5") ="",INDIRECT("'"&A$18&"'!"&"C5"),INDIRECT("'"&A$18&"'!"&"B5"))} | Y18: {=IFERROR(AVERAGE(INDIRECT("'"&A$18&"'!"&"B5:F5")),"")} | Z18: {=IF(INDIRECT("'"&A$18&"'!"&"B7") ="",INDIRECT("'"&A$18&"'!"&"C7"),INDIRECT("'"&A$18&"'!"&"B7"))} | AA18: {=IFERROR(AVERAGE(INDIRECT("'"&A$18&"'!"&"B7:F7")),"")} | AB18: =IFERROR((G18/(L18/E18))-1,"") -> -0.23615965 | AC18: =IFERROR(U18/G18,"") -> 0.096656923 | AD18: =IFERROR(IF(M18-L18=0,"",M18-L18),"") -> -84.40453 | AE18: =IFERROR(IF(M18-K18=0,"",M18-K18),"") -> -83.3 | AF18: =IF(P18>0,IFERROR((P18/G18)-1,""),"") | AG18: =IFERROR(T18/G18,"") -> 0.098646974 | AI18: {=IF(INDIRECT("'"&A$18&"'!"&"B16") ="",INDIRECT("'"&A$18&"'!"&"C16"),INDIRECT("'"&A$18&"'!"&"B16"))} | AJ18: {=IFERROR(AVERAGE(INDIRECT("'"&A$18&"'!"&"B16:F16")),"")} | AK18: =AVERAGE(AG18:AJ18) -> 0.098646974 | AL18: =IFERROR(IF(R18*E18=0,"",R18*E18),"") -> 6.732656 | AM18: =IFERROR(IF(S18*E18=0,"",S18*E18),"") -> 6.596835 | AN18: =IFERROR(IF(T18*E18=0,"",T18*E18),"") -> 26.930624 | AO18: =IFERROR(IF(U18*E18=0,"",U18*E18),"") -> 26.38734 | AP18: =IF(AC18*D18=0,"",AC18*D18) -> 0.0038443094
A19: FSHOP13 | B19: FIBRA SHOP | C19: {=IF(INDIRECT("'"&A$19&"'!"&"B10") ="",INDIRECT("'"&A$19&"'!"&"C1"),INDIRECT("'"&A$19&"'!"&"B1"))} -> 2023 Q1 | D19: =IFERROR(E19/SUM(E13:E35),0) -> 0.036931818 | E19: =SUMIFS(COMPRAS!B:B,COMPRAS!A:A,B19) -> 13 | F19: =IFERROR(AVERAGEIFS(COMPRAS!C:C,COMPRAS!A:A,B19),0) -> 6.0528571 | G19: =IFERROR(__xludf.DUMMYFUNCTION("GOOGLEFINANCE(A19,""price"")"),12.49) -> 12.49 | H19: =IFERROR(__xludf.DUMMYFUNCTION("(GOOGLEFINANCE(A19,""high52"") + GOOGLEFINANCE(A19,""low52""))/2"),10.350000000000001) -> 10.35 | I19: =IFERROR(__xludf.DUMMYFUNCTION("GOOGLEFINANCE(A19,""changepct"")"),-0.4) -> -0.4 | J19: =IFERROR(__xludf.DUMMYFUNCTION("GOOGLEFINANCE(A19,""volume"")"),210011.0) -> 210011 | K19: =E19*F19 -> 78.687143 | L19: =IFERROR(SUMIFS(COMPRAS!G:G,COMPRAS!A:A,B19),0) -> 78.452451 | M19: =E19*G19 -> 162.37 | N19: {=IF(INDIRECT("'"&A$19&"'!"&"B12") ="",INDIRECT("'"&A$19&"'!"&"C12"),INDIRECT("'"&A$19&"'!"&"B12"))} -> 0.0695 | O19: {=IFERROR(AVERAGE(INDIRECT("'"&A$19&"'!"&"B12:F12")),"")} -> 0.067366667 | P19: {=IF(INDIRECT("'"&A$19&"'!"&"B17") ="",INDIRECT("'"&A$19&"'!"&"C17"),INDIRECT("'"&A$19&"'!"&"B17"))} -> 28.08 | Q19: {=IFERROR(AVERAGE(INDIRECT("'"&A$19&"'!"&"B17:F17")),0)} -> 27.21 | R19: {=IF(INDIRECT("'"&A$19&"'!"&"B10") ="",INDIRECT("'"&A$19&"'!"&"C10"),INDIRECT("'"&A$19&"'!"&"B10"))} -> 0 | S19: {=IFERROR(AVERAGE(INDIRECT("'"&A$19&"'!"&"B10:F10")),0)} -> 0.0218618 | T19: =R19*4 -> 0 | U19: =S19*4 -> 0.0874472 | V19: {=IF(INDIRECT("'"&A$19&"'!"&"B15") ="",INDIRECT("'"&A$19&"'!"&"C15"),INDIRECT("'"&A$19&"'!"&"B15"))} -> 0.4535 | W19: {=IFERROR(AVERAGE(INDIRECT("'"&A$19&"'!"&"B15:F15")),"")} -> 0.44513333 | X19: {=IF(INDIRECT("'"&A$19&"'!"&"B5") ="",INDIRECT("'"&A$19&"'!"&"C5"),INDIRECT("'"&A$19&"'!"&"B5"))} -> 0.7886 | Y19: {=IFERROR(AVERAGE(INDIRECT("'"&A$19&"'!"&"B5:F5")),0)} -> 0.77588 | Z19: {=IF(INDIRECT("'"&A$19&"'!"&"B7") ="",INDIRECT("'"&A$19&"'!"&"C7"),INDIRECT("'"&A$19&"'!"&"B7"))} -> 0.1722 | AA19: {=IFERROR(AVERAGE(INDIRECT("'"&A$19&"'!"&"B7:F7")),0)} -> 0.24642 | AB19: =IFERROR((G19/(L19/E19))-1,"") -> 1.0696613 | AC19: =IFERROR(U19/G19,"") -> 0.0070013771 | AD19: =IFERROR(IF(M19-L19=0,"",M19-L19),"") -> 83.917549 | AE19: =IFERROR(IF(M19-K19=0,"",M19-K19),"") -> 83.682857 | AF19: =IF(P19>0,IFERROR((P19/G19)-1,""),"") -> 1.2481986 | AG19: =IFERROR(T19/G19,"") -> 0 | AI19: {=IF(INDIRECT("'"&A$19&"'!"&"B16") ="",INDIRECT("'"&A$19&"'!"&"C16"),INDIRECT("'"&A$19&"'!"&"B16"))} -> 0 | AJ19: {=AVERAGE(INDIRECT("'"&A$19&"'!"&"B16:F16"))} -> 0.034366667 | AK19: =AVERAGE(AG19:AJ19) -> 0.011455556 | AL19: =IFERROR(IF(R19*E19=0,"",R19*E19),"") | AM19: =IFERROR(IF(S19*E19=0,"",S19*E19),"") -> 0.2842034 | AN19: =IFERROR(IF(T19*E19=0,"",T19*E19),"") | AO19: =IFERROR(IF(U19*E19=0,"",U19*E19),"") -> 1.1368136 | AP19: =IF(AC19*D19=0,"",AC19*D19) -> 0.00025857359
A20: FINN13 | B20: FIBRA INN | C20: {=IF(INDIRECT("'"&A$20&"'!"&"B10") ="",INDIRECT("'"&A$20&"'!"&"C1"),INDIRECT("'"&A$20&"'!"&"B1"))} -> 2023 Q1 | D20: =IFERROR(E20/SUM(E13:E35),0) -> 0.011363636 | E20: =SUMIFS(COMPRAS!B:B,COMPRAS!A:A,B20) -> 4 | F20: =IFERROR(AVERAGEIFS(COMPRAS!C:C,COMPRAS!A:A,B20),0) -> 5.71 | G20: =IFERROR(__xludf.DUMMYFUNCTION("GOOGLEFINANCE(A20,""price"")"),5.1) -> 5.1 | H20: =IFERROR(__xludf.DUMMYFUNCTION("(GOOGLEFINANCE(A20,""high52"") + GOOGLEFINANCE(A20,""low52""))/2"),5.1899999999999995) -> 5.19 | I20: =IFERROR(__xludf.DUMMYFUNCTION("GOOGLEFINANCE(A20,""changepct"")"),0.0) -> 0 | J20: =IFERROR(__xludf.DUMMYFUNCTION("GOOGLEFINANCE(A20,""volume"")"),225136.0) -> 225136 | K20: =E20*F20 -> 22.84 | L20: =IFERROR(SUMIFS(COMPRAS!G:G,COMPRAS!A:A,B20),0) -> 22.911375 | M20: =E20*G20 -> 20.4 | N20: {=IF(INDIRECT("'"&A$20&"'!"&"B12") ="",INDIRECT("'"&A$20&"'!"&"C12"),INDIRECT("'"&A$20&"'!"&"B12"))} -> 0.0748 | O20: {=IFERROR(AVERAGE(INDIRECT("'"&A$20&"'!"&"B12:F12")),"")} -> 0.075566667 | P20: {=IF(INDIRECT("'"&A$20&"'!"&"B17") ="",INDIRECT("'"&A$20&"'!"&"C17"),INDIRECT("'"&A$20&"'!"&"B17"))} -> 15.34 | Q20: {=IFERROR(AVERAGE(INDIRECT("'"&A$20&"'!"&"B17:F17")),0)} -> 15.05 | R20: {=IF(INDIRECT("'"&A$20&"'!"&"B10") ="",INDIRECT("'"&A$20&"'!"&"C10"),INDIRECT("'"&A$20&"'!"&"B10"))} -> 0.04 | S20: {=IFERROR(AVERAGE(INDIRECT("'"&A$20&"'!"&"B10:F10")),0)} -> 0.025138 | T20: =R20*4 -> 0.16 | U20: =S20*4 -> 0.100552 | V20: {=IF(INDIRECT("'"&A$20&"'!"&"B15") ="",INDIRECT("'"&A$20&"'!"&"C15"),INDIRECT("'"&A$20&"'!"&"B15"))} -> 0.3353 | W20: {=IFERROR(AVERAGE(INDIRECT("'"&A$20&"'!"&"B15:F15")),"")} -> 0.33953333 | X20: {=IF(INDIRECT("'"&A$20&"'!"&"B5") ="",INDIRECT("'"&A$20&"'!"&"C5"),INDIRECT("'"&A$20&"'!"&"B5"))} -> 0.3359 | Y20: {=IFERROR(AVERAGE(INDIRECT("'"&A$20&"'!"&"B5:F5")),0)} -> 0.32938 | Z20: {=IF(INDIRECT("'"&A$20&"'!"&"B7") ="",INDIRECT("'"&A$20&"'!"&"C7"),INDIRECT("'"&A$20&"'!"&"B7"))} -> 0.0852 | AA20: {=IFERROR(AVERAGE(INDIRECT("'"&A$20&"'!"&"B7:F7")),0)} -> 0.06452 | AB20: =IFERROR((G20/(L20/E20))-1,"") -> -0.10961258 | AC20: =IFERROR(U20/G20,"") -> 0.019716078 | AD20: =IFERROR(IF(M20-L20=0,"",M20-L20),"") -> -2.511375 | AE20: =IFERROR(IF(M20-K20=0,"",M20-K20),"") -> -2.44 | AF20: =IF(P20>0,IFERROR((P20/G20)-1,""),"") -> 2.0078431 | AG20: =IFERROR(T20/G20,"") -> 0.031372549 | AI20: {=IF(INDIRECT("'"&A$20&"'!"&"B16") ="",INDIRECT("'"&A$20&"'!"&"C16"),INDIRECT("'"&A$20&"'!"&"B16"))} -> 0.0262 | AJ20: {=IFERROR(AVERAGE(INDIRECT("'"&A$20&"'!"&"B16:F16")),"")} -> 0.0238 | AK20: =AVERAGE(AG20:AJ20) -> 0.027124183 | AL20: =IFERROR(IF(R20*E20=0,"",R20*E20),"") -> 0.16 | AM20: =IFERROR(IF(S20*E20=0,"",S20*E20),"") -> 0.100552 | AN20: =IFERROR(IF(T20*E20=0,"",T20*E20),"") -> 0.64 | AO20: =IFERROR(IF(U20*E20=0,"",U20*E20),"") -> 0.402208 | AP20: =IF(AC20*D20=0,"",AC20*D20) -> 0.00022404635
A21: FPLUS16 | B21: FIBRA PLUS | C21: {=IF(INDIRECT("'"&A$21&"'!"&"B10") ="",INDIRECT("'"&A$21&"'!"&"C1"),INDIRECT("'"&A$21&"'!"&"B1"))} -> 2023 Q1 | D21: =IFERROR(E21/SUM(E13:E35),0) -> 0.0028409091 | E21: =SUMIFS(COMPRAS!B:B,COMPRAS!A:A,B21) -> 1 | F21: =IFERROR(AVERAGEIFS(COMPRAS!C:C,COMPRAS!A:A,B21),0) -> 6.4866667 | G21: =IFERROR(__xludf.DUMMYFUNCTION("GOOGLEFINANCE(A21,""price"")"),5.02) -> 5.02 | H21: =IFERROR(__xludf.DUMMYFUNCTION("(GOOGLEFINANCE(A21,""high52"") + GOOGLEFINANCE(A21,""low52""))/2"),5.505) -> 5.505 | I21: =IFERROR(__xludf.DUMMYFUNCTION("GOOGLEFINANCE(A21,""changepct"")"),-3.28) -> -3.28 | J21: =IFERROR(__xludf.DUMMYFUNCTION("GOOGLEFINANCE(A21,""volume"")"),143563.0) -> 143563 | K21: =E21*F21 -> 6.4866667 | L21: =IFERROR(SUMIFS(COMPRAS!G:G,COMPRAS!A:A,B21),0) -> 8.310211 | M21: =E21*G21 -> 5.02 | N21: {=IF(INDIRECT("'"&A$21&"'!"&"B12") ="",INDIRECT("'"&A$21&"'!"&"C12"),INDIRECT("'"&A$21&"'!"&"B12"))} -> 0.0368 | O21: {=IFERROR(AVERAGE(INDIRECT("'"&A$21&"'!"&"B12:F12")),"")} -> 0.03775 | P21: {=IF(INDIRECT("'"&A$21&"'!"&"B17") ="",INDIRECT("'"&A$21&"'!"&"C17"),INDIRECT("'"&A$21&"'!"&"B17"))} -> 17.49 | Q21: {=IFERROR(AVERAGE(INDIRECT("'"&A$21&"'!"&"B17:F17")),0)} -> 17.485 | R21: {=IF(INDIRECT("'"&A$21&"'!"&"B10") ="",INDIRECT("'"&A$21&"'!"&"C10"),INDIRECT("'"&A$21&"'!"&"B10"))} -> 0.0868 | S21: {=IFERROR(AVERAGE(INDIRECT("'"&A$21&"'!"&"B10:F10")),0)} -> 0.01736 | T21: =R21*4 -> 0.3472 | U21: =S21*4 -> 0.06944 | V21: {=IF(INDIRECT("'"&A$21&"'!"&"B15") ="",INDIRECT("'"&A$21&"'!"&"C15"),INDIRECT("'"&A$21&"'!"&"B15"))} -> 0.2454 | W21: {=IFERROR(AVERAGE(INDIRECT("'"&A$21&"'!"&"B15:F15")),"")} -> 0.26215 | X21: {=IF(INDIRECT("'"&A$21&"'!"&"B5") ="",INDIRECT("'"&A$21&"'!"&"C5"),INDIRECT("'"&A$21&"'!"&"B5"))} -> 0.7935 | Y21: {=IFERROR(AVERAGE(INDIRECT("'"&A$21&"'!"&"B5:F5")),0)} -> 0.83485 | Z21: {=IF(INDIRECT("'"&A$21&"'!"&"B7") ="",INDIRECT("'"&A$21&"'!"&"C7"),INDIRECT("'"&A$21&"'!"&"B7"))} -> 0.2794 | AA21: {=IFERROR(AVERAGE(INDIRECT("'"&A$21&"'!"&"B7:F7")),0)} -> 0.2711 | AB21: =IFERROR((G21/(L21/E21))-1,"") -> -0.39592388 | AC21: =IFERROR(U21/G21,"") -> 0.013832669 | AD21: =IFERROR(IF(M21-L21=0,"",M21-L21),"") -> -3.290211 | AE21: =IFERROR(IF(M21-K21=0,"",M21-K21),"") -> -1.4666667 | AF21: =IF(P21>0,IFERROR((P21/G21)-1,""),"") -> 2.4840637 | AG21: =IFERROR(T21/G21,"") -> 0.069163347 | AI21: {=IF(INDIRECT("'"&A$21&"'!"&"B16") ="",INDIRECT("'"&A$21&"'!"&"C16"),INDIRECT("'"&A$21&"'!"&"B16"))} -> 0 | AJ21: {=IFERROR(AVERAGE(INDIRECT("'"&A$21&"'!"&"B16:F16")),"")} -> 0 | AK21: =AVERAGE(AG21:AJ21) -> 0.023054449 | AL21: =IFERROR(IF(R21*E21=0,"",R21*E21),"") -> 0.0868 | AM21: =IFERROR(IF(S21*E21=0,"",S21*E21),"") -> 0.01736 | AN21: =IFERROR(IF(T21*E21=0,"",T21*E21),"") -> 0.3472 | AO21: =IFERROR(IF(U21*E21=0,"",U21*E21),"") -> 0.06944 | AP21: =IF(AC21*D21=0,"",AC21*D21) -> 3.9297356e-05
A22: FIBRAPL14 | B22: FIBRA PROLOGIS | C22: {=IF(INDIRECT("'"&A$22&"'!"&"B10") ="",INDIRECT("'"&A$22&"'!"&"C1"),INDIRECT("'"&A$22&"'!"&"B1"))} -> 2023 Q1 | D22: =IFERROR(E22/SUM(E13:E35),0) -> 0 | E22: =SUMIFS(COMPRAS!B:B,COMPRAS!A:A,B22) -> 0 | F22: =IFERROR(AVERAGEIFS(COMPRAS!C:C,COMPRAS!A:A,B22),0) -> 0 | G22: =IFERROR(__xludf.DUMMYFUNCTION("GOOGLEFINANCE(A22,""price"")"),79.66) -> 79.66 | H22: =IFERROR(__xludf.DUMMYFUNCTION("(GOOGLEFINANCE(A22,""high52"") + GOOGLEFINANCE(A22,""low52""))/2"),75.215) -> 75.215 | I22: =IFERROR(__xludf.DUMMYFUNCTION("GOOGLEFINANCE(A22,""changepct"")"),2.18) -> 2.18 | J22: =IFERROR(__xludf.DUMMYFUNCTION("GOOGLEFINANCE(A22,""volume"")"),525879.0) -> 525879 | K22: =E22*F22 -> 0 | L22: =IFERROR(SUMIFS(COMPRAS!G:G,COMPRAS!A:A,B22),0) -> 0 | M22: =E22*G22 -> 0 | N22: {=IF(INDIRECT("'"&A$22&"'!"&"B12") ="",INDIRECT("'"&A$22&"'!"&"C12"),INDIRECT("'"&A$22&"'!"&"B12"))} -> 0.0707 | O22: {=IFERROR(AVERAGE(INDIRECT("'"&A$22&"'!"&"B12:F12")),"")} -> 0.066233333 | P22: {=IF(INDIRECT("'"&A$22&"'!"&"B17") ="",INDIRECT("'"&A$22&"'!"&"C17"),INDIRECT("'"&A$22&"'!"&"B17"))} -> 54.51 | Q22: {=IFERROR(AVERAGE(INDIRECT("'"&A$22&"'!"&"B17:F17")),0)} -> 58.96 | R22: {=IF(INDIRECT("'"&A$22&"'!"&"B10") ="",INDIRECT("'"&A$22&"'!"&"C10"),INDIRECT("'"&A$22&"'!"&"B10"))} -> 0.85 | S22: {=IFERROR(AVERAGE(INDIRECT("'"&A$22&"'!"&"B10:F10")),0)} -> 0.644 | T22: =R22*4 -> 3.4 | U22: =S22*4 -> 2.576 | V22: {=IF(INDIRECT("'"&A$22&"'!"&"B15") ="",INDIRECT("'"&A$22&"'!"&"C15"),INDIRECT("'"&A$22&"'!"&"B15"))} -> 0.2278 | W22: {=IFERROR(AVERAGE(INDIRECT("'"&A$22&"'!"&"B15:F15")),"")} -> 0.24116667 | X22: {=IF(INDIRECT("'"&A$22&"'!"&"B5") ="",INDIRECT("'"&A$22&"'!"&"C5"),INDIRECT("'"&A$22&"'!"&"B5"))} -> 0.8657 | Y22: {=IFERROR(AVERAGE(INDIRECT("'"&A$22&"'!"&"B5:F5")),0)} -> 0.86852 | Z22: {=IF(INDIRECT("'"&A$22&"'!"&"B7") ="",INDIRECT("'"&A$22&"'!"&"C7"),INDIRECT("'"&A$22&"'!"&"B7"))} -> 0.6527 | AA22: {=IFERROR(AVERAGE(INDIRECT("'"&A$22&"'!"&"B7:F7")),0)} -> 0.5969 | AB22: =IFERROR((G22/(L22/E22))-1,"") | AC22: =IFERROR(U22/G22,"") -> 0.032337434 | AD22: =IFERROR(IF(M22-L22=0,"",M22-L22),"") | AE22: =IFERROR(IF(M22-K22=0,"",M22-K22),"") | AF22: =IF(P22>0,IFERROR((P22/G22)-1,""),"") -> -0.3157168 | AG22: =IFERROR(T22/G22,"") -> 0.042681396 | AI22: {=IF(INDIRECT("'"&A$22&"'!"&"B16") ="",INDIRECT("'"&A$22&"'!"&"C16"),INDIRECT("'"&A$22&"'!"&"B16"))} -> 0.035 | AJ22: {=IFERROR(AVERAGE(INDIRECT("'"&A$22&"'!"&"B16:F16")),"")} -> 0.0359 | AK22: =AVERAGE(AG22:AJ22) -> 0.037860465 | AL22: =IFERROR(IF(R22*E22=0,"",R22*E22),"") | AM22: =IFERROR(IF(S22*E22=0,"",S22*E22),"") | AN22: =IFERROR(IF(T22*E22=0,"",T22*E22),"") | AO22: =IFERROR(IF(U22*E22=0,"",U22*E22),"") | AP22: =IF(AC22*D22=0,"",AC22*D22)
A23: TERRA13 | B23: FIBRA TERRAFINA | C23: {=IF(INDIRECT("'"&A$23&"'!"&"B10") ="",INDIRECT("'"&A$23&"'!"&"C1"),INDIRECT("'"&A$23&"'!"&"B1"))} -> 2023 Q1 | D23: =IFERROR(E23/SUM(E13:E35),0) -> 0 | E23: =SUMIFS(COMPRAS!B:B,COMPRAS!A:A,B23) -> 0 | F23: =IFERROR(AVERAGEIFS(COMPRAS!C:C,COMPRAS!A:A,B23),0) -> 0 | G23: =IFERROR(__xludf.DUMMYFUNCTION("GOOGLEFINANCE(A23,""price"")"),"#N/A") -> #N/A | H23: =IFERROR(__xludf.DUMMYFUNCTION("(GOOGLEFINANCE(A23,""high52"") + GOOGLEFINANCE(A23,""low52""))/2"),"#N/A") -> #N/A | I23: =IFERROR(__xludf.DUMMYFUNCTION("GOOGLEFINANCE(A23,""changepct"")"),"#N/A") -> #N/A | J23: =IFERROR(__xludf.DUMMYFUNCTION("GOOGLEFINANCE(A23,""volume"")"),"#N/A") -> #N/A | K23: =E23*F23 -> 0 | L23: =IFERROR(SUMIFS(COMPRAS!G:G,COMPRAS!A:A,B23),0) -> 0 | M23: =E23*G23 -> #N/A | N23: {=IF(INDIRECT("'"&A$23&"'!"&"B12") ="",INDIRECT("'"&A$23&"'!"&"C12"),INDIRECT("'"&A$23&"'!"&"B12"))} -> 0.0774 | O23: {=IFERROR(AVERAGE(INDIRECT("'"&A$23&"'!"&"B12:F12")),"")} -> 0.067433333 | P23: {=IF(INDIRECT("'"&A$23&"'!"&"B17") ="",INDIRECT("'"&A$23&"'!"&"C17"),INDIRECT("'"&A$23&"'!"&"B17"))} -> 43.67 | Q23: {=IFERROR(AVERAGE(INDIRECT("'"&A$23&"'!"&"B17:F17")),0)} -> 47.066667 | R23: {=IF(INDIRECT("'"&A$23&"'!"&"B10") ="",INDIRECT("'"&A$23&"'!"&"C10"),INDIRECT("'"&A$23&"'!"&"B10"))} -> 0.47 | S23: {=IFERROR(AVERAGE(INDIRECT("'"&A$23&"'!"&"B10:F10")),0)} -> 0.472 | T23: =R23*4 -> 1.88 | U23: =S23*4 -> 1.888 | V23: {=IF(INDIRECT("'"&A$23&"'!"&"B15") ="",INDIRECT("'"&A$23&"'!"&"C15"),INDIRECT("'"&A$23&"'!"&"B15"))} -> 0.3123 | W23: {=IFERROR(AVERAGE(INDIRECT("'"&A$23&"'!"&"B15:F15")),"")} -> 0.30933333 | X23: {=IF(INDIRECT("'"&A$23&"'!"&"B5") ="",INDIRECT("'"&A$23&"'!"&"C5"),INDIRECT("'"&A$23&"'!"&"B5"))} -> 0.9297 | Y23: {=IFERROR(AVERAGE(INDIRECT("'"&A$23&"'!"&"B5:F5")),0)} -> 0.92722 | Z23: {=IF(INDIRECT("'"&A$23&"'!"&"B7") ="",INDIRECT("'"&A$23&"'!"&"C7"),INDIRECT("'"&A$23&"'!"&"B7"))} -> 0.5914 | AA23: {=IFERROR(AVERAGE(INDIRECT("'"&A$23&"'!"&"B7:F7")),0)} -> 0.60364 | AB23: =IFERROR((G23/(L23/E23))-1,"") | AC23: =IFERROR(U23/G23,"") | AD23: =IFERROR(IF(M23-L23=0,"",M23-L23),"") | AE23: =IFERROR(IF(M23-K23=0,"",M23-K23),"") | AF23: =IF(P23>0,IFERROR((P23/G23)-1,""),"") | AG23: =IFERROR(T23/G23,"") | AI23: {=IF(INDIRECT("'"&A$23&"'!"&"B16") ="",INDIRECT("'"&A$23&"'!"&"C16"),INDIRECT("'"&A$23&"'!"&"B16"))} -> 0.0575 | AJ23: {=AVERAGE(INDIRECT("'"&A$23&"'!"&"B16:F16"))} -> 0.0587 | AK23: =AVERAGE(AG23:AJ23) -> 0.0581 | AL23: =IFERROR(IF(R23*E23=0,"",R23*E23),"") | AM23: =IFERROR(IF(S23*E23=0,"",S23*E23),"") | AN23: =IFERROR(IF(T23*E23=0,"",T23*E23),"") | AO23: =IFERROR(IF(U23*E23=0,"",U23*E23),"") | AP23: =IF(AC23*D23=0,"",AC23*D23)
A24: FIHO12 | B24: FIBRA HOTEL | C24: {=IF(INDIRECT("'"&A$24&"'!"&"B10") ="",INDIRECT("'"&A$24&"'!"&"C1"),INDIRECT("'"&A$24&"'!"&"B1"))} -> 2023 Q1 | D24: =IFERROR(E24/SUM(E13:E35),0) -> 0 | E24: =SUMIFS(COMPRAS!B:B,COMPRAS!A:A,B24) -> 0 | F24: =IFERROR(AVERAGEIFS(COMPRAS!C:C,COMPRAS!A:A,B24),0) -> 0 | G24: =IFERROR(__xludf.DUMMYFUNCTION("GOOGLEFINANCE(A24,""price"")"),7.8) -> 7.8 | H24: =IFERROR(__xludf.DUMMYFUNCTION("(GOOGLEFINANCE(A24,""high52"") + GOOGLEFINANCE(A24,""low52""))/2"),8.684999999999999) -> 8.685 | I24: =IFERROR(__xludf.DUMMYFUNCTION("GOOGLEFINANCE(A24,""changepct"")"),1.96) -> 1.96 | J24: =IFERROR(__xludf.DUMMYFUNCTION("GOOGLEFINANCE(A24,""volume"")"),41200.0) -> 41200 | K24: =E24*F24 -> 0 | L24: =IFERROR(SUMIFS(COMPRAS!G:G,COMPRAS!A:A,B24),0) -> 0 | M24: =E24*G24 -> 0 | N24: {=IF(INDIRECT("'"&A$24&"'!"&"B12") ="",INDIRECT("'"&A$24&"'!"&"C12"),INDIRECT("'"&A$24&"'!"&"B12"))} -> 0.1174 | O24: {=IFERROR(AVERAGE(INDIRECT("'"&A$24&"'!"&"B12:F12")),"")} -> 0.11125 | P24: {=IF(INDIRECT("'"&A$24&"'!"&"B17") ="",INDIRECT("'"&A$24&"'!"&"C17"),INDIRECT("'"&A$24&"'!"&"B17"))} -> 14.79 | Q24: {=IFERROR(AVERAGE(INDIRECT("'"&A$24&"'!"&"B17:F17")),0)} -> 14.825 | R24: {=IF(INDIRECT("'"&A$24&"'!"&"B10") ="",INDIRECT("'"&A$24&"'!"&"C10"),INDIRECT("'"&A$24&"'!"&"B10"))} -> 0.125 | S24: {=IFERROR(AVERAGE(INDIRECT("'"&A$24&"'!"&"B10:F10")),0)} -> 0.025 | T24: =R24*4 -> 0.5 | U24: =S24*4 -> 0.1 | V24: {=IF(INDIRECT("'"&A$24&"'!"&"B15") ="",INDIRECT("'"&A$24&"'!"&"C15"),INDIRECT("'"&A$24&"'!"&"B15"))} -> 0.2574 | W24: {=IFERROR(AVERAGE(INDIRECT("'"&A$24&"'!"&"B15:F15")),"")} -> 0.26785 | X24: {=IF(INDIRECT("'"&A$24&"'!"&"B5") ="",INDIRECT("'"&A$24&"'!"&"C5"),INDIRECT("'"&A$24&"'!"&"B5"))} -> 0.3613 | Y24: {=IFERROR(AVERAGE(INDIRECT("'"&A$24&"'!"&"B5:F5")),0)} -> 0.31675 | Z24: {=IF(INDIRECT("'"&A$24&"'!"&"B7") ="",INDIRECT("'"&A$24&"'!"&"C7"),INDIRECT("'"&A$24&"'!"&"B7"))} -> 0.2118 | AA24: {=IFERROR(AVERAGE(INDIRECT("'"&A$24&"'!"&"B7:F7")),0)} -> 0.169575 | AB24: =IFERROR((G24/(L24/E24))-1,"") | AC24: =IFERROR(U24/G24,"") -> 0.012820513 | AD24: =IFERROR(IF(M24-L24=0,"",M24-L24),"") | AE24: =IFERROR(IF(M24-K24=0,"",M24-K24),"") | AF24: =IF(P24>0,IFERROR((P24/G24)-1,""),"") -> 0.89615385 | AG24: =IFERROR(T24/G24,"") -> 0.064102564 | AI24: {=IF(INDIRECT("'"&A$24&"'!"&"B16") ="",INDIRECT("'"&A$24&"'!"&"C16"),INDIRECT("'"&A$24&"'!"&"B16"))} -> 0.0105 | AJ24: {=IFERROR(AVERAGE(INDIRECT("'"&A$24&"'!"&"B16:F16")),"")} -> 0.0035 | AK24: =AVERAGE(AG24:AJ24) -> 0.026034188 | AL24: =IFERROR(IF(R24*E24=0,"",R24*E24),"") | AM24: =IFERROR(IF(S24*E24=0,"",S24*E24),"") | AN24: =IFERROR(IF(T24*E24=0,"",T24*E24),"") | AO24: =IFERROR(IF(U24*E24=0,"",U24*E24),"") | AP24: =IF(AC24*D24=0,"",AC24*D24)
A25: EDUCA18 | B25: FIBRA EDUCA | C25: {=IF(INDIRECT("'"&A$25&"'!"&"B10") ="",INDIRECT("'"&A$25&"'!"&"C1"),INDIRECT("'"&A$25&"'!"&"B1"))} -> 2023 Q1 | D25: =IFERROR(E25/SUM(E13:E35),0) -> 0 | E25: =SUMIFS(COMPRAS!B:B,COMPRAS!A:A,B25) -> 0 | F25: =IFERROR(AVERAGEIFS(COMPRAS!C:C,COMPRAS!A:A,B25),0) -> 0 | G25: =IFERROR(__xludf.DUMMYFUNCTION("GOOGLEFINANCE(A25,""price"")"),59.01) -> 59.01 | H25: =IFERROR(__xludf.DUMMYFUNCTION("(GOOGLEFINANCE(A25,""high52"") + GOOGLEFINANCE(A25,""low52""))/2"),53.254999999999995) -> 53.255 | I25: =IFERROR(__xludf.DUMMYFUNCTION("GOOGLEFINANCE(A25,""changepct"")"),0.0) -> 0 | J25: =IFERROR(__xludf.DUMMYFUNCTION("GOOGLEFINANCE(A25,""volume"")"),0.0) -> 0 | K25: =E25*F25 -> 0 | L25: =IFERROR(SUMIFS(COMPRAS!G:G,COMPRAS!A:A,B25),0) -> 0 | M25: =E25*G25 -> 0 | N25: {=IF(INDIRECT("'"&A$25&"'!"&"B12") ="",INDIRECT("'"&A$25&"'!"&"C12"),INDIRECT("'"&A$25&"'!"&"B12"))} -> 0.1141 | O25: {=IFERROR(AVERAGE(INDIRECT("'"&A$25&"'!"&"B12:F12")),"")} -> 0.117 | P25: {=IF(INDIRECT("'"&A$25&"'!"&"B17") ="",INDIRECT("'"&A$25&"'!"&"C17"),INDIRECT("'"&A$25&"'!"&"B17"))} -> 25.3 | Q25: {=IFERROR(AVERAGE(INDIRECT("'"&A$25&"'!"&"B17:F17")),0)} -> 24.75 | R25: {=IF(INDIRECT("'"&A$25&"'!"&"B10") ="",INDIRECT("'"&A$25&"'!"&"C10"),INDIRECT("'"&A$25&"'!"&"B10"))} -> 0.5702 | S25: {=IFERROR(AVERAGE(INDIRECT("'"&A$25&"'!"&"B10:F10")),0)} -> 0.5706034 | T25: =R25*4 -> 2.2808 | U25: =S25*4 -> 2.2824136 | V25: {=IF(INDIRECT("'"&A$25&"'!"&"B15") ="",INDIRECT("'"&A$25&"'!"&"C15"),INDIRECT("'"&A$25&"'!"&"B15"))} -> 0.1529 | W25: {=IFERROR(AVERAGE(INDIRECT("'"&A$25&"'!"&"B15:F15")),"")} -> 0.1556 | X25: {=IF(INDIRECT("'"&A$25&"'!"&"B5") ="",INDIRECT("'"&A$25&"'!"&"C5"),INDIRECT("'"&A$25&"'!"&"B5"))} -> 0.8683 | Y25: {=IFERROR(AVERAGE(INDIRECT("'"&A$25&"'!"&"B5:F5")),0)} -> 0.869125 | Z25: {=IF(INDIRECT("'"&A$25&"'!"&"B7") ="",INDIRECT("'"&A$25&"'!"&"C7"),INDIRECT("'"&A$25&"'!"&"B7"))} -> 0.7189 | AA25: {=IFERROR(AVERAGE(INDIRECT("'"&A$25&"'!"&"B7:F7")),0)} -> 0.789875 | AB25: =IFERROR((G25/(L25/E25))-1,"") | AC25: =IFERROR(U25/G25,"") -> 0.038678421 | AD25: =IFERROR(IF(M25-L25=0,"",M25-L25),"") | AE25: =IFERROR(IF(M25-K25=0,"",M25-K25),"") | AF25: =IF(P25>0,IFERROR((P25/G25)-1,""),"") -> -0.57125911 | AG25: =IFERROR(T25/G25,"") -> 0.038651076 | AI25: {=IF(INDIRECT("'"&A$25&"'!"&"B16") ="",INDIRECT("'"&A$25&"'!"&"C16"),INDIRECT("'"&A$25&"'!"&"B16"))} -> 0.0456 | AJ25: {=AVERAGE(INDIRECT("'"&A$25&"'!"&"B16:F16"))} -> 0.04535 | AK25: =AVERAGE(AG25:AJ25) -> 0.043200359 | AL25: =IFERROR(IF(R25*E25=0,"",R25*E25),"") | AM25: =IFERROR(IF(S25*E25=0,"",S25*E25),"") | AN25: =IFERROR(IF(T25*E25=0,"",T25*E25),"") | AO25: =IFERROR(IF(U25*E25=0,"",U25*E25),"") | AP25: =IF(AC25*D25=0,"",AC25*D25)
A26: SOMA21 | B26: FIBRA SOMA | C26: {=IF(INDIRECT("'"&A$26&"'!"&"B10") ="",INDIRECT("'"&A$26&"'!"&"C1"),INDIRECT("'"&A$26&"'!"&"B1"))} -> 2023 Q1 | D26: =IFERROR(E26/SUM(E13:E35),0) -> 0 | E26: =SUMIFS(COMPRAS!B:B,COMPRAS!A:A,B26) -> 0 | F26: =IFERROR(AVERAGEIFS(COMPRAS!C:C,COMPRAS!A:A,B26),0) -> 0 | G26: =IFERROR(__xludf.DUMMYFUNCTION("GOOGLEFINANCE(A26,""price"")"),50.0) -> 50 | H26: =IFERROR(__xludf.DUMMYFUNCTION("IFERROR(G26,(GOOGLEFINANCE(A26,""high52"") + GOOGLEFINANCE(A26,""low52""))/2)"),50.0) -> 50 | I26: =IFERROR(__xludf.DUMMYFUNCTION("IF(GOOGLEFINANCE(A26,""changepct"") <=-100,0,GOOGLEFINANCE(A26,""changepct"") )"),0.0) -> 0 | J26: =IFERROR(__xludf.DUMMYFUNCTION("GOOGLEFINANCE(A26,""volume"")"),0.0) -> 0 | K26: =E26*F26 -> 0 | L26: =IFERROR(SUMIFS(COMPRAS!G:G,COMPRAS!A:A,B26),0) -> 0 | M26: =E26*G26 -> 0 | N26: {=IF(INDIRECT("'"&A$26&"'!"&"B12") ="",INDIRECT("'"&A$26&"'!"&"C12"),INDIRECT("'"&A$26&"'!"&"B12"))} -> 0.0365 | O26: {=IFERROR(AVERAGE(INDIRECT("'"&A$26&"'!"&"B12:F12")),"")} -> 0.0367 | P26: {=IF(INDIRECT("'"&A$26&"'!"&"B17") ="",INDIRECT("'"&A$26&"'!"&"C17"),INDIRECT("'"&A$26&"'!"&"B17"))} -> 49.5 | Q26: {=IFERROR(AVERAGE(INDIRECT("'"&A$26&"'!"&"B17:F17")),0)} -> 50.845 | R26: {=IF(INDIRECT("'"&A$26&"'!"&"B10") ="",INDIRECT("'"&A$26&"'!"&"C10"),INDIRECT("'"&A$26&"'!"&"B10"))} -> 0 | S26: {=IFERROR(AVERAGE(INDIRECT("'"&A$26&"'!"&"B10:F10")),0)} -> 0.166 | T26: =R26*4 -> 0 | U26: =S26*4 -> 0.664 | V26: {=IF(INDIRECT("'"&A$26&"'!"&"B15") ="",INDIRECT("'"&A$26&"'!"&"C15"),INDIRECT("'"&A$26&"'!"&"B15"))} -> 0.2519 | W26: {=IFERROR(AVERAGE(INDIRECT("'"&A$26&"'!"&"B15:F15")),"")} -> 0.24505 | X26: {=IF(INDIRECT("'"&A$26&"'!"&"B5") ="",INDIRECT("'"&A$26&"'!"&"C5"),INDIRECT("'"&A$26&"'!"&"B5"))} -> 0.7701 | Y26: {=IFERROR(AVERAGE(INDIRECT("'"&A$26&"'!"&"B5:F5")),0)} -> 0.71144 | Z26: {=IF(INDIRECT("'"&A$26&"'!"&"B7") ="",INDIRECT("'"&A$26&"'!"&"C7"),INDIRECT("'"&A$26&"'!"&"B7"))} -> 0.407 | AA26: {=IFERROR(AVERAGE(INDIRECT("'"&A$26&"'!"&"B7:F7")),0)} -> 0.30386 | AB26: =IFERROR((G26/(L26/E26))-1,"") | AC26: =IFERROR(U26/G26,"") -> 0.01328 | AD26: =IFERROR(IF(M26-L26=0,"",M26-L26),"") | AE26: =IFERROR(IF(M26-K26=0,"",M26-K26),"") | AF26: =IF(P26>0,IFERROR((P26/G26)-1,""),"") -> -0.01 | AG26: =IFERROR(T26/G26,"") -> 0 | AI26: {=IF(INDIRECT("'"&A$26&"'!"&"B16") ="",INDIRECT("'"&A$26&"'!"&"C16"),INDIRECT("'"&A$26&"'!"&"B16"))} -> 0 | AJ26: {=IFERROR(AVERAGE(INDIRECT("'"&A$26&"'!"&"B16:F16")),"")} -> 0 | AK26: =AVERAGE(AG26:AJ26) -> 0 | AL26: =IFERROR(IF(R26*E26=0,"",R26*E26),"") | AM26: =IFERROR(IF(S26*E26=0,"",S26*E26),"") | AN26: =IFERROR(IF(T26*E26=0,"",T26*E26),"") | AO26: =IFERROR(IF(U26*E26=0,"",U26*E26),"") | AP26: =IF(AC26*D26=0,"",AC26*D26)
A27: STORAGE18 | B27: FIBRA STORAGE | C27: {=IF(INDIRECT("'"&A$27&"'!"&"B10") ="",INDIRECT("'"&A$27&"'!"&"C1"),INDIRECT("'"&A$27&"'!"&"B1"))} -> 2022 Q4 | D27: =IFERROR(E27/SUM(E13:E35),0) -> 0 | E27: =SUMIFS(COMPRAS!B:B,COMPRAS!A:A,B27) -> 0 | F27: =IFERROR(AVERAGEIFS(COMPRAS!C:C,COMPRAS!A:A,B27),0) -> 0 | G27: =IFERROR(__xludf.DUMMYFUNCTION("GOOGLEFINANCE(A27,""price"")"),24.99) -> 24.99 | H27: =IFERROR(__xludf.DUMMYFUNCTION("IFERROR(G27,(GOOGLEFINANCE(A27,""high52"") + GOOGLEFINANCE(A27,""low52""))/2)"),24.99) -> 24.99 | I27: =IFERROR(__xludf.DUMMYFUNCTION("GOOGLEFINANCE(A27,""changepct"")"),-0.08) -> -0.08 | J27: =IFERROR(__xludf.DUMMYFUNCTION("GOOGLEFINANCE(A27,""volume"")"),1293.0) -> 1293 | K27: =E27*F27 -> 0 | L27: =IFERROR(SUMIFS(COMPRAS!G:G,COMPRAS!A:A,B27),0) -> 0 | M27: =E27*G27 -> 0 | N27: {=IF(INDIRECT("'"&A$27&"'!"&"B12") ="",INDIRECT("'"&A$27&"'!"&"C12"),INDIRECT("'"&A$27&"'!"&"B12"))} -> 0.0695 | O27: {=IFERROR(AVERAGE(INDIRECT("'"&A$27&"'!"&"B12:F12")),"")} -> 0.071 | P27: {=IF(INDIRECT("'"&A$27&"'!"&"B17") ="",INDIRECT("'"&A$27&"'!"&"C17"),INDIRECT("'"&A$27&"'!"&"B17"))} -> 21.09 | Q27: {=IFERROR(AVERAGE(INDIRECT("'"&A$27&"'!"&"B17:F17")),0)} -> 20.61 | R27: {=IF(INDIRECT("'"&A$27&"'!"&"B10") ="",INDIRECT("'"&A$27&"'!"&"C10"),INDIRECT("'"&A$27&"'!"&"B10"))} -> 0 | S27: {=IFERROR(AVERAGE(INDIRECT("'"&A$27&"'!"&"B10:F10")),0)} -> 0.0875 | T27: =R27*4 -> 0 | U27: =S27*4 -> 0.35 | V27: {=IF(INDIRECT("'"&A$27&"'!"&"B15") ="",INDIRECT("'"&A$27&"'!"&"C15"),INDIRECT("'"&A$27&"'!"&"B15"))} -> 0.2267 | W27: {=IFERROR(AVERAGE(INDIRECT("'"&A$27&"'!"&"B15:F15")),"")} -> 0.2319 | X27: {=IF(INDIRECT("'"&A$27&"'!"&"B5") ="",INDIRECT("'"&A$27&"'!"&"C5"),INDIRECT("'"&A$27&"'!"&"B5"))} -> 0.7703 | Y27: {=IFERROR(AVERAGE(INDIRECT("'"&A$27&"'!"&"B5:F5")),0)} -> 0.76485 | Z27: {=IF(INDIRECT("'"&A$27&"'!"&"B7") ="",INDIRECT("'"&A$27&"'!"&"C7"),INDIRECT("'"&A$27&"'!"&"B7"))} -> 0.4378 | AA27: {=IFERROR(AVERAGE(INDIRECT("'"&A$27&"'!"&"B7:F7")),0)} -> 0.334975 | AB27: =IFERROR((G27/(L27/E27))-1,"") | AC27: =IFERROR(U27/G27,"") -> 0.014005602 | AD27: =IFERROR(IF(M27-L27=0,"",M27-L27),"") | AE27: =IFERROR(IF(M27-K27=0,"",M27-K27),"") | AF27: =IF(P27>0,IFERROR((P27/G27)-1,""),"") -> -0.15606243 | AG27: =IFERROR(T27/G27,"") -> 0 | AI27: {=IF(INDIRECT("'"&A$27&"'!"&"B16") ="",INDIRECT("'"&A$27&"'!"&"C16"),INDIRECT("'"&A$27&"'!"&"B16"))} -> 0 | AJ27: {=IFERROR(AVERAGE(INDIRECT("'"&A$27&"'!"&"B16:F16")),"")} -> 0 | AK27: =AVERAGE(AG27:AJ27) -> 0 | AL27: =IFERROR(IF(R27*E27=0,"",R27*E27),"") | AM27: =IFERROR(IF(S27*E27=0,"",S27*E27),"") | AN27: =IFERROR(IF(T27*E27=0,"",T27*E27),"") | AO27: =IFERROR(IF(U27*E27=0,"",U27*E27),"") | AP27: =IF(AC27*D27=0,"",AC27*D27)
A28: FSITES20 | B28: FIBRA TELESITES | C28: {=IF(INDIRECT("'"&A$28&"'!"&"B10") ="",INDIRECT("'"&A$28&"'!"&"C1"),INDIRECT("'"&A$28&"'!"&"B1"))} -> 2023 Q1 | D28: =IFERROR(E28/SUM(E13:E35),0) -> 0 | E28: =SUMIFS(COMPRAS!B:B,COMPRAS!A:A,B28) -> 0 | F28: =IFERROR(AVERAGEIFS(COMPRAS!C:C,COMPRAS!A:A,B28),0) -> 0 | G28: =IFERROR(__xludf.DUMMYFUNCTION("GOOGLEFINANCE(A28,""price"")"),26.0) -> 26 | H28: =IFERROR(__xludf.DUMMYFUNCTION("IFERROR(G28,(GOOGLEFINANCE(A28,""high52"") + GOOGLEFINANCE(A28,""low52""))/2)"),26.0) -> 26 | I28: =IFERROR(__xludf.DUMMYFUNCTION("GOOGLEFINANCE(A28,""changepct"")"),0.0) -> 0 | J28: =IFERROR(__xludf.DUMMYFUNCTION("GOOGLEFINANCE(A28,""volume"")"),0.0) -> 0 | K28: =E28*F28 -> 0 | L28: =IFERROR(SUMIFS(COMPRAS!G:G,COMPRAS!A:A,B28),0) -> 0 | M28: =E28*G28 -> 0 | N28: {=IF(INDIRECT("'"&A$28&"'!"&"B12") ="",INDIRECT("'"&A$28&"'!"&"C12"),INDIRECT("'"&A$28&"'!"&"B12"))} | O28: {=IFERROR(AVERAGE(INDIRECT("'"&A$28&"'!"&"B12:F12")),"")} -> 0.1113 | P28: {=IF(INDIRECT("'"&A$28&"'!"&"B17") ="",INDIRECT("'"&A$28&"'!"&"C17"),INDIRECT("'"&A$28&"'!"&"B17"))} | Q28: {=IFERROR(AVERAGE(INDIRECT("'"&A$28&"'!"&"B17:F17")),"")} -> 17.68 | R28: {=IF(INDIRECT("'"&A$28&"'!"&"B10") ="",INDIRECT("'"&A$28&"'!"&"C10"),INDIRECT("'"&A$28&"'!"&"B10"))} -> 0.147633 | S28: {=IFERROR(AVERAGE(INDIRECT("'"&A$28&"'!"&"B10:F10")),0)} -> 0.181872 | T28: =R28*4 -> 0.590532 | U28: =S28*4 -> 0.727488 | V28: {=IF(INDIRECT("'"&A$28&"'!"&"B15") ="",INDIRECT("'"&A$28&"'!"&"C15"),INDIRECT("'"&A$28&"'!"&"B15"))} | W28: {=IFERROR(AVERAGE(INDIRECT("'"&A$28&"'!"&"B15:F15")),"")} | X28: {=IF(INDIRECT("'"&A$28&"'!"&"B5") ="",INDIRECT("'"&A$28&"'!"&"C5"),INDIRECT("'"&A$28&"'!"&"B5"))} | Y28: {=IFERROR(AVERAGE(INDIRECT("'"&A$28&"'!"&"B5:F5")),"")} | Z28: {=IF(INDIRECT("'"&A$28&"'!"&"B7") ="",INDIRECT("'"&A$28&"'!"&"C7"),INDIRECT("'"&A$28&"'!"&"B7"))} | AA28: {=IFERROR(AVERAGE(INDIRECT("'"&A$28&"'!"&"B7:F7")),"")} | AB28: =IFERROR((G28/(L28/E28))-1,"") | AC28: =IFERROR(U28/G28,"") -> 0.027980308 | AD28: =IFERROR(IF(M28-L28=0,"",M28-L28),"") | AE28: =IFERROR(IF(M28-K28=0,"",M28-K28),"") | AF28: =IF(P28>0,IFERROR((P28/G28)-1,""),"") | AG28: =IFERROR(T28/G28,"") -> 0.022712769 | AI28: {=IF(INDIRECT("'"&A$28&"'!"&"B16") ="",INDIRECT("'"&A$28&"'!"&"C16"),INDIRECT("'"&A$28&"'!"&"B16"))} -> 0.0077 | AJ28: {=IFERROR(AVERAGE(INDIRECT("'"&A$28&"'!"&"B16:F16")),"")} -> 0.00385 | AK28: =AVERAGE(AG28:AJ28) -> 0.011420923 | AL28: =IFERROR(IF(R28*E28=0,"",R28*E28),"") | AM28: =IFERROR(IF(S28*E28=0,"",S28*E28),"") | AN28: =IFERROR(IF(T28*E28=0,"",T28*E28),"") | AO28: =IFERROR(IF(U28*E28=0,"",U28*E28),"") | AP28: =IF(AC28*D28=0,"",AC28*D28)
A29: FIDEAL20 | B29: FIBRA IDEAL | C29: {=IF(INDIRECT("'"&A$29&"'!"&"B10") ="",INDIRECT("'"&A$29&"'!"&"C1"),INDIRECT("'"&A$29&"'!"&"B1"))} -> 2022 Q4 | D29: =IFERROR(E29/SUM(E13:E35),0) -> 0 | E29: =SUMIFS(COMPRAS!B:B,COMPRAS!A:A,B29) -> 0 | F29: =IFERROR(AVERAGEIFS(COMPRAS!C:C,COMPRAS!A:A,B29),0) -> 0 | G29: =IFERROR(__xludf.DUMMYFUNCTION("GOOGLEFINANCE(A29,""price"")"),68.85) -> 68.85 | H29: =IFERROR(__xludf.DUMMYFUNCTION("IFERROR(G29,(GOOGLEFINANCE(A29,""high52"") + GOOGLEFINANCE(A29,""low52""))/2)"),68.85) -> 68.85 | I29: =IFERROR(__xludf.DUMMYFUNCTION("GOOGLEFINANCE(A29,""changepct"")"),0.0) -> 0 | J29: =IFERROR(__xludf.DUMMYFUNCTION("GOOGLEFINANCE(A29,""volume"")"),0.0) -> 0 | K29: =E29*F29 -> 0 | L29: =IFERROR(SUMIFS(COMPRAS!G:G,COMPRAS!A:A,B29),0) -> 0 | M29: =E29*G29 -> 0 | N29: {=IF(INDIRECT("'"&A$29&"'!"&"B12") ="",INDIRECT("'"&A$29&"'!"&"C12"),INDIRECT("'"&A$29&"'!"&"B12"))} | O29: {=IFERROR(AVERAGE(INDIRECT("'"&A$29&"'!"&"B12:F12")),"")} | P29: {=IF(INDIRECT("'"&A$29&"'!"&"B17") ="",INDIRECT("'"&A$29&"'!"&"C17"),INDIRECT("'"&A$29&"'!"&"B17"))} | Q29: {=IFERROR(AVERAGE(INDIRECT("'"&A$29&"'!"&"B17:F17")),"")} | R29: {=IF(INDIRECT("'"&A$29&"'!"&"B10") ="",INDIRECT("'"&A$29&"'!"&"C10"),INDIRECT("'"&A$29&"'!"&"B10"))} -> 1.4136 | S29: {=IFERROR(AVERAGE(INDIRECT("'"&A$29&"'!"&"B10:F10")),"")} -> 1.3759 | T29: =R29*4 -> 5.6544 | U29: =S29*4 -> 5.5036 | V29: {=IF(INDIRECT("'"&A$29&"'!"&"B15") ="",INDIRECT("'"&A$29&"'!"&"C15"),INDIRECT("'"&A$29&"'!"&"B15"))} | W29: {=IFERROR(AVERAGE(INDIRECT("'"&A$29&"'!"&"B15:F15")),"")} | X29: {=IF(INDIRECT("'"&A$29&"'!"&"B5") ="",INDIRECT("'"&A$29&"'!"&"C5"),INDIRECT("'"&A$29&"'!"&"B5"))} | Y29: {=IFERROR(AVERAGE(INDIRECT("'"&A$29&"'!"&"B5:F5")),"")} | Z29: {=IF(INDIRECT("'"&A$29&"'!"&"B7") ="",INDIRECT("'"&A$29&"'!"&"C7"),INDIRECT("'"&A$29&"'!"&"B7"))} | AA29: {=IFERROR(AVERAGE(INDIRECT("'"&A$29&"'!"&"B7:F7")),"")} | AB29: =IFERROR((G29/(L29/E29))-1,"") | AC29: =IFERROR(U29/G29,"") -> 0.079936093 | AD29: =IFERROR(IF(M29-L29=0,"",M29-L29),"") | AE29: =IFERROR(IF(M29-K29=0,"",M29-K29),"") | AF29: =IF(P29>0,IFERROR((P29/G29)-1,""),"") | AG29: =IFERROR(T29/G29,"") -> 0.082126362 | AI29: {=IF(INDIRECT("'"&A$29&"'!"&"B16") ="",INDIRECT("'"&A$29&"'!"&"C16"),INDIRECT("'"&A$29&"'!"&"B16"))} | AJ29: {=IFERROR(AVERAGE(INDIRECT("'"&A$29&"'!"&"B16:F16")),"")} | AK29: =AVERAGE(AG29:AJ29) -> 0.082126362 | AL29: =IFERROR(IF(R29*E29=0,"",R29*E29),"") | AM29: =IFERROR(IF(S29*E29=0,"",S29*E29),"") | AN29: =IFERROR(IF(T29*E29=0,"",T29*E29),"") | AO29: =IFERROR(IF(U29*E29=0,"",U29*E29),"") | AP29: =IF(AC29*D29=0,"",AC29*D29)
A30: FEXI21 | B30: FIBRA EXI | C30: {=IF(INDIRECT("'"&A$30&"'!"&"B10") ="",INDIRECT("'"&A$30&"'!"&"C1"),INDIRECT("'"&A$30&"'!"&"B1"))} -> 2022 Q4 | D30: =IFERROR(E30/SUM(E13:E35),0) -> 0 | E30: =SUMIFS(COMPRAS!B:B,COMPRAS!A:A,B30) -> 0 | F30: =IFERROR(AVERAGEIFS(COMPRAS!C:C,COMPRAS!A:A,B30),0) -> 0 | G30: =IFERROR(__xludf.DUMMYFUNCTION("GOOGLEFINANCE(A30,""price"")"),19.48) -> 19.48 | H30: =IFERROR(__xludf.DUMMYFUNCTION("IFERROR(G30,(GOOGLEFINANCE(A30,""high52"") + GOOGLEFINANCE(A30,""low52""))/2)"),19.48) -> 19.48 | I30: =IFERROR(__xludf.DUMMYFUNCTION("GOOGLEFINANCE(A30,""changepct"")"),-0.2) -> -0.2 | J30: =IFERROR(__xludf.DUMMYFUNCTION("GOOGLEFINANCE(A30,""volume"")"),1062.0) -> 1062 | K30: =E30*F30 -> 0 | L30: =IFERROR(SUMIFS(COMPRAS!G:G,COMPRAS!A:A,B30),0) -> 0 | M30: =E30*G30 -> 0 | N30: {=IF(INDIRECT("'"&A$30&"'!"&"B12") ="",INDIRECT("'"&A$30&"'!"&"C12"),INDIRECT("'"&A$30&"'!"&"B12"))} | O30: {=IFERROR(AVERAGE(INDIRECT("'"&A$30&"'!"&"B12:F12")),"")} | P30: {=IF(INDIRECT("'"&A$30&"'!"&"B17") ="",INDIRECT("'"&A$30&"'!"&"C17"),INDIRECT("'"&A$30&"'!"&"B17"))} | Q30: {=IFERROR(AVERAGE(INDIRECT("'"&A$30&"'!"&"B17:F17")),"")} | R30: {=IF(INDIRECT("'"&A$30&"'!"&"B10") ="",INDIRECT("'"&A$30&"'!"&"C10"),INDIRECT("'"&A$30&"'!"&"B10"))} -> 0.1246 | S30: {=IFERROR(AVERAGE(INDIRECT("'"&A$30&"'!"&"B10:F10")),"")} -> 0.17365 | T30: =R30*4 -> 0.4984 | U30: =S30*4 -> 0.6946 | V30: {=IF(INDIRECT("'"&A$30&"'!"&"B15") ="",INDIRECT("'"&A$30&"'!"&"C15"),INDIRECT("'"&A$30&"'!"&"B15"))} | W30: {=IFERROR(AVERAGE(INDIRECT("'"&A$30&"'!"&"B15:F15")),"")} | X30: {=IF(INDIRECT("'"&A$30&"'!"&"B5") ="",INDIRECT("'"&A$30&"'!"&"C5"),INDIRECT("'"&A$30&"'!"&"B5"))} | Y30: {=IFERROR(AVERAGE(INDIRECT("'"&A$30&"'!"&"B5:F5")),"")} | Z30: {=IF(INDIRECT("'"&A$30&"'!"&"B7") ="",INDIRECT("'"&A$30&"'!"&"C7"),INDIRECT("'"&A$30&"'!"&"B7"))} | AA30: {=IFERROR(AVERAGE(INDIRECT("'"&A$30&"'!"&"B7:F7")),"")} | AB30: =IFERROR((G30/(L30/E30))-1,"") | AC30: =IFERROR(U30/G30,"") -> 0.035657084 | AD30: =IFERROR(IF(M30-L30=0,"",M30-L30),"") | AE30: =IFERROR(IF(M30-K30=0,"",M30-K30),"") | AF30: =IF(P30>0,IFERROR((P30/G30)-1,""),"") | AG30: =IFERROR(T30/G30,"") -> 0.025585216 | AI30: {=IF(INDIRECT("'"&A$30&"'!"&"B16") ="",INDIRECT("'"&A$30&"'!"&"C16"),INDIRECT("'"&A$30&"'!"&"B16"))} | AJ30: {=IFERROR(AVERAGE(INDIRECT("'"&A$30&"'!"&"B16:F16")),"")} | AK30: =AVERAGE(AG30:AJ30) -> 0.025585216 | AL30: =IFERROR(IF(R30*E30=0,"",R30*E30),"") | AM30: =IFERROR(IF(S30*E30=0,"",S30*E30),"") | AN30: =IFERROR(IF(T30*E30=0,"",T30*E30),"") | AO30: =IFERROR(IF(U30*E30=0,"",U30*E30),"") | AP30: =IF(AC30*D30=0,"",AC30*D30)
A31: FSOCIAL23 | B31: FIBRA SOCIAL | C31: {=IF(INDIRECT("'"&A$31&"'!"&"B10") ="",INDIRECT("'"&A$31&"'!"&"C1"),INDIRECT("'"&A$31&"'!"&"B1"))} -> 2023 Q1 | D31: =IFERROR(E31/SUM(E13:E35),0) -> 0 | E31: =SUMIFS(COMPRAS!B:B,COMPRAS!A:A,B31) -> 0 | F31: 20 | G31: =IFERROR(yahooF(A31&".MX",1),F31) -> 20 | H31: =IFERROR(__xludf.DUMMYFUNCTION("IFERROR(G31,(GOOGLEFINANCE(A31,""high52"") + GOOGLEFINANCE(A31,""low52""))/2)"),20.0) -> 20 | I31: ? | J31: ? | K31: =E31*F31 -> 0 | L31: =IFERROR(SUMIFS(COMPRAS!G:G,COMPRAS!A:A,B31),0) -> 0 | M31: =E31*G31 -> 0 | N31: {=IF(INDIRECT("'"&A$31&"'!"&"B12") ="",INDIRECT("'"&A$31&"'!"&"C12"),INDIRECT("'"&A$31&"'!"&"B12"))} | O31: {=IFERROR(AVERAGE(INDIRECT("'"&A$31&"'!"&"B12:F12")),"")} | P31: {=IF(INDIRECT("'"&A$31&"'!"&"B17") ="",INDIRECT("'"&A$31&"'!"&"C17"),INDIRECT("'"&A$31&"'!"&"B17"))} | Q31: {=IFERROR(AVERAGE(INDIRECT("'"&A$31&"'!"&"B17:F17")),"")} | R31: {=IF(INDIRECT("'"&A$31&"'!"&"B10") ="",INDIRECT("'"&A$31&"'!"&"C10"),INDIRECT("'"&A$31&"'!"&"B10"))} -> 0.474875 | S31: {=IFERROR(AVERAGE(INDIRECT("'"&A$31&"'!"&"B10:F10")),"")} -> 0.094975 | T31: =R31*4 -> 1.8995 | U31: =S31*4 -> 0.3799 | V31: {=IF(INDIRECT("'"&A$31&"'!"&"B15") ="",INDIRECT("'"&A$31&"'!"&"C15"),INDIRECT("'"&A$31&"'!"&"B15"))} | W31: {=IFERROR(AVERAGE(INDIRECT("'"&A$31&"'!"&"B15:F15")),"")} | X31: {=IF(INDIRECT("'"&A$31&"'!"&"B5") ="",INDIRECT("'"&A$31&"'!"&"C5"),INDIRECT("'"&A$31&"'!"&"B5"))} | Y31: {=IFERROR(AVERAGE(INDIRECT("'"&A$31&"'!"&"B5:F5")),"")} | Z31: {=IF(INDIRECT("'"&A$31&"'!"&"B7") ="",INDIRECT("'"&A$31&"'!"&"C7"),INDIRECT("'"&A$31&"'!"&"B7"))} | AA31: {=IFERROR(AVERAGE(INDIRECT("'"&A$31&"'!"&"B7:F7")),"")} | AB31: =IFERROR((G31/(L31/E31))-1,"") | AC31: =IFERROR(U31/G31,"") -> 0.018995 | AD31: =IFERROR(IF(M31-L31=0,"",M31-L31),"") | AE31: =IFERROR(IF(M31-K31=0,"",M31-K31),"") | AF31: =IF(P31>0,IFERROR((P31/G31)-1,""),"") | AG31: =IFERROR(T31/G31,"") -> 0.094975 | AI31: {=IF(INDIRECT("'"&A$31&"'!"&"B16") ="",INDIRECT("'"&A$31&"'!"&"C16"),INDIRECT("'"&A$31&"'!"&"B16"))} | AJ31: {=IFERROR(AVERAGE(INDIRECT("'"&A$31&"'!"&"B16:F16")),"")} | AK31: =AVERAGE(AG31:AJ31) -> 0.094975 | AL31: =IFERROR(IF(R31*E31=0,"",R31*E31),"") | AM31: =IFERROR(IF(S31*E31=0,"",S31*E31),"") | AN31: =IFERROR(IF(T31*E31=0,"",T31*E31),"") | AO31: =IFERROR(IF(U31*E31=0,"",U31*E31),"") | AP31: =IF(AC31*D31=0,"",AC31*D31)
A32: FMX23 | B32: FIBRA eMX | C32: {=IF(INDIRECT("'"&A$32&"'!"&"B10") ="",INDIRECT("'"&A$32&"'!"&"C1"),INDIRECT("'"&A$32&"'!"&"B1"))} -> 2022 Q4 | D32: =IFERROR(E32/SUM(E13:E35),0) -> 0 | E32: =SUMIFS(COMPRAS!B:B,COMPRAS!A:A,B32) -> 0 | F32: =IFERROR(AVERAGEIFS(COMPRAS!C:C,COMPRAS!A:A,B32),0) -> 0 | G32: =yahooF(A32&".MX",1) -> #ERROR! | H32: =IFERROR(__xludf.DUMMYFUNCTION("IFERROR(G32,(GOOGLEFINANCE(A32,""high52"") + GOOGLEFINANCE(A32,""low52""))/2)"),35.45) -> 35.45 | I32: =yahooF(A32&".MX",2) -> #ERROR! | J32: 2265 | K32: =E32*F32 -> 0 | L32: =IFERROR(SUMIFS(COMPRAS!G:G,COMPRAS!A:A,B32),0) -> 0 | M32: =E32*G32 -> #ERROR! | N32: {=IF(INDIRECT("'"&A$32&"'!"&"B12") ="",INDIRECT("'"&A$32&"'!"&"C12"),INDIRECT("'"&A$32&"'!"&"B12"))} | O32: {=IFERROR(AVERAGE(INDIRECT("'"&A$32&"'!"&"B12:F12")),"")} | P32: {=IF(INDIRECT("'"&A$32&"'!"&"B17") ="",INDIRECT("'"&A$32&"'!"&"C17"),INDIRECT("'"&A$32&"'!"&"B17"))} | Q32: {=IFERROR(AVERAGE(INDIRECT("'"&A$32&"'!"&"B17:F17")),"")} | R32: {=IF(INDIRECT("'"&A$32&"'!"&"B10") ="",INDIRECT("'"&A$32&"'!"&"C10"),INDIRECT("'"&A$32&"'!"&"B10"))} | S32: {=IFERROR(AVERAGE(INDIRECT("'"&A$32&"'!"&"B10:F10")),"")} | T32: =R32*4 -> 0 | U32: =S32*4 -> 0 | V32: {=IF(INDIRECT("'"&A$32&"'!"&"B15") ="",INDIRECT("'"&A$32&"'!"&"C15"),INDIRECT("'"&A$32&"'!"&"B15"))} | W32: {=IFERROR(AVERAGE(INDIRECT("'"&A$32&"'!"&"B15:F15")),"")} | X32: {=IF(INDIRECT("'"&A$32&"'!"&"B5") ="",INDIRECT("'"&A$32&"'!"&"C5"),INDIRECT("'"&A$32&"'!"&"B5"))} | Y32: {=IFERROR(AVERAGE(INDIRECT("'"&A$32&"'!"&"B5:F5")),"")} | Z32: {=IF(INDIRECT("'"&A$32&"'!"&"B7") ="",INDIRECT("'"&A$32&"'!"&"C7"),INDIRECT("'"&A$32&"'!"&"B7"))} | AA32: {=IFERROR(AVERAGE(INDIRECT("'"&A$32&"'!"&"B7:F7")),"")} | AB32: =IFERROR((G32/(L32/E32))-1,"") | AC32: =IFERROR(U32/G32,"") | AD32: =IFERROR(IF(M32-L32=0,"",M32-L32),"") | AE32: =IFERROR(IF(M32-K32=0,"",M32-K32),"") | AF32: =IF(P32>0,IFERROR((P32/G32)-1,""),"") | AG32: =IFERROR(T32/G32,"") | AI32: {=IF(INDIRECT("'"&A$32&"'!"&"B16") ="",INDIRECT("'"&A$32&"'!"&"C16"),INDIRECT("'"&A$32&"'!"&"B16"))} | AJ32: {=IFERROR(AVERAGE(INDIRECT("'"&A$32&"'!"&"B16:F16")),"")} | AK32: =AVERAGE(AG32:AJ32) -> #DIV/0! | AL32: =IFERROR(IF(R32*E32=0,"",R32*E32),"") | AM32: =IFERROR(IF(S32*E32=0,"",S32*E32),"") | AN32: =IFERROR(IF(T32*E32=0,"",T32*E32),"") | AO32: =IFERROR(IF(U32*E32=0,"",U32*E32),"") | AP32: =IF(AC32*D32=0,"",AC32*D32)
A33: AGRO22 | B33: FIBRA AGRO | C33: {=IF(INDIRECT("'"&A$33&"'!"&"B10") ="",INDIRECT("'"&A$33&"'!"&"C1"),INDIRECT("'"&A$3&"'!"&"B1"))} -> 2022 Q4 | D33: =IFERROR(E33/SUM(E13:E35),0) -> 0 | E33: 0 | F33: 40 | G33: =IFERROR(yahooF(A33&".MX",1),F33) -> 40 | H33: =IFERROR(__xludf.DUMMYFUNCTION("IFERROR(G33,(GOOGLEFINANCE(A33,""high52"") + GOOGLEFINANCE(A33,""low52""))/2)"),40.0) -> 40 | I33: ? | J33: ? | K33: =E33*F33 -> 0 | L33: =IFERROR(SUMIFS(COMPRAS!G:G,COMPRAS!A:A,B33),0) -> 0 | M33: =E33*G33 -> 0 | T33: =R33*4 -> 0 | U33: =S33*4 -> 0 | AC33: =IFERROR(U33/G33,"") -> 0 | AG33: =IFERROR(T33/G33,"") -> 0 | AK33: =AVERAGE(AG33:AJ33) -> 0 | AO33: =IFERROR(IF(U33*E33=0,"",U33*E33),"")
A37: FIBRATC14 | B37: ETF FIBRA TC | E37: =SUMIFS(COMPRAS!B:B,COMPRAS!A:A,B37) -> 0 | F37: =IFERROR(AVERAGEIFS(COMPRAS!C:C,COMPRAS!A:A,B37),0) -> 21.486667 | G37: =IFERROR(__xludf.DUMMYFUNCTION("GOOGLEFINANCE(A37,""price"")"),30.2) -> 30.2 | I37: =IFERROR(__xludf.DUMMYFUNCTION("GOOGLEFINANCE(A37,""changepct"")"),3.07) -> 3.07 | J37: =IFERROR(__xludf.DUMMYFUNCTION("GOOGLEFINANCE(A37,""volume"")"),5581.0) -> 5581 | K37: =E37*F37 -> 0 | L37: =IFERROR(SUMIFS(COMPRAS!G:G,COMPRAS!A:A,B37),0) -> 21.8023 | M37: =E37*G37 -> 0 | R37: {=IF(INDIRECT("'"&A$30&"'!"&"B10") ="",INDIRECT("'"&A$30&"'!"&"C10"),INDIRECT("'"&A$30&"'!"&"B10"))} -> 0.1246 | S37: {=IFERROR(AVERAGE(INDIRECT("'"&A$30&"'!"&"B10:F10")),"")} -> 0.17365 | T37: =S37*4 -> 0.6946 | U37: =S37*4 -> 0.6946 | AB37: =IFERROR((G37/(L37/E37))-1,"") | AC37: =IFERROR((G37/F37)-1,"") -> 0.4055228 | AD37: =IFERROR(IF(M37-L37=0,"",M37-L37),"") -> -21.8023 | AE37: =IFERROR(IF(M37-K37=0,"",M37-K37),"") | AG37: =IFERROR(T37/G37,"") -> 0.023 | AH37: =IFERROR(U37/G37,"") -> 0.023 | AL37: =IFERROR(IF(R37*E37=0,"",R37*E37),"") | AM37: =IFERROR(IF(S37*E37=0,"",S37*E37),"") | AN37: =IFERROR(IF(T37*E37=0,"",T37*E37),"") | AO37: =IFERROR(IF(U37*E37=0,"",U37*E37),"") | AP37: =IF(AH37*D37=0,"",AH37*D37)

Sheet COMPRAS
A1: FIBRA | B1: Cantidad | C1: Costo Promedio | D1: Valor Compra | E1: Fecha de compra | G1: Costo Real | H1: Costo de Venta
A2: ETF FIBRA TC | B2: 45 | C2: 21.64 | D2: =B2*C2 -> 973.8 | E2: 44995 | F2: =IF(IF(ROUNDUP(MONTH(E2)/3,0)-1=0,4,ROUNDUP(MONTH(E2)/3,0)-1)=4,YEAR(E2)-1,YEAR(E2)) & " Q" & IF(ROUNDUP(MONTH(E2)/3,0)-1=0,4,ROUNDUP(MONTH(E2)/3,0)-1) -> 2022 Q4 | G2: =IF(B2>0,D2*1.0031,0) -> 976.81878
A3: FIBRA MONTEREY | B3: 4 | C3: 12.22 | D3: =B3*C3 -> 48.88 | E3: 45010 | F3: =IF(IF(ROUNDUP(MONTH(E3)/3,0)-1=0,4,ROUNDUP(MONTH(E3)/3,0)-1)=4,YEAR(E3)-1,YEAR(E3)) & " Q" & IF(ROUNDUP(MONTH(E3)/3,0)-1=0,4,ROUNDUP(MONTH(E3)/3,0)-1) -> 2022 Q4 | G3: =IF(B3>0,D3*1.0031,0) -> 49.031528 | K3: INVERSIÓN PORTAFOLIO | L3: =SUM(D:D) -> 10945.31
A4: FIBRA DAHNOS | B4: 22 | C4: 23.63 | D4: =B4*C4 -> 519.86 | E4: 45031 | F4: =IF(IF(ROUNDUP(MONTH(E4)/3,0)-1=0,4,ROUNDUP(MONTH(E4)/3,0)-1)=4,YEAR(E4)-1,YEAR(E4)) & " Q" & IF(ROUNDUP(MONTH(E4)/3,0)-1=0,4,ROUNDUP(MONTH(E4)/3,0)-1) -> 2023 Q1 | G4: =IF(B4>0,D4*1.0031,0) -> 521.47157
A5: FIBRA CFE | B5: 10 | C5: 26.95 | D5: =B5*C5 -> 269.5 | E5: 45031 | F5: =IF(IF(ROUNDUP(MONTH(E5)/3,0)-1=0,4,ROUNDUP(MONTH(E5)/3,0)-1)=4,YEAR(E5)-1,YEAR(E5)) & " Q" & IF(ROUNDUP(MONTH(E5)/3,0)-1=0,4,ROUNDUP(MONTH(E5)/3,0)-1) -> 2023 Q1 | G5: =IF(B5>0,D5*1.0031,0) -> 270.33545
A6: FIBRA HIPOTECARIA | B6: 1 | C6: 16.7 | D6: =B6*C6 -> 16.7 | E6: 45031 | F6: =IF(IF(ROUNDUP(MONTH(E6)/3,0)-1=0,4,ROUNDUP(MONTH(E6)/3,0)-1)=4,YEAR(E6)-1,YEAR(E6)) & " Q" & IF(ROUNDUP(MONTH(E6)/3,0)-1=0,4,ROUNDUP(MONTH(E6)/3,0)-1) -> 2023 Q1 | G6: =IF(B6>0,D6*1.0031,0) -> 16.75177 | J6: Inversion a simular | K6: Clave | L6: FIBRA | M6: % De Compra | N6: CBFIs Adicionales | O6: Sobrantes | P6: Precio de Mercado | Q6: Distribución Trimestral por CBFI | R6: AVG Distribución Trimestral por CBFI | S6: Renta Brutal Trimestral Adicional | T6: AVG Renta Brutal Trimestral Adicional | U6: Renta Bruta Mensual Adicional | V6: AVG Renta Bruta Mensual Adiciona | W6: Renta Bruta Anual Adicional | X6: AVG Renta Bruta Anual Adiciona | Y6: Ganancia Anual
A7: FIBRA MACQUARIE | B7: 4 | C7: 29.27 | D7: =B7*C7 -> 117.08 | E7: 45031 | F7: =IF(IF(ROUNDUP(MONTH(E7)/3,0)-1=0,4,ROUNDUP(MONTH(E7)/3,0)-1)=4,YEAR(E7)-1,YEAR(E7)) & " Q" & IF(ROUNDUP(MONTH(E7)/3,0)-1=0,4,ROUNDUP(MONTH(E7)/3,0)-1) -> 2023 Q1 | G7: =IF(B7>0,D7*1.0031,0) -> 117.44295 | K7: FUNO11 | L7: FIBRA UNO | M7: =IFERROR(J7/SUM(J$7:J$30),0) -> 0 | N7: =ROUNDDOWN(J7/P7,0) -> 0 | O7: =(J7/P7-N7)*P7 -> 0 | P7: =IFERROR(__xludf.DUMMYFUNCTION("GOOGLEFINANCE(K7,""price"")"),29.73) -> 29.73 | Q7: =IF(INDIRECT("'"&K7&"'!"&"B10") ="",INDIRECT("'"&K7&"'!"&"C10"),INDIRECT("'"&K7&"'!"&"B10")) -> 0.389133 | R7: =IFERROR(AVERAGE(INDIRECT("'"&K7&"'!"&"B10:F10")),0) -> 0.6180646 | S7: =N7*Q7 -> 0 | T7: =N7*R7 -> 0 | U7: =S7/3 -> 0 | V7: =T7/3 -> 0 | W7: =U7*12 -> 0 | X7: =V7*12 -> 0 | Y7: =IFERROR(X7/J7,"")
A8: FIBRA INN | B8: 5 | C8: 5.71 | D8: =B8*C8 -> 28.55 | E8: 45031 | F8: =IF(IF(ROUNDUP(MONTH(E8)/3,0)-1=0,4,ROUNDUP(MONTH(E8)/3,0)-1)=4,YEAR(E8)-1,YEAR(E8)) & " Q" & IF(ROUNDUP(MONTH(E8)/3,0)-1=0,4,ROUNDUP(MONTH(E8)/3,0)-1) -> 2023 Q1 | G8: =IF(B8>0,D8*1.0031,0) -> 28.638505 | K8: FMTY14 | L8: FIBRA MONTEREY | M8: =IFERROR(J8/SUM(J$7:J$30),0) -> 0 | N8: =ROUNDDOWN(J8/P8,0) -> 0 | O8: =(J8/P8-N8)*P8 -> 0 | P8: =IFERROR(__xludf.DUMMYFUNCTION("GOOGLEFINANCE(K8,""price"")"),14.61) -> 14.61 | Q8: =IF(INDIRECT("'"&K8&"'!"&"B10") ="",INDIRECT("'"&K8&"'!"&"C10"),INDIRECT("'"&K8&"'!"&"B10")) -> 0 | R8: =IFERROR(AVERAGE(INDIRECT("'"&K8&"'!"&"B10:F10")),0) -> 0.2125466 | S8: =N8*Q8 -> 0 | T8: =N8*R8 -> 0 | U8: =S8/3 -> 0 | V8: =T8/3 -> 0 | W8: =U8*12 -> 0 | X8: =V8*12 -> 0 | Y8: =IFERROR(X8/J8,"")
A9: FIBRA MONTEREY | B9: 27 | C9: 12.22 | D9: =B9*C9 -> 329.94 | E9: 45031 | F9: =IF(IF(ROUNDUP(MONTH(E9)/3,0)-1=0,4,ROUNDUP(MONTH(E9)/3,0)-1)=4,YEAR(E9)-1,YEAR(E9)) & " Q" & IF(ROUNDUP(MONTH(E9)/3,0)-1=0,4,ROUNDUP(MONTH(E9)/3,0)-1) -> 2023 Q1 | G9: =IF(B9>0,D9*1.0031,0) -> 330.96281 | K9: FIBRAMQ12 | L9: FIBRA MACQUARIE | M9: =IFERROR(J9/SUM(J$7:J$30),0) -> 0 | N9: =ROUNDDOWN(J9/P9,0) -> 0 | O9: =(J9/P9-N9)*P9 -> 0 | P9: =IFERROR(__xludf.DUMMYFUNCTION("GOOGLEFINANCE(K9,""price"")"),43.51) -> 43.51 | Q9: =IF(INDIRECT("'"&K9&"'!"&"B10") ="",INDIRECT("'"&K9&"'!"&"C10"),INDIRECT("'"&K9&"'!"&"B10")) -> 0.525 | R9: =IFERROR(AVERAGE(INDIRECT("'"&K9&"'!"&"B10:F10")),0) -> 0.6807648 | S9: =N9*Q9 -> 0 | T9: =N9*R9 -> 0 | U9: =S9/3 -> 0 | V9: =T9/3 -> 0 | W9: =U9*12 -> 0 | X9: =V9*12 -> 0 | Y9: =IFERROR(X9/J9,"")
A10: FIBRA NOVA | B10: 3 | C10: 31.54 | D10: =B10*C10 -> 94.62 | E10: 45031 | F10: =IF(IF(ROUNDUP(MONTH(E10)/3,0)-1=0,4,ROUNDUP(MONTH(E10)/3,0)-1)=4,YEAR(E10)-1,YEAR(E10)) & " Q" & IF(ROUNDUP(MONTH(E10)/3,0)-1=0,4,ROUNDUP(MONTH(E10)/3,0)-1) -> 2023 Q1 | G10: =IF(B10>0,D10*1.0031,0) -> 94.913322 | K10: DANHOS13 | L10: FIBRA DAHNOS | M10: =IFERROR(J10/SUM(J$7:J$30),0) -> 0 | N10: =ROUNDDOWN(J10/P10,0) -> 0 | O10: =(J10/P10-N10)*P10 -> 0 | P10: =IFERROR(__xludf.DUMMYFUNCTION("GOOGLEFINANCE(K10,""price"")"),27.34) -> 27.34 | Q10: =IF(INDIRECT("'"&K10&"'!"&"B10") ="",INDIRECT("'"&K10&"'!"&"C10"),INDIRECT("'"&K10&"'!"&"B10")) -> 0.6 | R10: =IFERROR(AVERAGE(INDIRECT("'"&K10&"'!"&"B10:F10")),0) -> 0.6 | S10: =N10*Q10 -> 0 | T10: =N10*R10 -> 0 | U10: =S10/3 -> 0 | V10: =T10/3 -> 0 | W10: =U10*12 -> 0 | X10: =V10*12 -> 0 | Y10: =IFERROR(X10/J10,"")
A11: FIBRA PLUS | B11: 7 | C11: 6.79 | D11: =B11*C11 -> 47.53 | E11: 45032 | F11: =IF(IF(ROUNDUP(MONTH(E11)/3,0)-1=0,4,ROUNDUP(MONTH(E11)/3,0)-1)=4,YEAR(E11)-1,YEAR(E11)) & " Q" & IF(ROUNDUP(MONTH(E11)/3,0)-1=0,4,ROUNDUP(MONTH(E11)/3,0)-1) -> 2023 Q1 | G11: =IF(B11>0,D11*1.0031,0) -> 47.677343 | K11: FIBRAUP18 | L11: FIBRA UPSITE | M11: =IFERROR(J11/SUM(J$7:J$30),0) -> 0 | N11: =ROUNDDOWN(J11/P11,0) -> 0 | O11: =(J11/P11-N11)*P11 -> 0 | P11: =IFERROR(__xludf.DUMMYFUNCTION("GOOGLEFINANCE(K11,""price"")"),38.8) -> 38.8 | Q11: =IF(INDIRECT("'"&K11&"'!"&"B10") ="",INDIRECT("'"&K11&"'!"&"C10"),INDIRECT("'"&K11&"'!"&"B10")) -> 0 | R11: =IFERROR(AVERAGE(INDIRECT("'"&K11&"'!"&"B10:F10")),0) -> 0 | S11: =N11*Q11 -> 0 | T11: =N11*R11 -> 0 | U11: =S11/3 -> 0 | V11: =T11/3 -> 0 | W11: =U11*12 -> 0 | X11: =V11*12 -> 0 | Y11: =IFERROR(X11/J11,"")
A12: FIBRA SHOP | B12: 3 | C12: 6.22 | D12: =B12*C12 -> 18.66 | E12: 45033 | F12: =IF(IF(ROUNDUP(MONTH(E12)/3,0)-1=0,4,ROUNDUP(MONTH(E12)/3,0)-1)=4,YEAR(E12)-1,YEAR(E12)) & " Q" & IF(ROUNDUP(MONTH(E12)/3,0)-1=0,4,ROUNDUP(MONTH(E12)/3,0)-1) -> 2023 Q1 | G12: =IF(B12>0,D12*1.0031,0) -> 18.717846 | K12: FNOVA17 | L12: FIBRA NOVA | M12: =IFERROR(J12/SUM(J$7:J$30),0) -> 0 | N12: =ROUNDDOWN(J12/P12,0) -> #N/A | O12: =(J12/P12-N12)*P12 -> #N/A | P12: =IFERROR(__xludf.DUMMYFUNCTION("GOOGLEFINANCE(K12,""price"")"),"#N/A") -> #N/A | Q12: =IF(INDIRECT("'"&K12&"'!"&"B10") ="",INDIRECT("'"&K12&"'!"&"C10"),INDIRECT("'"&K12&"'!"&"B10")) -> 0.5797 | R12: =IFERROR(AVERAGE(INDIRECT("'"&K12&"'!"&"B10:F10")),0) -> 0.4594304 | S12: =N12*Q12 -> #N/A | T12: =N12*R12 -> #N/A | U12: =S12/3 -> #N/A | V12: =T12/3 -> #N/A | W12: =U12*12 -> #N/A | X12: =V12*12 -> #N/A | Y12: =IFERROR(X12/J12,"")
A13: FIBRA UNO | B13: 27 | C13: 24.7 | D13: =B13*C13 -> 666.9 | E13: 45034 | F13: =IF(IF(ROUNDUP(MONTH(E13)/3,0)-1=0,4,ROUNDUP(MONTH(E13)/3,0)-1)=4,YEAR(E13)-1,YEAR(E13)) & " Q" & IF(ROUNDUP(MONTH(E13)/3,0)-1=0,4,ROUNDUP(MONTH(E13)/3,0)-1) -> 2023 Q1 | G13: =IF(B13>0,D13*1.0031,0) -> 668.96739 | K13: FPLUS16 | L13: FIBRA PLUS | M13: =IFERROR(J13/SUM(J$7:J$30),0) -> 0 | N13: =ROUNDDOWN(J13/P13,0) -> 0 | O13: =(J13/P13-N13)*P13 -> 0 | P13: =IFERROR(__xludf.DUMMYFUNCTION("GOOGLEFINANCE(K13,""price"")"),5.02) -> 5.02 | Q13: =IF(INDIRECT("'"&K13&"'!"&"B10") ="",INDIRECT("'"&K13&"'!"&"C10"),INDIRECT("'"&K13&"'!"&"B10")) -> 0.0868 | R13: =IFERROR(AVERAGE(INDIRECT("'"&K13&"'!"&"B10:F10")),0) -> 0.01736 | S13: =N13*Q13 -> 0 | T13: =N13*R13 -> 0 | U13: =S13/3 -> 0 | V13: =T13/3 -> 0 | W13: =U13*12 -> 0 | X13: =V13*12 -> 0 | Y13: =IFERROR(X13/J13,"")
A14: FIBRA UNO | B14: 7 | C14: 24.66 | D14: =B14*C14 -> 172.62 | E14: 45035 | F14: =IF(IF(ROUNDUP(MONTH(E14)/3,0)-1=0,4,ROUNDUP(MONTH(E14)/3,0)-1)=4,YEAR(E14)-1,YEAR(E14)) & " Q" & IF(ROUNDUP(MONTH(E14)/3,0)-1=0,4,ROUNDUP(MONTH(E14)/3,0)-1) -> 2023 Q1 | G14: =IF(B14>0,D14*1.0031,0) -> 173.15512 | K14: FIBRAPL14 | L14: FIBRA PROLOGIS | M14: =IFERROR(J14/SUM(J$7:J$30),0) -> 0 | N14: =ROUNDDOWN(J14/P14,0) -> 0 | O14: =(J14/P14-N14)*P14 -> 0 | P14: =IFERROR(__xludf.DUMMYFUNCTION("GOOGLEFINANCE(K14,""price"")"),79.66) -> 79.66 | Q14: =IF(INDIRECT("'"&K14&"'!"&"B10") ="",INDIRECT("'"&K14&"'!"&"C10"),INDIRECT("'"&K14&"'!"&"B10")) -> 0.85 | R14: =IFERROR(AVERAGE(INDIRECT("'"&K14&"'!"&"B10:F10")),0) -> 0.644 | S14: =N14*Q14 -> 0 | T14: =N14*R14 -> 0 | U14: =S14/3 -> 0 | V14: =T14/3 -> 0 | W14: =U14*12 -> 0 | X14: =V14*12 -> 0 | Y14: =IFERROR(X14/J14,"")
A15: FIBRA PLUS | B15: 1 | C15: 6.18 | D15: =B15*C15 -> 6.18 | E15: 45036 | F15: =IF(IF(ROUNDUP(MONTH(E15)/3,0)-1=0,4,ROUNDUP(MONTH(E15)/3,0)-1)=4,YEAR(E15)-1,YEAR(E15)) & " Q" & IF(ROUNDUP(MONTH(E15)/3,0)-1=0,4,ROUNDUP(MONTH(E15)/3,0)-1) -> 2023 Q1 | G15: =IF(B15>0,D15*1.0031,0) -> 6.199158 | K15: TERRA13 | L15: FIBRA TERRAFINA | M15: =IFERROR(J15/SUM(J$7:J$30),0) -> 0 | N15: =ROUNDDOWN(J15/P15,0) -> #N/A | O15: =(J15/P15-N15)*P15 -> #N/A | P15: =IFERROR(__xludf.DUMMYFUNCTION("GOOGLEFINANCE(K15,""price"")"),"#N/A") -> #N/A | Q15: =IF(INDIRECT("'"&K15&"'!"&"B10") ="",INDIRECT("'"&K15&"'!"&"C10"),INDIRECT("'"&K15&"'!"&"B10")) -> 0.47 | R15: =IFERROR(AVERAGE(INDIRECT("'"&K15&"'!"&"B10:F10")),0) -> 0.472 | S15: =N15*Q15 -> #N/A | T15: =N15*R15 -> #N/A | U15: =S15/3 -> #N/A | V15: =T15/3 -> #N/A | W15: =U15*12 -> #N/A | X15: =V15*12 -> #N/A | Y15: =IFERROR(X15/J15,"")
A16: FIBRA MONTEREY | B16: 1 | C16: 12.14 | D16: =B16*C16 -> 12.14 | E16: 45048 | F16: =IF(IF(ROUNDUP(MONTH(E16)/3,0)-1=0,4,ROUNDUP(MONTH(E16)/3,0)-1)=4,YEAR(E16)-1,YEAR(E16)) & " Q" & IF(ROUNDUP(MONTH(E16)/3,0)-1=0,4,ROUNDUP(MONTH(E16)/3,0)-1) -> 2023 Q1 | G16: =IF(B16>0,D16*1.0031,0) -> 12.177634 | K16: FIHO12 | L16: FIBRA HOTEL | M16: =IFERROR(J16/SUM(J$7:J$30),0) -> 0 | N16: =ROUNDDOWN(J16/P16,0) -> 0 | O16: =(J16/P16-N16)*P16 -> 0 | P16: =IFERROR(__xludf.DUMMYFUNCTION("GOOGLEFINANCE(K16,""price"")"),7.8) -> 7.8 | Q16: =IF(INDIRECT("'"&K16&"'!"&"B10") ="",INDIRECT("'"&K16&"'!"&"C10"),INDIRECT("'"&K16&"'!"&"B10")) -> 0.125 | R16: =IFERROR(AVERAGE(INDIRECT("'"&K16&"'!"&"B10:F10")),0) -> 0.025 | S16: =N16*Q16 -> 0 | T16: =N16*R16 -> 0 | U16: =S16/3 -> 0 | V16: =T16/3 -> 0 | W16: =U16*12 -> 0 | X16: =V16*12 -> 0 | Y16: =IFERROR(X16/J16,"")
A17: FIBRA MACQUARIE | B17: 4 | C17: 28.86 | D17: =B17*C17 -> 115.44 | E17: 45048 | F17: =IF(IF(ROUNDUP(MONTH(E17)/3,0)-1=0,4,ROUNDUP(MONTH(E17)/3,0)-1)=4,YEAR(E17)-1,YEAR(E17)) & " Q" & IF(ROUNDUP(MONTH(E17)/3,0)-1=0,4,ROUNDUP(MONTH(E17)/3,0)-1) -> 2023 Q1 | G17: =IF(B17>0,D17*1.0031,0) -> 115.79786 | K17: FINN13 | L17: FIBRA INN | M17: =IFERROR(J17/SUM(J$7:J$30),0) -> 0 | N17: =ROUNDDOWN(J17/P17,0) -> 0 | O17: =(J17/P17-N17)*P17 -> 0 | P17: =IFERROR(__xludf.DUMMYFUNCTION("GOOGLEFINANCE(K17,""price"")"),5.1) -> 5.1 | Q17: =IF(INDIRECT("'"&K17&"'!"&"B10") ="",INDIRECT("'"&K17&"'!"&"C10"),INDIRECT("'"&K17&"'!"&"B10")) -> 0.04 | R17: =IFERROR(AVERAGE(INDIRECT("'"&K17&"'!"&"B10:F10")),0) -> 0.025138 | S17: =N17*Q17 -> 0 | T17: =N17*R17 -> 0 | U17: =S17/3 -> 0 | V17: =T17/3 -> 0 | W17: =U17*12 -> 0 | X17: =V17*12 -> 0 | Y17: =IFERROR(X17/J17,"")
A18: FIBRA DAHNOS | B18: 13 | C18: 23.9 | D18: =B18*C18 -> 310.7 | E18: 45049 | F18: =IF(IF(ROUNDUP(MONTH(E18)/3,0)-1=0,4,ROUNDUP(MONTH(E18)/3,0)-1)=4,YEAR(E18)-1,YEAR(E18)) & " Q" & IF(ROUNDUP(MONTH(E18)/3,0)-1=0,4,ROUNDUP(MONTH(E18)/3,0)-1) -> 2023 Q1 | G18: =IF(B18>0,D18*1.0031,0) -> 311.66317 | K18: EDUCA18 | L18: FIBRA EDUCA | M18: =IFERROR(J18/SUM(J$7:J$30),0) -> 0 | N18: =ROUNDDOWN(J18/P18,0) -> 0 | O18: =(J18/P18-N18)*P18 -> 0 | P18: =IFERROR(__xludf.DUMMYFUNCTION("GOOGLEFINANCE(K18,""price"")"),59.01) -> 59.01 | Q18: =IF(INDIRECT("'"&K18&"'!"&"B10") ="",INDIRECT("'"&K18&"'!"&"C10"),INDIRECT("'"&K18&"'!"&"B10")) -> 0.5702 | R18: =IFERROR(AVERAGE(INDIRECT("'"&K18&"'!"&"B10:F10")),0) -> 0.5706034 | S18: =N18*Q18 -> 0 | T18: =N18*R18 -> 0 | U18: =S18/3 -> 0 | V18: =T18/3 -> 0 | W18: =U18*12 -> 0 | X18: =V18*12 -> 0 | Y18: =IFERROR(X18/J18,"")
A19: FIBRA HIPOTECARIA | B19: 17 | C19: 16.47 | D19: =B19*C19 -> 279.99 | E19: 45049 | F19: =IF(IF(ROUNDUP(MONTH(E19)/3,0)-1=0,4,ROUNDUP(MONTH(E19)/3,0)-1)=4,YEAR(E19)-1,YEAR(E19)) & " Q" & IF(ROUNDUP(MONTH(E19)/3,0)-1=0,4,ROUNDUP(MONTH(E19)/3,0)-1) -> 2023 Q1 | G19: =IF(B19>0,D19*1.0031,0) -> 280.85797 | K19: FSHOP13 | L19: FIBRA SHOP | M19: =IFERROR(J19/SUM(J$7:J$30),0) -> 0 | N19: =ROUNDDOWN(J19/P19,0) -> 0 | O19: =(J19/P19-N19)*P19 -> 0 | P19: =IFERROR(__xludf.DUMMYFUNCTION("GOOGLEFINANCE(K19,""price"")"),12.49) -> 12.49 | Q19: =IF(INDIRECT("'"&K19&"'!"&"B10") ="",INDIRECT("'"&K19&"'!"&"C10"),INDIRECT("'"&K19&"'!"&"B10")) -> 0 | R19: =IFERROR(AVERAGE(INDIRECT("'"&K19&"'!"&"B10:F10")),0) -> 0.0218618 | S19: =N19*Q19 -> 0 | T19: =N19*R19 -> 0 | U19: =S19/3 -> 0 | V19: =T19/3 -> 0 | W19: =U19*12 -> 0 | X19: =V19*12 -> 0 | Y19: =IFERROR(X19/J19,"")
A20: ETF FIBRA TC | B20: -44 | C20: 21.64 | D20: =B20*C20 -> -952.16 | E20: 45049 | F20: =IF(IF(ROUNDUP(MONTH(E20)/3,0)-1=0,4,ROUNDUP(MONTH(E20)/3,0)-1)=4,YEAR(E20)-1,YEAR(E20)) & " Q" & IF(ROUNDUP(MONTH(E20)/3,0)-1=0,4,ROUNDUP(MONTH(E20)/3,0)-1) -> 2023 Q1 | G20: =IF(B20>0,D20*1.0031,(H20*B20)+I20) -> -955.01648 | H20: 21 | I20: =(H20-C20)*(B20*-1)+(D20*0.003) -> -31.01648 | K20: FCFE18 | L20: FIBRA CFE | M20: =IFERROR(J20/SUM(J$7:J$30),0) -> 0 | N20: =ROUNDDOWN(J20/P20,0) -> 0 | O20: =(J20/P20-N20)*P20 -> 0 | P20: =IFERROR(__xludf.DUMMYFUNCTION("GOOGLEFINANCE(K20,""price"")"),23.84) -> 23.84 | Q20: =IF(INDIRECT("'"&K20&"'!"&"B10") ="",INDIRECT("'"&K20&"'!"&"C10"),INDIRECT("'"&K20&"'!"&"B10")) -> 0.575 | R20: =IFERROR(AVERAGE(INDIRECT("'"&K20&"'!"&"B10:F10")),0) -> 0.7700312 | S20: =N20*Q20 -> 0 | T20: =N20*R20 -> 0 | U20: =S20/3 -> 0 | V20: =T20/3 -> 0 | W20: =U20*12 -> 0 | X20: =V20*12 -> 0 | Y20: =IFERROR(X20/J20,"")
A21: FIBRA CFE | B21: 22 | C21: 27.2 | D21: =B21*C21 -> 598.4 | E21: 45049 | F21: =IF(IF(ROUNDUP(MONTH(E21)/3,0)-1=0,4,ROUNDUP(MONTH(E21)/3,0)-1)=4,YEAR(E21)-1,YEAR(E21)) & " Q" & IF(ROUNDUP(MONTH(E21)/3,0)-1=0,4,ROUNDUP(MONTH(E21)/3,0)-1) -> 2023 Q1 | G21: =IF(B21>0,D21*1.0031,(H21*B21)+I21) -> 600.25504 | K21: SOMA21 | L21: FIBRA SOMA | M21: =IFERROR(J21/SUM(J$7:J$30),0) -> 0 | N21: =IFERROR(ROUNDDOWN(J21/P21,0),"") -> 0 | O21: =IFERROR((J21/P21-N21)*P21,"") -> 0 | P21: =IFERROR(__xludf.DUMMYFUNCTION("GOOGLEFINANCE(K21,""price"")"),50.0) -> 50 | Q21: =IF(INDIRECT("'"&K21&"'!"&"B10") ="",INDIRECT("'"&K21&"'!"&"C10"),INDIRECT("'"&K21&"'!"&"B10")) -> 0 | R21: =IFERROR(AVERAGE(INDIRECT("'"&K21&"'!"&"B10:F10")),0) -> 0.166 | S21: =N21*Q21 -> 0 | T21: =N21*R21 -> 0 | U21: =S21/3 -> 0 | V21: =T21/3 -> 0 | W21: =U21*12 -> 0 | X21: =V21*12 -> 0 | Y21: =IFERROR(X21/J21,"")
A22: FIBRA MONTEREY | B22: 1 | C22: 12.14 | D22: =B22*C22 -> 12.14 | E22: 45049 | F22: =IF(IF(ROUNDUP(MONTH(E22)/3,0)-1=0,4,ROUNDUP(MONTH(E22)/3,0)-1)=4,YEAR(E22)-1,YEAR(E22)) & " Q" & IF(ROUNDUP(MONTH(E22)/3,0)-1=0,4,ROUNDUP(MONTH(E22)/3,0)-1) -> 2023 Q1 | G22: =IF(B22>0,D22*1.0031,(H22*B22)+I22) -> 12.177634 | K22: STORAGE18 | L22: FIBRA STORAGE | M22: =IFERROR(J22/SUM(J$7:J$30),0) -> 0 | N22: =ROUNDDOWN(J22/P22,0) -> 0 | O22: =(J22/P22-N22)*P22 -> 0 | P22: =IFERROR(__xludf.DUMMYFUNCTION("GOOGLEFINANCE(K22,""price"")"),24.99) -> 24.99 | Q22: =IF(INDIRECT("'"&K22&"'!"&"B10") ="",INDIRECT("'"&K22&"'!"&"C10"),INDIRECT("'"&K22&"'!"&"B10")) -> 0 | R22: =IFERROR(AVERAGE(INDIRECT("'"&K22&"'!"&"B10:F10")),0) -> 0.0875 | S22: =N22*Q22 -> 0 | T22: =N22*R22 -> 0 | U22: =S22/3 -> 0 | V22: =T22/3 -> 0 | W22: =U22*12 -> 0 | X22: =V22*12 -> 0 | Y22: =IFERROR(X22/J22,"")
A23: FIBRA PLUS | B23: -7 | C23: 6.49 | D23: =B23*C23 -> -45.43 | E23: 45049 | F23: =IF(IF(ROUNDUP(MONTH(E23)/3,0)-1=0,4,ROUNDUP(MONTH(E23)/3,0)-1)=4,YEAR(E23)-1,YEAR(E23)) & " Q" & IF(ROUNDUP(MONTH(E23)/3,0)-1=0,4,ROUNDUP(MONTH(E23)/3,0)-1) -> 2023 Q1 | G23: =IF(B23>0,D23*1.0031,(H23*B23)+I23) -> -45.56629 | H23: 6.1 | I23: =(H23-C23)*(B23*-1)+(D23*0.003) -> -2.86629 | K23: FSITES20 | L23: FIBRA TELESITES | M23: =IFERROR(J23/SUM(J$7:J$30),0) -> 0 | N23: =ROUNDDOWN(J23/P23,0) -> 0 | O23: =(J23/P23-N23)*P23 -> 0 | P23: =IFERROR(__xludf.DUMMYFUNCTION("GOOGLEFINANCE(K23,""price"")"),26.0) -> 26 | Q23: =IF(INDIRECT("'"&K23&"'!"&"B10") ="",INDIRECT("'"&K23&"'!"&"C10"),INDIRECT("'"&K23&"'!"&"B10")) -> 0.147633 | R23: =IFERROR(AVERAGE(INDIRECT("'"&K23&"'!"&"B10:F10")),0) -> 0.181872 | S23: =N23*Q23 -> 0 | T23: =N23*R23 -> 0 | U23: =S23/3 -> 0 | V23: =T23/3 -> 0 | W23: =U23*12 -> 0 | X23: =V23*12 -> 0 | Y23: =IFERROR(X23/J23,"")
A24: FIBRA UNO | B24: 1 | C24: 24.58 | D24: =B24*C24 -> 24.58 | E24: 45049 | F24: =IF(IF(ROUNDUP(MONTH(E24)/3,0)-1=0,4,ROUNDUP(MONTH(E24)/3,0)-1)=4,YEAR(E24)-1,YEAR(E24)) & " Q" & IF(ROUNDUP(MONTH(E24)/3,0)-1=0,4,ROUNDUP(MONTH(E24)/3,0)-1) -> 2023 Q1 | G24: =IF(B24>0,D24*1.0031,(H24*B24)+I24) -> 24.656198 | K24: FHIPO14 | L24: FIBRA HIPOTECARIA | M24: =IFERROR(J24/SUM(J$7:J$30),0) -> 0 | N24: =ROUNDDOWN(J24/P24,0) -> #VALUE! | O24: =(J24/P24-N24)*P24 -> #VALUE! | P24: =IFERROR(yahooF(K24&".MX",1),L24) -> FIBRA HIPOTECARIA | Q24: =IF(INDIRECT("'"&K24&"'!"&"B10") ="",INDIRECT("'"&K24&"'!"&"C10"),INDIRECT("'"&K24&"'!"&"B10")) -> 0.2566 | R24: =IFERROR(AVERAGE(INDIRECT("'"&K24&"'!"&"B10:F10")),0) -> 0.5060862 | S24: =N24*Q24 -> #VALUE! | T24: =N24*R24 -> #VALUE! | U24: =S24/3 -> #VALUE! | V24: =T24/3 -> #VALUE! | W24: =U24*12 -> #VALUE! | X24: =V24*12 -> #VALUE! | Y24: =IFERROR(X24/J24,"")
A25: FIBRA INN | B25: -1 | C25: 5.71 | D25: =B25*C25 -> -5.71 | E25: 45049 | F25: =IF(IF(ROUNDUP(MONTH(E25)/3,0)-1=0,4,ROUNDUP(MONTH(E25)/3,0)-1)=4,YEAR(E25)-1,YEAR(E25)) & " Q" & IF(ROUNDUP(MONTH(E25)/3,0)-1=0,4,ROUNDUP(MONTH(E25)/3,0)-1) -> 2023 Q1 | G25: =IF(B25>0,D25*1.0031,(H25*B25)+I25) -> -5.72713 | H25: 5.6 | I25: =(H25-C25)*(B25*-1)+(D25*0.003) -> -0.12713 | K25: FVIA16 | L25: FIBRA VIA | M25: =IFERROR(J25/SUM(J$7:J$30),0) -> 0 | N25: =ROUNDDOWN(J25/P25,0) -> 0 | O25: =(J25/P25-N25)*P25 -> 0 | P25: =IFERROR(__xludf.DUMMYFUNCTION("GOOGLEFINANCE(K25,""price"")"),19.5) -> 19.5 | Q25: =IF(INDIRECT("'"&K25&"'!"&"B10") ="",INDIRECT("'"&K25&"'!"&"C10"),INDIRECT("'"&K25&"'!"&"B10")) -> 0.480904 | R25: =IFERROR(AVERAGE(INDIRECT("'"&K25&"'!"&"B10:F10")),0) -> 0.4712025 | S25: =N25*Q25 -> 0 | T25: =N25*R25 -> 0 | U25: =S25/3 -> 0 | V25: =T25/3 -> 0 | W25: =U25*12 -> 0 | X25: =V25*12 -> 0 | Y25: =IFERROR(X25/J25,"")
A26: FIBRA UNO | B26: 1 | C26: 24.63 | D26: =B26*C26 -> 24.63 | E26: 45049 | F26: =IF(IF(ROUNDUP(MONTH(E26)/3,0)-1=0,4,ROUNDUP(MONTH(E26)/3,0)-1)=4,YEAR(E26)-1,YEAR(E26)) & " Q" & IF(ROUNDUP(MONTH(E26)/3,0)-1=0,4,ROUNDUP(MONTH(E26)/3,0)-1) -> 2023 Q1 | G26: =IF(B26>0,D26*1.0031,(H26*B26)+I26) -> 24.706353 | K26: FIDEAL20 | L26: FIBRA IDEAL | M26: =IFERROR(J26/SUM(J$7:J$30),0) -> 0 | N26: =ROUNDDOWN(J26/P26,0) -> 0 | O26: =(J26/P26-N26)*P26 -> 0 | P26: =IFERROR(__xludf.DUMMYFUNCTION("GOOGLEFINANCE(K26,""price"")"),68.85) -> 68.85 | Q26: =IF(INDIRECT("'"&K26&"'!"&"B10") ="",INDIRECT("'"&K26&"'!"&"C10"),INDIRECT("'"&K26&"'!"&"B10")) -> 1.4136 | R26: =IFERROR(AVERAGE(INDIRECT("'"&K26&"'!"&"B10:F10")),0) -> 1.3759 | S26: =N26*Q26 -> 0 | T26: =N26*R26 -> 0 | U26: =S26/3 -> 0 | V26: =T26/3 -> 0 | W26: =U26*12 -> 0 | X26: =V26*12 -> 0 | Y26: =IFERROR(X26/J26,"")
A27: FIBRA MACQUARIE | B27: 4 | C27: 28.85 | D27: =B27*C27 -> 115.4 | E27: 45049 | F27: =IF(IF(ROUNDUP(MONTH(E27)/3,0)-1=0,4,ROUNDUP(MONTH(E27)/3,0)-1)=4,YEAR(E27)-1,YEAR(E27)) & " Q" & IF(ROUNDUP(MONTH(E27)/3,0)-1=0,4,ROUNDUP(MONTH(E27)/3,0)-1) -> 2023 Q1 | G27: =IF(B27>0,D27*1.0031,(H27*B27)+I27) -> 115.75774 | J27: 0 | K27: FEXI21 | L27: FIBRA EXI | M27: =IFERROR(J27/SUM(J$7:J$30),0) -> 0 | N27: =ROUNDDOWN(J27/P27,0) -> 0 | O27: =(J27/P27-N27)*P27 -> 0 | P27: =IFERROR(__xludf.DUMMYFUNCTION("GOOGLEFINANCE(K27,""price"")"),19.48) -> 19.48 | Q27: =IF(INDIRECT("'"&K27&"'!"&"B10") ="",INDIRECT("'"&K27&"'!"&"C10"),INDIRECT("'"&K27&"'!"&"B10")) -> 0.1246 | R27: =IFERROR(AVERAGE(INDIRECT("'"&K27&"'!"&"B10:F10")),0) -> 0.17365 | S27: =N27*Q27 -> 0 | T27: =N27*R27 -> 0 | U27: =S27/3 -> 0 | V27: =T27/3 -> 0 | W27: =U27*12 -> 0 | X27: =V27*12 -> 0 | Y27: =IFERROR(X27/J27,"")
A28: FIBRA DAHNOS | B28: 5 | C28: 23.9 | D28: =B28*C28 -> 119.5 | E28: 45049 | F28: =IF(IF(ROUNDUP(MONTH(E28)/3,0)-1=0,4,ROUNDUP(MONTH(E28)/3,0)-1)=4,YEAR(E28)-1,YEAR(E28)) & " Q" & IF(ROUNDUP(MONTH(E28)/3,0)-1=0,4,ROUNDUP(MONTH(E28)/3,0)-1) -> 2023 Q1 | G28: =IF(B28>0,D28*1.0031,(H28*B28)+I28) -> 119.87045 | J28: 0 | K28: FSOCIAL23 | L28: FIBRA SOCIAL | M28: =IFERROR(J28/SUM(J$7:J$30),0) -> 0 | N28: =ROUNDDOWN(J28/P28,0) -> 0 | O28: =(J28/P28-N28)*P28 -> 0 | P28: =IFERROR(yahooF(K28&".MX",1),20) -> 20 | Q28: =IF(INDIRECT("'"&K28&"'!"&"B10") ="",INDIRECT("'"&K28&"'!"&"C10"),INDIRECT("'"&K28&"'!"&"B10")) -> 0.474875 | R28: =IFERROR(AVERAGE(INDIRECT("'"&K28&"'!"&"B10:F10")),0) -> 0.094975 | S28: =N28*Q28 -> 0 | T28: =N28*R28 -> 0 | U28: =S28/3 -> 0 | V28: =T28/3 -> 0 | W28: =U28*12 -> 0 | X28: =V28*12 -> 0 | Y28: =IFERROR(X28/J28,"")
A29: FIBRA MACQUARIE | B29: 5 | C29: 28.63 | D29: =B29*C29 -> 143.15 | E29: 45049 | F29: =IF(IF(ROUNDUP(MONTH(E29)/3,0)-1=0,4,ROUNDUP(MONTH(E29)/3,0)-1)=4,YEAR(E29)-1,YEAR(E29)) & " Q" & IF(ROUNDUP(MONTH(E29)/3,0)-1=0,4,ROUNDUP(MONTH(E29)/3,0)-1) -> 2023 Q1 | G29: =IF(B29>0,D29*1.0031,(H29*B29)+I29) -> 143.59376 | J29: 0 | K29: FMX23 | L29: FIBRA eMX | M29: =IFERROR(J29/SUM(J$7:J$30),0) -> 0 | N29: =ROUNDDOWN(J29/P29,0) -> #VALUE! | O29: =(J29/P29-N29)*P29 -> #VALUE! | P29: =IFERROR(yahooF(K29&".MX",1),L29) -> FIBRA eMX | Q29: =IF(INDIRECT("'"&K29&"'!"&"B10") ="",INDIRECT("'"&K29&"'!"&"C10"),INDIRECT("'"&K29&"'!"&"B10")) | R29: =IFERROR(AVERAGE(INDIRECT("'"&K29&"'!"&"B10:F10")),0) -> 0 | S29: =N29*Q29 -> #VALUE! | T29: =N29*R29 -> #VALUE! | U29: =S29/3 -> #VALUE! | V29: =T29/3 -> #VALUE! | W29: =U29*12 -> #VALUE! | X29: =V29*12 -> #VALUE! | Y29: =IFERROR(X29/J29,"")
A30: FIBRA MACQUARIE | B30: 4 | C30: 28.47 | D30: =B30*C30 -> 113.88 | E30: 45049 | F30: =IF(IF(ROUNDUP(MONTH(E30)/3,0)-1=0,4,ROUNDUP(MONTH(E30)/3,0)-1)=4,YEAR(E30)-1,YEAR(E30)) & " Q" & IF(ROUNDUP(MONTH(E30)/3,0)-1=0,4,ROUNDUP(MONTH(E30)/3,0)-1) -> 2023 Q1 | G30: =IF(B30>0,D30*1.0031,(H30*B30)+I30) -> 114.23303 | J30: 0 | K30: AGRO22 | L30: FIBRA AGRO | M30: =IFERROR(J30/SUM(J$7:J$30),0) -> 0 | N30: =ROUNDDOWN(J30/P30,0) -> 0 | O30: =(J30/P30-N30)*P30 -> 0 | P30: 40 | Q30: =IF(INDIRECT("'"&K30&"'!"&"B10") ="",INDIRECT("'"&K30&"'!"&"C10"),INDIRECT("'"&K30&"'!"&"B10")) | R30: =IFERROR(AVERAGE(INDIRECT("'"&K30&"'!"&"B10:F10")),0) -> 0 | S30: =N30*Q30 -> 0 | T30: =N30*R30 -> 0 | U30: =S30/3 -> 0 | V30: =T30/3 -> 0 | W30: =U30*12 -> 0 | X30: =V30*12 -> 0 | Y30: =IFERROR(X30/J30,"")
A31: FIBRA DAHNOS | B31: 6 | C31: 23.53 | D31: =B31*C31 -> 141.18 | E31: 45049 | F31: =IF(IF(ROUNDUP(MONTH(E31)/3,0)-1=0,4,ROUNDUP(MONTH(E31)/3,0)-1)=4,YEAR(E31)-1,YEAR(E31)) & " Q" & IF(ROUNDUP(MONTH(E31)/3,0)-1=0,4,ROUNDUP(MONTH(E31)/3,0)-1) -> 2023 Q1 | G31: =IF(B31>0,D31*1.0031,(H31*B31)+I31) -> 141.61766 | J31: =SUM(J7:J30) -> 0 | M31: =SUM(M7:M30) -> 0 | O31: =SUM(O7:O30) -> #N/A | U31: =SUM(U7:U30) -> #N/A | V31: =SUM(V7:V30) -> #N/A | W31: =SUM(W7:W30) -> #N/A | X31: =SUM(X7:X30) -> #N/A | Y31: =X31/J31 -> #N/A
A32: FIBRA SHOP | B32: 1 | C32: 6.12 | D32: =B32*C32 -> 6.12 | E32: 45049 | F32: =IF(IF(ROUNDUP(MONTH(E32)/3,0)-1=0,4,ROUNDUP(MONTH(E32)/3,0)-1)=4,YEAR(E32)-1,YEAR(E32)) & " Q" & IF(ROUNDUP(MONTH(E32)/3,0)-1=0,4,ROUNDUP(MONTH(E32)/3,0)-1) -> 2023 Q1 | G32: =IF(B32>0,D32*1.0031,(H32*B32)+I32) -> 6.138972
A33: FIBRA UNO | B33: 9 | C33: 24.31 | D33: =B33*C33 -> 218.79 | E33: 45049 | F33: =IF(IF(ROUNDUP(MONTH(E33)/3,0)-1=0,4,ROUNDUP(MONTH(E33)/3,0)-1)=4,YEAR(E33)-1,YEAR(E33)) & " Q" & IF(ROUNDUP(MONTH(E33)/3,0)-1=0,4,ROUNDUP(MONTH(E33)/3,0)-1) -> 2023 Q1 | G33: =IF(B33>0,D33*1.0031,(H33*B33)+I33) -> 219.46825
A34: FIBRA MACQUARIE | B34: 1 | C34: 28.63 | D34: =B34*C34 -> 28.63 | E34: 45049 | F34: =IF(IF(ROUNDUP(MONTH(E34)/3,0)-1=0,4,ROUNDUP(MONTH(E34)/3,0)-1)=4,YEAR(E34)-1,YEAR(E34)) & " Q" & IF(ROUNDUP(MONTH(E34)/3,0)-1=0,4,ROUNDUP(MONTH(E34)/3,0)-1) -> 2023 Q1 | G34: =IF(B34>0,D34*1.0031,(H34*B34)+I34) -> 28.718753
A35: FIBRA HIPOTECARIA | B35: 1 | C35: 16.88 | D35: =B35*C35 -> 16.88 | E35: 45049 | F35: =IF(IF(ROUNDUP(MONTH(E35)/3,0)-1=0,4,ROUNDUP(MONTH(E35)/3,0)-1)=4,YEAR(E35)-1,YEAR(E35)) & " Q" & IF(ROUNDUP(MONTH(E35)/3,0)-1=0,4,ROUNDUP(MONTH(E35)/3,0)-1) -> 2023 Q1 | G35: =IF(B35>0,D35*1.0031,(H35*B35)+I35) -> 16.932328
A36: FIBRA MACQUARIE | B36: 10 | C36: 28.51 | D36: =B36*C36 -> 285.1 | E36: 45049 | F36: =IF(IF(ROUNDUP(MONTH(E36)/3,0)-1=0,4,ROUNDUP(MONTH(E36)/3,0)-1)=4,YEAR(E36)-1,YEAR(E36)) & " Q" & IF(ROUNDUP(MONTH(E36)/3,0)-1=0,4,ROUNDUP(MONTH(E36)/3,0)-1) -> 2023 Q1 | G36: =IF(B36>0,D36*1.0031,(H36*B36)+I36) -> 285.98381
A37: FIBRA MONTEREY | B37: 6 | C37: 11.99 | D37: =B37*C37 -> 71.94 | E37: 45049 | F37: =IF(IF(ROUNDUP(MONTH(E37)/3,0)-1=0,4,ROUNDUP(MONTH(E37)/3,0)-1)=4,YEAR(E37)-1,YEAR(E37)) & " Q" & IF(ROUNDUP(MONTH(E37)/3,0)-1=0,4,ROUNDUP(MONTH(E37)/3,0)-1) -> 2023 Q1 | G37: =IF(B37>0,D37*1.0031,(H37*B37)+I37) -> 72.163014
A38: FIBRA UNO | B38: 15 | C38: 24 | D38: =B38*C38 -> 360 | E38: 45049 | F38: =IF(IF(ROUNDUP(MONTH(E38)/3,0)-1=0,4,ROUNDUP(MONTH(E38)/3,0)-1)=4,YEAR(E38)-1,YEAR(E38)) & " Q" & IF(ROUNDUP(MONTH(E38)/3,0)-1=0,4,ROUNDUP(MONTH(E38)/3,0)-1) -> 2023 Q1 | G38: =IF(B38>0,D38*1.0031,(H38*B38)+I38) -> 361.116
A39: FIBRA NOVA | B39: 30 | C39: 29 | D39: =B39*C39 -> 870 | E39: 45049 | F39: =IF(IF(ROUNDUP(MONTH(E39)/3,0)-1=0,4,ROUNDUP(MONTH(E39)/3,0)-1)=4,YEAR(E39)-1,YEAR(E39)) & " Q" & IF(ROUNDUP(MONTH(E39)/3,0)-1=0,4,ROUNDUP(MONTH(E39)/3,0)-1) -> 2023 Q1 | G39: =IF(B39>0,D39*1.0031,(H39*B39)+I39) -> 872.697
A40: FIBRA CFE | B40: 4 | C40: 27.92 | D40: =B40*C40 -> 111.68 | E40: 45049 | F40: =IF(IF(ROUNDUP(MONTH(E40)/3,0)-1=0,4,ROUNDUP(MONTH(E40)/3,0)-1)=4,YEAR(E40)-1,YEAR(E40)) & " Q" & IF(ROUNDUP(MONTH(E40)/3,0)-1=0,4,ROUNDUP(MONTH(E40)/3,0)-1) -> 2023 Q1 | G40: =IF(B40>0,D40*1.0031,(H40*B40)+I40) -> 112.02621
A41: FIBRA MONTEREY | B41: 33 | C41: 11.88 | D41: =B41*C41 -> 392.04 | E41: 45049 | F41: =IF(IF(ROUNDUP(MONTH(E41)/3,0)-1=0,4,ROUNDUP(MONTH(E41)/3,0)-1)=4,YEAR(E41)-1,YEAR(E41)) & " Q" & IF(ROUNDUP(MONTH(E41)/3,0)-1=0,4,ROUNDUP(MONTH(E41)/3,0)-1) -> 2023 Q1 | G41: =IF(B41>0,D41*1.0031,(H41*B41)+I41) -> 393.25532
A42: FIBRA SHOP | B42: 1 | C42: 6.14 | D42: =B42*C42 -> 6.14 | E42: 45049 | F42: =IF(IF(ROUNDUP(MONTH(E42)/3,0)-1=0,4,ROUNDUP(MONTH(E42)/3,0)-1)=4,YEAR(E42)-1,YEAR(E42)) & " Q" & IF(ROUNDUP(MONTH(E42)/3,0)-1=0,4,ROUNDUP(MONTH(E42)/3,0)-1) -> 2023 Q1 | G42: =IF(B42>0,D42*1.0031,(H42*B42)+I42) -> 6.159034
A43: FIBRA NOVA | B43: 20 | C43: 29.31 | D43: =B43*C43 -> 586.2 | E43: 45049 | F43: =IF(IF(ROUNDUP(MONTH(E43)/3,0)-1=0,4,ROUNDUP(MONTH(E43)/3,0)-1)=4,YEAR(E43)-1,YEAR(E43)) & " Q" & IF(ROUNDUP(MONTH(E43)/3,0)-1=0,4,ROUNDUP(MONTH(E43)/3,0)-1) -> 2023 Q1 | G43: =IF(B43>0,D43*1.0031,(H43*B43)+I43) -> 588.01722
... A57: FIBRA CFE | B57: 8 | C57: 27.05 | D57: =B57*C57 -> 216.4 | E57: 45141 | F57: =IF(IF(ROUNDUP(MONTH(E57)/3,0)-1=0,4,ROUNDUP(MONTH(E57)/3,0)-1)=4,YEAR(E57)-1,YEAR(E57)) & " Q" & IF(ROUNDUP(MONTH(E57)/3,0)-1=0,4,ROUNDUP(MONTH(E57)/3,0)-1) -> 2023 Q2 | G57: =IF(B57>0,D57*1.0031,(H57*B57)+I57) -> 217.07084
A58: FIBRA HIPOTECARIA | B58: 20 | C58: 16.12 | D58: =B58*C58 -> 322.4 | E58: 45181 | F58: =IF(IF(ROUNDUP(MONTH(E58)/3,0)-1=0,4,ROUNDUP(MONTH(E58)/3,0)-1)=4,YEAR(E58)-1,YEAR(E58)) & " Q" & IF(ROUNDUP(MONTH(E58)/3,0)-1=0,4,ROUNDUP(MONTH(E58)/3,0)-1) -> 2023 Q2 | G58: =IF(B58>0,D58*1.0031,0) -> 323.39944
A59: FIBRA MONTEREY | B59: 67 | C59: 11.18 | D59: =B59*C59 -> 749.06 | E59: 45181 | F59: =IF(IF(ROUNDUP(MONTH(E59)/3,0)-1=0,4,ROUNDUP(MONTH(E59)/3,0)-1)=4,YEAR(E59)-1,YEAR(E59)) & " Q" & IF(ROUNDUP(MONTH(E59)/3,0)-1=0,4,ROUNDUP(MONTH(E59)/3,0)-1) -> 2023 Q2 | G59: =IF(B59>0,D59*1.0031,0) -> 751.38209
A60: FIBRA DAHNOS | B60: 9 | C60: 19.9 | D60: =B60*C60 -> 179.1 | E60: 45184 | F60: =IF(IF(ROUNDUP(MONTH(E60)/3,0)-1=0,4,ROUNDUP(MONTH(E60)/3,0)-1)=4,YEAR(E60)-1,YEAR(E60)) & " Q" & IF(ROUNDUP(MONTH(E60)/3,0)-1=0,4,ROUNDUP(MONTH(E60)/3,0)-1) -> 2023 Q2 | G60: =IF(B60>0,D60*1.0031,(H60*B60)+I60) -> 179.65521
A61: FIBRA DAHNOS | B61: 8 | C61: 19.59 | D61: =B61*C61 -> 156.72 | E61: 45196 | F61: =IF(IF(ROUNDUP(MONTH(E61)/3,0)-1=0,4,ROUNDUP(MONTH(E61)/3,0)-1)=4,YEAR(E61)-1,YEAR(E61)) & " Q" & IF(ROUNDUP(MONTH(E61)/3,0)-1=0,4,ROUNDUP(MONTH(E61)/3,0)-1) -> 2023 Q2 | G61: =IF(B61>0,D61*1.0031,(H61*B61)+I61) -> 157.20583
A62: FIBRA DAHNOS | B62: 7 | C62: 19.46 | D62: =B62*C62 -> 136.22 | E62: 45257 | F62: =IF(IF(ROUNDUP(MONTH(E62)/3,0)-1=0,4,ROUNDUP(MONTH(E62)/3,0)-1)=4,YEAR(E62)-1,YEAR(E62)) & " Q" & IF(ROUNDUP(MONTH(E62)/3,0)-1=0,4,ROUNDUP(MONTH(E62)/3,0)-1) -> 2023 Q3 | G62: =IF(B62>0,D62*1.0031,(H62*B62)+I62) -> 136.64228

Sheet DIVIDENDOS
A1: FIBRA | B1: Cantidad | C1: Dividendo por CBFI | D1: Pago bruto | E1: Pago neto | F1: Fecha de pago | G1: Trimestre | H1: Concepto de pago
A2: FIBRA MONTEREY | B2: 4 | C2: =FMTY14!C10/3 -> 0.102889 | D2: =B2*C2 -> 0.411556 | E2: =IF(H2="Reembolso de Capital",D2,D2*0.7) -> 0.411556 | F2: 45014 | G2: =IF(IF(ROUNDUP(MONTH(F2)/3,0)-1=0,4,ROUNDUP(MONTH(F2)/3,0)-1)=4,YEAR(F2)-1,YEAR(F2)) & " Q" & IF(ROUNDUP(MONTH(F2)/3,0)-1=0,4,ROUNDUP(MONTH(F2)/3,0)-1) -> 2022 Q4 | H2: =FMTY14_DIV!F2 -> Reembolso de Capital
A3: ETF FIBRA TC | B3: 45 | C3: =FIBRATC14_DIV!C2 -> 0.013681 | D3: =B3*C3 -> 0.615645 | E3: =IF(H3="Reembolso de Capital",D3,D3*0.7) -> 0.4309515 | F3: 45021 | G3: =IF(IF(ROUNDUP(MONTH(F3)/3,0)-1=0,4,ROUNDUP(MONTH(F3)/3,0)-1)=4,YEAR(F3)-1,YEAR(F3)) & " Q" & IF(ROUNDUP(MONTH(F3)/3,0)-1=0,4,ROUNDUP(MONTH(F3)/3,0)-1) -> 2023 Q1 | H3: Resultado Fiscal | J3: RENTAS ANUALES BRUTAS | M3: =SUM(D:D) -> 39.773589
A4: FIBRA PLUS | B4: 7 | C4: =FPLUS16!B10 -> 0.0868 | D4: =B4*C4 -> 0.6076 | E4: =IF(H4="Reembolso de Capital",D4,D4*0.7) -> 0.6076 | F4: 45037 | G4: =IF(IF(ROUNDUP(MONTH(F4)/3,0)-1=0,4,ROUNDUP(MONTH(F4)/3,0)-1)=4,YEAR(F4)-1,YEAR(F4)) & " Q" & IF(ROUNDUP(MONTH(F4)/3,0)-1=0,4,ROUNDUP(MONTH(F4)/3,0)-1) -> 2023 Q1 | H4: Reembolso de Capital
A5: FIBRA UNO | B5: 36 | C5: =FUNO11_DIV!C2 -> 0.389133 | D5: =B5*C5 -> 14.008788 | E5: =IF(H5="Reembolso de Capital",D5,D5*0.7) -> 9.8061516 | F5: 45051 | G5: =IF(IF(ROUNDUP(MONTH(F5)/3,0)-1=0,4,ROUNDUP(MONTH(F5)/3,0)-1)=4,YEAR(F5)-1,YEAR(F5)) & " Q" & IF(ROUNDUP(MONTH(F5)/3,0)-1=0,4,ROUNDUP(MONTH(F5)/3,0)-1) -> 2023 Q1 | H5: Resultado Fiscal
A6: ETF FIBRA TC | B6: 1 | C6: 0.11 | D6: =B6*C6 -> 0.11 | E6: =IF(H6="Reembolso de Capital",D6,D6*0.7) -> 0.077 | F6: 45051 | G6: =IF(IF(ROUNDUP(MONTH(F6)/3,0)-1=0,4,ROUNDUP(MONTH(F6)/3,0)-1)=4,YEAR(F6)-1,YEAR(F6)) & " Q" & IF(ROUNDUP(MONTH(F6)/3,0)-1=0,4,ROUNDUP(MONTH(F6)/3,0)-1) -> 2023 Q1 | H6: Resultado Fiscal | J6: RENTAS ANUALES NETAS | M6: =SUM(E:E) -> 31.039583
A7: ETF FIBRA TC | B7: 1 | C7: 0.02 | D7: =B7*C7 -> 0.02 | E7: =IF(H7="Reembolso de Capital",D7,D7*0.7) -> 0.02 | F7: 45051 | G7: =IF(IF(ROUNDUP(MONTH(F7)/3,0)-1=0,4,ROUNDUP(MONTH(F7)/3,0)-1)=4,YEAR(F7)-1,YEAR(F7)) & " Q" & IF(ROUNDUP(MONTH(F7)/3,0)-1=0,4,ROUNDUP(MONTH(F7)/3,0)-1) -> 2023 Q1 | H7: Reembolso de Capital
A8: FIBRA DAHNOS | B8: 40 | C8: =DANHOS13_DIV!C2 -> 0.240527 | D8: =B8*C8 -> 9.62108 | E8: =IF(H8="Reembolso de Capital",D8,D8*0.7) -> 9.62108 | F8: 45051 | G8: =IF(IF(ROUNDUP(MONTH(F8)/3,0)-1=0,4,ROUNDUP(MONTH(F8)/3,0)-1)=4,YEAR(F8)-1,YEAR(F8)) & " Q" & IF(ROUNDUP(MONTH(F8)/3,0)-1=0,4,ROUNDUP(MONTH(F8)/3,0)-1) -> 2023 Q1 | H8: Reembolso de Capital
A9: FIBRA DAHNOS | B9: 40 | C9: =DANHOS13_DIV!C3 -> 0.359473 | D9: =B9*C9 -> 14.37892 | E9: =IF(H9="Reembolso de Capital",D9,D9*0.7) -> 10.065244 | F9: 45051 | G9: =IF(IF(ROUNDUP(MONTH(F9)/3,0)-1=0,4,ROUNDUP(MONTH(F9)/3,0)-1)=4,YEAR(F9)-1,YEAR(F9)) & " Q" & IF(ROUNDUP(MONTH(F9)/3,0)-1=0,4,ROUNDUP(MONTH(F9)/3,0)-1) -> 2023 Q1 | H9: Resultado Fiscal

Sheet SEGMENTOS
P1: Portafolio
A2: Clave | B2: Fibra | C2: Participación | D2: Industrial | E2: Comercial | F2: Oficinas | G2: Agro | H2: Escuelas | I2: Hoteles | J2: Vivienda | K2: Carreteras | L2: Auto Almacenaje | M2: Hipotecas | N2: Energía | O2: Penitenciaria | P2: Industrial | Q2: Comercial | R2: Oficinas | S2: Agro | T2: Escuelas | U2: Hoteles | V2: Vivienda | W2: Carreteras | X2: Auto Almacenaje | Y2: Hipotecas | Z2: Energía | AA2: Penitenciaria
A3: FUNO11 | B3: FIBRA UNO | C3: =GENERAL!D13 -> 0.17045455 | D3: 0.31 | E3: 0.415 | F3: 0.275 | G3: 0 | H3: 0 | I3: 0 | J3: 0 | K3: 0 | L3: 0 | M3: 0 | N3: 0 | O3: 0 | P3: =C3*D3 -> 0.052840909 | Q3: =C3*E3 -> 0.070738636 | R3: =C3*F3 -> 0.046875 | S3: =C3*G3 -> 0 | T3: =C3*H3 -> 0 | U3: =C3*I3 -> 0 | V3: =C3*J3 -> 0 | W3: =C3*K3 -> 0 | X3: =C3*L3 -> 0 | Y3: =C3*M3 -> 0 | Z3: =C3*N3 -> 0 | AA3: =C3*O3 -> 0
A4: FMTY14 | B4: FIBRA MONTEREY | C4: =GENERAL!D14 -> 0.4375 | D4: 0.471 | E4: 0.029 | F4: 0.5 | G4: 0 | H4: 0 | I4: 0 | J4: 0 | K4: 0 | L4: 0 | M4: 0 | N4: 0 | O4: 0 | P4: =C4*D4 -> 0.2060625 | Q4: =C4*E4 -> 0.0126875 | R4: =C4*F4 -> 0.21875 | S4: =C4*G4 -> 0 | T4: =C4*H4 -> 0 | U4: =C4*I4 -> 0 | V4: =C4*J4 -> 0 | W4: =C4*K4 -> 0 | X4: =C4*L4 -> 0 | Y4: =C4*M4 -> 0 | Z4: =C4*N4 -> 0 | AA4: =C4*O4 -> 0
A5: FIBRAMQ12 | B5: FIBRA MACQUARIE | C5: =GENERAL!D16 -> 0.090909091 | D5: 0.86 | E5: 0.14 | F5: 0 | G5: 0 | H5: 0 | I5: 0 | J5: 0 | K5: 0 | L5: 0 | M5: 0 | N5: 0 | O5: 0 | P5: =C5*D5 -> 0.078181818 | Q5: =C5*E5 -> 0.012727273 | R5: =C5*F5 -> 0 | S5: =C5*G5 -> 0 | T5: =C5*H5 -> 0 | U5: =C5*I5 -> 0 | V5: =C5*J5 -> 0 | W5: =C5*K5 -> 0 | X5: =C5*L5 -> 0 | Y5: =C5*M5 -> 0 | Z5: =C5*N5 -> 0 | AA5: =C5*O5 -> 0
A6: DANHOS13 | B6: FIBRA DAHNOS | C6: =GENERAL!D12 -> 0.28409091 | D6: 0 | E6: 0.64 | F6: 0.36 | G6: 0 | H6: 0 | I6: 0 | J6: 0 | K6: 0 | L6: 0 | M6: 0 | N6: 0 | O6: 0 | P6: =C6*D6 -> 0 | Q6: =C6*E6 -> 0.18181818 | R6: =C6*F6 -> 0.10227273 | S6: =C6*G6 -> 0 | T6: =C6*H6 -> 0 | U6: =C6*I6 -> 0 | V6: =C6*J6 -> 0 | W6: =C6*K6 -> 0 | X6: =C6*L6 -> 0 | Y6: =C6*M6 -> 0 | Z6: =C6*N6 -> 0 | AA6: =C6*O6 -> 0
A7: FIBRAUP18 | B7: FIBRA UPSITE | C7: =GENERAL!D17 -> 0 | D7: 1 | E7: 0 | F7: 0 | G7: 0 | H7: 0 | I7: 0 | J7: 0 | K7: 0 | L7: 0 | M7: 0 | N7: 0 | O7: 0 | P7: =C7*D7 -> 0 | Q7: =C7*E7 -> 0 | R7: =C7*F7 -> 0 | S7: =C7*G7 -> 0 | T7: =C7*H7 -> 0 | U7: =C7*I7 -> 0 | V7: =C7*J7 -> 0 | W7: =C7*K7 -> 0 | X7: =C7*L7 -> 0 | Y7: =C7*M7 -> 0 | Z7: =C7*N7 -> 0 | AA7: =C7*O7 -> 0
A8: FNOVA17 | B8: FIBRA NOVA | C8: =GENERAL!D15 -> 0.21022727 | D8: 0.633 | E8: 0.044 | F8: 0 | G8: 0.204 | H8: 0.119 | I8: 0 | J8: 0 | K8: 0 | L8: 0 | M8: 0 | N8: 0 | O8: 0 | P8: =C8*D8 -> 0.13307386 | Q8: =C8*E8 -> 0.00925 | R8: =C8*F8 -> 0 | S8: =C8*G8 -> 0.042886364 | T8: =C8*H8 -> 0.025017045 | U8: =C8*I8 -> 0 | V8: =C8*J8 -> 0 | W8: =C8*K8 -> 0 | X8: =C8*L8 -> 0 | Y8: =C8*M8 -> 0 | Z8: =C8*N8 -> 0 | AA8: =C8*O8 -> 0
A9: FPLUS16 | B9: FIBRA PLUS | C9: =GENERAL!D21 -> 0.0028409091 | D9: 0.34 | E9: 0.21 | F9: 0.3 | G9: 0 | H9: 0 | I9: 0 | J9: 0.09 | K9: 0 | L9: 0 | M9: 0 | N9: 0 | O9: 0 | P9: =C9*D9 -> 0.00096590909 | Q9: =C9*E9 -> 0.00059659091 | R9: =C9*F9 -> 0.00085227273 | S9: =C9*G9 -> 0 | T9: =C9*H9 -> 0 | U9: =C9*I9 -> 0 | V9: =C9*J9 -> 0.00025568182 | W9: =C9*K9 -> 0 | X9: =C9*L9 -> 0 | Y9: =C9*M9 -> 0 | Z9: =C9*N9 -> 0 | AA9: =C9*O9 -> 0
A10: FIBRAPL14 | B10: FIBRA PROLOGIS | C10: =GENERAL!D22 -> 0 | D10: 1 | E10: 0 | F10: 0 | G10: 0 | H10: 0 | I10: 0 | J10: 0 | K10: 0 | L10: 0 | M10: 0 | N10: 0 | O10: 0 | P10: =C10*D10 -> 0 | Q10: =C10*E10 -> 0 | R10: =C10*F10 -> 0 | S10: =C10*G10 -> 0 | T10: =C10*H10 -> 0 | U10: =C10*I10 -> 0 | V10: =C10*J10 -> 0 | W10: =C10*K10 -> 0 | X10: =C10*L10 -> 0 | Y10: =C10*M10 -> 0 | Z10: =C10*N10 -> 0 | AA10: =C10*O10 -> 0
A11: TERRA13 | B11: FIBRA TERRAFINA | C11: =GENERAL!D23 -> 0 | D11: 1 | E11: 0 | F11: 0 | G11: 0 | H11: 0 | I11: 0 | J11: 0 | K11: 0 | L11: 0 | M11: 0 | N11: 0 | O11: 0 | P11: =C11*D11 -> 0 | Q11: =C11*E11 -> 0 | R11: =C11*F11 -> 0 | S11: =C11*G11 -> 0 | T11: =C11*H11 -> 0 | U11: =C11*I11 -> 0 | V11: =C11*J11 -> 0 | W11: =C11*K11 -> 0 | X11: =C11*L11 -> 0 | Y11: =C11*M11 -> 0 | Z11: =C11*N11 -> 0 | AA11: =C11*O11 -> 0
A12: FIHO12 | B12: FIBRA HOTEL | C12: =GENERAL!D24 -> 0 | D12: 0 | E12: 0 | F12: 0 | G12: 0 | H12: 0 | I12: 1 | J12: 0 | K12: 0 | L12: 0 | M12: 0 | N12: 0 | O12: 0 | P12: =C12*D12 -> 0 | Q12: =C12*E12 -> 0 | R12: =C12*F12 -> 0 | S12: =C12*G12 -> 0 | T12: =C12*H12 -> 0 | U12: =C12*I12 -> 0 | V12: =C12*J12 -> 0 | W12: =C12*K12 -> 0 | X12: =C12*L12 -> 0 | Y12: =C12*M12 -> 0 | Z12: =C12*N12 -> 0 | AA12: =C12*O12 -> 0
A13: FINN13 | B13: FIBRA INN | C13: =GENERAL!D20 -> 0.011363636 | D13: 0 | E13: 0 | F13: 0 | G13: 0 | H13: 0 | I13: 1 | J13: 0 | K13: 0 | L13: 0 | M13: 0 | N13: 0 | O13: 0 | P13: =C13*D13 -> 0 | Q13: =C13*E13 -> 0 | R13: =C13*F13 -> 0 | S13: =C13*G13 -> 0 | T13: =C13*H13 -> 0 | U13: =C13*I13 -> 0.011363636 | V13: =C13*J13 -> 0 | W13: =C13*K13 -> 0 | X13: =C13*L13 -> 0 | Y13: =C13*M13 -> 0 | Z13: =C13*N13 -> 0 | AA13: =C13*O13 -> 0
A14: EDUCA18 | B14: FIBRA EDUCA | C14: =GENERAL!D25 -> 0 | D14: 0 | E14: 0 | F14: 0 | G14: 0 | H14: 1 | I14: 0 | J14: 0 | K14: 0 | L14: 0 | M14: 0 | N14: 0 | O14: 0 | P14: =C14*D14 -> 0 | Q14: =C14*E14 -> 0 | R14: =C14*F14 -> 0 | S14: =C14*G14 -> 0 | T14: =C14*H14 -> 0 | U14: =C14*I14 -> 0 | V14: =C14*J14 -> 0 | W14: =C14*K14 -> 0 | X14: =C14*L14 -> 0 | Y14: =C14*M14 -> 0 | Z14: =C14*N14 -> 0 | AA14: =C14*O14 -> 0
A15: FSHOP13 | B15: FIBRA SHOP | C15: =GENERAL!D19 -> 0.036931818 | D15: 0 | E15: 1 | F15: 0 | G15: 0 | H15: 0 | I15: 0 | J15: 0 | K15: 0 | L15: 0 | M15: 0 | N15: 0 | O15: 0 | P15: =C15*D15 -> 0 | Q15: =C15*E15 -> 0.036931818 | R15: =C15*F15 -> 0 | S15: =C15*G15 -> 0 | T15: =C15*H15 -> 0 | U15: =C15*I15 -> 0 | V15: =C15*J15 -> 0 | W15: =C15*K15 -> 0 | X15: =C15*L15 -> 0 | Y15: =C15*M15 -> 0 | Z15: =C15*N15 -> 0 | AA15: =C15*O15 -> 0
A16: FCFE18 | B16: FIBRA CFE | C16: =GENERAL!D11 -> 0.13352273 | D16: 0 | E16: 0 | F16: 0 | G16: 0 | H16: 0 | I16: 0 | J16: 0 | K16: 0 | L16: 0 | M16: 0 | N16: 1 | O16: 0 | P16: =C16*D16 -> 0 | Q16: =C16*E16 -> 0 | R16: =C16*F16 -> 0 | S16: =C16*G16 -> 0 | T16: =C16*H16 -> 0 | U16: =C16*I16 -> 0 | V16: =C16*J16 -> 0 | W16: =C16*K16 -> 0 | X16: =C16*L16 -> 0 | Y16: =C16*M16 -> 0 | Z16: =C16*N16 -> 0.13352273 | AA16: =C16*O16 -> 0
A17: SOMA21 | B17: FIBRA SOMA | C17: =GENERAL!D26 -> 0 | D17: 0 | E17: 0.3 | F17: 0.3 | G17: 0 | H17: 0 | I17: 0.2 | J17: 0.2 | K17: 0 | L17: 0 | M17: 0 | N17: 0 | O17: 0 | P17: =C17*D17 -> 0 | Q17: =C17*E17 -> 0 | R17: =C17*F17 -> 0 | S17: =C17*G17 -> 0 | T17: =C17*H17 -> 0 | U17: =C17*I17 -> 0 | V17: =C17*J17 -> 0 | W17: =C17*K17 -> 0 | X17: =C17*L17 -> 0 | Y17: =C17*M17 -> 0 | Z17: =C17*N17 -> 0 | AA17: =C17*O17 -> 0
A18: STORAGE18 | B18: FIBRA STORAGE | C18: =GENERAL!D27 -> 0 | D18: 0 | E18: 0 | F18: 0 | G18: 0 | H18: 0 | I18: 0 | J18: 0 | K18: 0 | L18: 1 | M18: 0 | N18: 0 | O18: 0 | P18: =C18*D18 -> 0 | Q18: =C18*E18 -> 0 | R18: =C18*F18 -> 0 | S18: =C18*G18 -> 0 | T18: =C18*H18 -> 0 | U18: =C18*I18 -> 0 | V18: =C18*J18 -> 0 | W18: =C18*K18 -> 0 | X18: =C18*L18 -> 0 | Y18: =C18*M18 -> 0 | Z18: =C18*N18 -> 0 | AA18: =C18*O18 -> 0
A19: FSITES20 | B19: FIBRA TELESITES | C19: =GENERAL!D28 -> 0 | D19: 1 | E19: 0 | F19: 0 | G19: 0 | H19: 0 | I19: 0 | J19: 0 | K19: 0 | L19: 0 | M19: 0 | N19: 0 | O19: 0 | P19: =C19*D19 -> 0 | Q19: =C19*E19 -> 0 | R19: =C19*F19 -> 0 | S19: =C19*G19 -> 0 | T19: =C19*H19 -> 0 | U19: =C19*I19 -> 0 | V19: =C19*J19 -> 0 | W19: =C19*K19 -> 0 | X19: =C19*L19 -> 0 | Y19: =C19*M19 -> 0 | Z19: =C19*N19 -> 0 | AA19: =C19*O19 -> 0
A20: FHIPO14 | B20: FIBRA HIPOTECARIA | C20: =GENERAL!D10 -> 0.11079545 | D20: 0 | E20: 0 | F20: 0 | G20: 0 | H20: 0 | I20: 0 | J20: 0 | K20: 0 | L20: 0 | M20: 1 | N20: 0 | O20: 0 | P20: =C20*D20 -> 0 | Q20: =C20*E20 -> 0 | R20: =C20*F20 -> 0 | S20: =C20*G20 -> 0 | T20: =C20*H20 -> 0 | U20: =C20*I20 -> 0 | V20: =C20*J20 -> 0 | W20: =C20*K20 -> 0 | X20: =C20*L20 -> 0 | Y20: =C20*M20 -> 0.11079545 | Z20: =C20*N20 -> 0 | AA20: =C20*O20 -> 0
A21: FVIA16 | B21: FIBRA VIA | C21: =GENERAL!D18 -> 0.039772727 | D21: 0 | E21: 0 | F21: 0 | G21: 0 | H21: 0 | I21: 0 | J21: 0 | K21: 1 | L21: 0 | M21: 0 | N21: 0 | O21: 0 | P21: =C21*D21 -> 0 | Q21: =C21*E21 -> 0 | R21: =C21*F21 -> 0 | S21: =C21*G21 -> 0 | T21: =C21*H21 -> 0 | U21: =C21*I21 -> 0 | V21: =C21*J21 -> 0 | W21: =C21*K21 -> 0.039772727 | X21: =C21*L21 -> 0 | Y21: =C21*M21 -> 0 | Z21: =C21*N21 -> 0 | AA21: =C21*O21 -> 0
A22: FIDEAL20 | B22: FIBRA IDEAL | C22: =GENERAL!D29 -> 0 | D22: 1 | E22: 0 | F22: 0 | G22: 0 | H22: 0 | I22: 0 | J22: 0 | K22: 0 | L22: 0 | M22: 0 | N22: 0 | O22: 0 | P22: =C22*D22 -> 0 | Q22: =C22*E22 -> 0 | R22: =C22*F22 -> 0 | S22: =C22*G22 -> 0 | T22: =C22*H22 -> 0 | U22: =C22*I22 -> 0 | V22: =C22*J22 -> 0 | W22: =C22*K22 -> 0 | X22: =C22*L22 -> 0 | Y22: =C22*M22 -> 0 | Z22: =C22*N22 -> 0 | AA22: =C22*O22 -> 0
A23: FEXI21 | B23: FIBRA EXI | C23: =GENERAL!D30 -> 0 | D23: 0 | E23: 0 | F23: 0 | G23: 0 | H23: 0 | I23: 0 | J23: 0 | K23: 1 | L23: 0 | M23: 0 | N23: 0 | O23: 0 | P23: =C23*D23 -> 0 | Q23: =C23*E23 -> 0 | R23: =C23*F23 -> 0 | S23: =C23*G23 -> 0 | T23: =C23*H23 -> 0 | U23: =C23*I23 -> 0 | V23: =C23*J23 -> 0 | W23: =C23*K23 -> 0 | X23: =C23*L23 -> 0 | Y23: =C23*M23 -> 0 | Z23: =C23*N23 -> 0 | AA23: =C23*O23 -> 0
A24: FSOCIAL23 | B24: FIBRA SOCIAL | C24: =GENERAL!D31 -> 0 | D24: 0 | E24: 0 | F24: 0 | G24: 0 | H24: 0 | I24: 0 | J24: 0 | K24: 0 | L24: 0 | M24: 0 | N24: 0 | O24: 1 | P24: =C24*D24 -> 0 | Q24: =C24*E24 -> 0 | R24: =C24*F24 -> 0 | S24: =C24*G24 -> 0 | T24: =C24*H24 -> 0 | U24: =C24*I24 -> 0 | V24: =C24*J24 -> 0 | W24: =C24*K24 -> 0 | X24: =C24*L24 -> 0 | Y24: =C24*M24 -> 0 | Z24: =C24*N24 -> 0 | AA24: =C24*O24 -> 0
A25: FMX23 | B25: FIBRA eMX | C25: =GENERAL!D32 -> 0 | D25: 0 | E25: 0 | F25: 0 | G25: 0 | H25: 0 | I25: 0 | J25: 0 | K25: 0.5 | L25: 0 | M25: 0 | N25: 0.5 | O25: 0 | P25: =C25*D25 -> 0 | Q25: =C25*E25 -> 0 | R25: =C25*F25 -> 0 | S25: =C25*G25 -> 0 | T25: =C25*H25 -> 0 | U25: =C25*I25 -> 0 | V25: =C25*J25 -> 0 | W25: =C25*K25 -> 0 | X25: =C25*L25 -> 0 | Y25: =C25*M25 -> 0 | Z25: =C25*N25 -> 0 | AA25: =C25*O25 -> 0
A26: AGRO22 | B26: FIBRA AGRO | C26: =GENERAL!D33 -> 0 | D26: 0 | E26: 0 | F26: 0 | G26: 1 | H26: 0 | I26: 0 | J26: 0 | K26: 0 | L26: 0 | M26: 0 | N26: 0 | O26: 0 | P26: =C26*D26 -> 0 | Q26: =C26*E26 -> 0 | R26: =C26*F26 -> 0 | S26: =C26*G26 -> 0 | T26: =C26*H26 -> 0 | U26: =C26*I26 -> 0 | V26: =C26*J26 -> 0 | W26: =C26*K26 -> 0 | X26: =C26*L26 -> 0 | Y26: =C26*M26 -> 0 | Z26: =C26*N26 -> 0 | AA26: =C26*O26 -> 0
P27: =SUM(P3:P25) -> 0.471125 | Q27: =SUM(Q3:Q25) -> 0.32475 | R27: =SUM(R3:R25) -> 0.36875 | S27: =SUM(S3:S25) -> 0.042886364 | T27: =SUM(T3:T25) -> 0.025017045 | U27: =SUM(U3:U25) -> 0.011363636 | V27: =SUM(V3:V25) -> 0.00025568182 | W27: =SUM(W3:W25) -> 0.039772727 | ... AA27: =SUM(AA3:AA25) -> 0

Sheet FIBRATC14
A1: FIBRATC14 | B1: 2023 Q1 | C1: 2022 Q4 | D1: 2022 Q3 | E1: 2022 Q2 | F1: 2022 Q1
A10: Dividendos decretados por CBFI | B10: {=IF(SUMIFS(INDIRECT("'"&A$1&"_DIV'!"&"C:C"),INDIRECT("'"&A$1&"_DIV'!"&"E:E"),B1)=0,"",SUMIFS(INDIRECT("'"&A$1&"_DIV'!"&"C:C"),INDIRECT("'"&A$1&"_DIV'!"&"E:E"),B1))} -> 0.013681 | C10: {=SUMIFS(INDIRECT("'"&A$1&"_DIV'!"&"C:C"),INDIRECT("'"&A$1&"_DIV'!"&"E:E"),C1)} -> 0.668868 | D10: {=SUMIFS(INDIRECT("'"&A$1&"_DIV'!"&"C:C"),INDIRECT("'"&A$1&"_DIV'!"&"E:E"),D1)} -> 0.29326 | E10: {=SUMIFS(INDIRECT("'"&A$1&"_DIV'!"&"C:C"),INDIRECT("'"&A$1&"_DIV'!"&"E:E"),E1)} -> 0.36297 | F10: {=SUMIFS(INDIRECT("'"&A$1&"_DIV'!"&"C:C"),INDIRECT("'"&A$1&"_DIV'!"&"E:E"),F1)} -> 0.34339

Sheet FIBRATC14_DIV
A1: Fecha de pago | B1: Importe
A2: 10 de abril de 2023 | B2: MXN $0.013681 | C2: =VALUE(SUBSTITUTE(SUBSTITUTE(B2,"MXN $",""),"","")) -> 0.013681 | D2: =SUBSTITUTE(SUBSTITUTE(A2,"de",""),"","") -> 10 abril 2023 | E2: =IF(IF(ROUNDUP(MONTH(D2)/3,0)-1=0,4,ROUNDUP(MONTH(D2)/3,0)-1)=4,YEAR(D2)-1,YEAR(D2)) & " Q" & IF(ROUNDUP(MONTH(D2)/3,0)-1=0,4,ROUNDUP(MONTH(D2)/3,0)-1) -> 2023 Q1 | F2: Resultado Fiscal
A3: 15 de marzo de 2023 | B3: MXN $0.031746 | C3: =VALUE(SUBSTITUTE(SUBSTITUTE(B3,"MXN $",""),"","")) -> 0.031746 | D3: =SUBSTITUTE(SUBSTITUTE(A3,"de",""),"","") -> 15 marzo 2023 | E3: =IF(IF(ROUNDUP(MONTH(D3)/3,0)-1=0,4,ROUNDUP(MONTH(D3)/3,0)-1)=4,YEAR(D3)-1,YEAR(D3)) & " Q" & IF(ROUNDUP(MONTH(D3)/3,0)-1=0,4,ROUNDUP(MONTH(D3)/3,0)-1) -> 2022 Q4
A4: 10 de marzo de 2023 | B4: MXN $0.172035 | C4: =VALUE(SUBSTITUTE(SUBSTITUTE(B4,"MXN $",""),"","")) -> 0.172035 | D4: =SUBSTITUTE(SUBSTITUTE(A4,"de",""),"","") -> 10 marzo 2023 | E4: =IF(IF(ROUNDUP(MONTH(D4)/3,0)-1=0,4,ROUNDUP(MONTH(D4)/3,0)-1)=4,YEAR(D4)-1,YEAR(D4)) & " Q" & IF(ROUNDUP(MONTH(D4)/3,0)-1=0,4,ROUNDUP(MONTH(D4)/3,0)-1) -> 2022 Q4
A5: 8 de marzo de 2023 | B5: MXN $0.063574 | C5: =VALUE(SUBSTITUTE(SUBSTITUTE(B5,"MXN $",""),"","")) -> 0.063574 | D5: =SUBSTITUTE(SUBSTITUTE(A5,"de",""),"","") -> 8 marzo 2023 | E5: =IF(IF(ROUNDUP(MONTH(D5)/3,0)-1=0,4,ROUNDUP(MONTH(D5)/3,0)-1)=4,YEAR(D5)-1,YEAR(D5)) & " Q" & IF(ROUNDUP(MONTH(D5)/3,0)-1=0,4,ROUNDUP(MONTH(D5)/3,0)-1) -> 2022 Q4
A6: 3 de marzo de 2023 | B6: MXN $0.04401 | C6: =VALUE(SUBSTITUTE(SUBSTITUTE(B6,"MXN $",""),"","")) -> 0.04401 | D6: =SUBSTITUTE(SUBSTITUTE(A6,"de",""),"","") -> 3 marzo 2023 | E6: =IF(IF(ROUNDUP(MONTH(D6)/3,0)-1=0,4,ROUNDUP(MONTH(D6)/3,0)-1)=4,YEAR(D6)-1,YEAR(D6)) & " Q" & IF(ROUNDUP(MONTH(D6)/3,0)-1=0,4,ROUNDUP(MONTH(D6)/3,0)-1) -> 2022 Q4
A7: 1 de marzo de 2023 | B7: MXN $0.051636 | C7: =VALUE(SUBSTITUTE(SUBSTITUTE(B7,"MXN $",""),"","")) -> 0.051636 | D7: =SUBSTITUTE(SUBSTITUTE(A7,"de",""),"","") -> 1 marzo 2023 | E7: =IF(IF(ROUNDUP(MONTH(D7)/3,0)-1=0,4,ROUNDUP(MONTH(D7)/3,0)-1)=4,YEAR(D7)-1,YEAR(D7)) & " Q" & IF(ROUNDUP(MONTH(D7)/3,0)-1=0,4,ROUNDUP(MONTH(D7)/3,0)-1) -> 2022 Q4
A8: 15 de febrero de 2023 | B8: MXN $0.205899 | C8: =VALUE(SUBSTITUTE(SUBSTITUTE(B8,"MXN $",""),"","")) -> 0.205899 | D8: =SUBSTITUTE(SUBSTITUTE(A8,"de",""),"","") -> 15 febrero 2023 | E8: =IF(IF(ROUNDUP(MONTH(D8)/3,0)-1=0,4,ROUNDUP(MONTH(D8)/3,0)-1)=4,YEAR(D8)-1,YEAR(D8)) & " Q" & IF(ROUNDUP(MONTH(D8)/3,0)-1=0,4,ROUNDUP(MONTH(D8)/3,0)-1) -> 2022 Q4
A9: 30 de enero de 2023 | B9: MXN $0.080577 | C9: =VALUE(SUBSTITUTE(SUBSTITUTE(B9,"MXN $",""),"","")) -> 0.080577 | D9: =SUBSTITUTE(SUBSTITUTE(A9,"de",""),"","") -> 30 enero 2023 | E9: =IF(IF(ROUNDUP(MONTH(D9)/3,0)-1=0,4,ROUNDUP(MONTH(D9)/3,0)-1)=4,YEAR(D9)-1,YEAR(D9)) & " Q" & IF(ROUNDUP(MONTH(D9)/3,0)-1=0,4,ROUNDUP(MONTH(D9)/3,0)-1) -> 2022 Q4
A10: 11 de enero de 2023 | B10: MXN $0.019391 | C10: =VALUE(SUBSTITUTE(SUBSTITUTE(B10,"MXN $",""),"","")) -> 0.019391 | D10: =SUBSTITUTE(SUBSTITUTE(A10,"de",""),"","") -> 11 enero 2023 | E10: =IF(IF(ROUNDUP(MONTH(D10)/3,0)-1=0,4,ROUNDUP(MONTH(D10)/3,0)-1)=4,YEAR(D10)-1,YEAR(D10)) & " Q" & IF(ROUNDUP(MONTH(D10)/3,0)-1=0,4,ROUNDUP(MONTH(D10)/3,0)-1) -> 2022 Q4
A11: 11 de noviembre de 2022 | B11: MXN $0.05108 | C11: =VALUE(SUBSTITUTE(SUBSTITUTE(B11,"MXN $",""),"","")) -> 0.05108 | D11: =SUBSTITUTE(SUBSTITUTE(A11,"de",""),"","") -> 11 noviembre 2022 | E11: =IF(IF(ROUNDUP(MONTH(D11)/3,0)-1=0,4,ROUNDUP(MONTH(D11)/3,0)-1)=4,YEAR(D11)-1,YEAR(D11)) & " Q" & IF(ROUNDUP(MONTH(D11)/3,0)-1=0,4,ROUNDUP(MONTH(D11)/3,0)-1) -> 2022 Q3
A12: 9 de noviembre de 2022 | B12: MXN $0.20458 | C12: =VALUE(SUBSTITUTE(SUBSTITUTE(B12,"MXN $",""),"","")) -> 0.20458 | D12: =SUBSTITUTE(SUBSTITUTE(A12,"de",""),"","") -> 9 noviembre 2022 | E12: =IF(IF(ROUNDUP(MONTH(D12)/3,0)-1=0,4,ROUNDUP(MONTH(D12)/3,0)-1)=4,YEAR(D12)-1,YEAR(D12)) & " Q" & IF(ROUNDUP(MONTH(D12)/3,0)-1=0,4,ROUNDUP(MONTH(D12)/3,0)-1) -> 2022 Q3
A13: 28 de octubre de 2022 | B13: MXN $0.0376 | C13: =VALUE(SUBSTITUTE(SUBSTITUTE(B13,"MXN $",""),"","")) -> 0.0376 | D13: =SUBSTITUTE(SUBSTITUTE(A13,"de",""),"","") -> 28 octubre 2022 | E13: =IF(IF(ROUNDUP(MONTH(D13)/3,0)-1=0,4,ROUNDUP(MONTH(D13)/3,0)-1)=4,YEAR(D13)-1,YEAR(D13)) & " Q" & IF(ROUNDUP(MONTH(D13)/3,0)-1=0,4,ROUNDUP(MONTH(D13)/3,0)-1) -> 2022 Q3
A14: 28 de septiembre de 2022 | B14: MXN $0.0666 | C14: =VALUE(SUBSTITUTE(SUBSTITUTE(B14,"MXN $",""),"","")) -> 0.0666 | D14: =SUBSTITUTE(SUBSTITUTE(A14,"de",""),"","") -> 28 septiembre 2022 | E14: =IF(IF(ROUNDUP(MONTH(D14)/3,0)-1=0,4,ROUNDUP(MONTH(D14)/3,0)-1)=4,YEAR(D14)-1,YEAR(D14)) & " Q" & IF(ROUNDUP(MONTH(D14)/3,0)-1=0,4,ROUNDUP(MONTH(D14)/3,0)-1) -> 2022 Q2
... A107: 12 de febrero de 2018 | B107: MXN $0.088824 | C107: =VALUE(SUBSTITUTE(SUBSTITUTE(B107,"MXN $",""),"","")) -> 0.088824 | D107: =SUBSTITUTE(SUBSTITUTE(A107,"de",""),"","") -> 12 febrero 2018 | E107: =IF(IF(ROUNDUP(MONTH(D107)/3,0)-1=0,4,ROUNDUP(MONTH(D107)/3,0)-1)=4,YEAR(D107)-1,YEAR(D107)) & " Q" & IF(ROUNDUP(MONTH(D107)/3,0)-1=0,4,ROUNDUP(MONTH(D107)/3,0)-1) -> 2017 Q4

Sheet FUNO11
A1: FUNO11 | B1: 2023 Q1 | C1: 2022 Q4 | D1: 2022 Q3 | E1: 2022 Q2 | F1: 2022 Q1 | G1: 2021 Q4 | H1: 2021 Q3 | I1: 2021 Q2 | J1: 2021 Q1 | K1: 2020 Q4 | L1: 2020 Q3 | M1: 2020 Q2 | N1: 2020 Q1 | O1: 2019 Q4 | P1: 2019 Q3 | Q1: 2019 Q2 | R1: 2019 Q1
A2: Ingresos Rentas | B2: 5706059000 | C2: 5316395000 | D2: 5419708000 | E2: 5215475000 | F2: 5214485000 | G2: 5271302000 | H2: 4894380000 | I2: 4802116000 | J2: 4901841000 | K2: 4702990000 | L2: 4389710000 | M2: 3886200000 | N2: 4637904000 | O2: 4567731000 | P2: 4177200000 | Q2: 4227600000 | R2: 4051022000
A3: Ingresos Totales | B3: 6377591000 | C3: 6231561000 | D3: 6018427000 | E3: 5801324000 | F3: 5849374000 | G3: 5818087000 | H3: 5395586000 | I3: 5285546000 | J3: 5369491000 | K3: 5191427000 | L3: 4534300000 | M3: 4298271000 | N3: 5169237000 | O3: 5093101000 | P3: 4755900000 | Q3: 4736900000 | R3: 4603200000
A4: NOI | B4: 5000100000 | C4: 4872100000 | D4: 4785000000 | E4: 4546700000 | F4: 4616000000 | G4: 4604400000 | H4: 4356100000 | I4: 4241100000 | J4: 4220100000 | K4: 4112500000 | L4: 3408300000 | M4: 3245000000 | N4: 4160100000 | O4: 4024000000 | P4: 3774600000 | Q4: 3747300000 | R4: 3667700000
A5: Margen NOI | B5: 0.784 | C5: 0.7818 | D5: 0.7951 | E5: 0.7837 | F5: 0.7891 | G5: 0.7914 | H5: 0.8073 | I5: 0.8024 | J5: 0.7859 | K5: 0.7868 | L5: 0.7517 | M5: 0.755 | N5: 0.8048 | O5: 0.7901 | P5: 0.7937 | Q5: 0.7911 | R5: 0.7968
A6: FFO | B6: 2219700000 | C6: 2249400000 | D6: 2275400000 | E6: 2341700000 | F6: 2384900000 | G6: 2538900000 | H6: 2221800000 | I6: 2179700000 | J6: 2059000000 | K6: 1828500000 | L6: 1146300000 | M6: 1003400000 | N6: 2281800000 | O6: 2475600000 | P6: 2220700000 | Q6: 2206200000 | R6: 2218400000
A7: Margen FFO que reporta la FIBRA | B7: 0.348 | C7: 0.361 | D7: 0.3781 | E7: 0.4036 | F7: 0.4077 | G7: 0.4364 | H7: 0.4118 | I7: 0.4124 | J7: 0.3835 | K7: 0.3522 | L7: 0.2528 | M7: 0.2334 | N7: 0.4414 | O7: 0.4861 | P7: 0.4669 | Q7: 0.4657 | R7: 0.4819
A8: FFO que reporta la FIBRA por CBFI | B8: 0.59 | C8: 0.6 | D8: 0.6 | E8: 0.62 | F8: 0.63 | G8: 0.67 | H8: 0.58 | I8: 0.57 | J8: 0.54 | K8: 0.47 | L8: 0.3 | M8: 0.26 | N8: 0.58 | O8: 0.63 | P8: 0.57 | Q8: 0.57 | R8: 0.57
A9: Dividendos Decretados | B9: 1470408900 | C9: 4182597200 | D9: 2138536100 | E9: 1.9904037e+09 | F9: 1908017100 | G9: 2.59502e+09 | H9: 1.406e+09 | I9: 1.2641639e+09 | J9: 1.2534733e+09 | K9: 1.2078064e+09 | L9: 1.228206e+09 | M9: 1.1038226e+09 | N9: 1.1407476e+09 | O9: 2.3172418e+09 | P9: 2.2979936e+09 | Q9: 2.2702708e+09 | R9: 2.2586004e+09
A10: Dividendos Decretados por CBFI | B10: {=IF(SUMIFS(INDIRECT("'"&A$1&"_DIV'!"&"C:C"),INDIRECT("'"&A$1&"_DIV'!"&"E:E"),B1)=0,"",SUMIFS(INDIRECT("'"&A$1&"_DIV'!"&"C:C"),INDIRECT("'"&A$1&"_DIV'!"&"E:E"),B1))} -> 0.389133 | C10: {=SUMIFS(INDIRECT("'"&A$1&"_DIV'!"&"C:C"),INDIRECT("'"&A$1&"_DIV'!"&"E:E"),C1)} -> 1.106778 | D10: {=SUMIFS(INDIRECT("'"&A$1&"_DIV'!"&"C:C"),INDIRECT("'"&A$1&"_DIV'!"&"E:E"),D1)} -> 0.5659 | E10: {=SUMIFS(INDIRECT("'"&A$1&"_DIV'!"&"C:C"),INDIRECT("'"&A$1&"_DIV'!"&"E:E"),E1)} -> 0.523632 | F10: {=SUMIFS(INDIRECT("'"&A$1&"_DIV'!"&"C:C"),INDIRECT("'"&A$1&"_DIV'!"&"E:E"),F1)} -> 0.50488 | G10: 0.68 | H10: 0.37 | I10: 0.33 | J10: 0.33 | K10: 0.31 | L10: 0.32 | M10: 0.28 | N10: 0.29 | O10: 0.59 | P10: 0.58 | Q10: 0.58 | R10: 0.58
A11: CBFIS en Circulación | B11: 3779000000 | C11: 3779000000 | D11: 3779000000 | E11: 3801382093 | F11: 3779000000 | G11: 3799999999 | H11: 3799999999 | I11: 3818072916 | J11: 3818072916 | K11: 3872415403 | L11: 3874466823 | M11: 3928194243 | N11: 3928194243 | O11: 3928194243 | P11: 3928194243 | Q11: 3890114426 | R11: 3890114426
A12: Cape Rate Implicito | B12: 0.0636 | C12: 0.0625 | D12: 0.0621
A13: Capitalización de Mercado | B13: $96.93B | C13: $93.40B | D13: 90582630000
A14: Descuento o Premium sobre NAV | B14: -0.4872 | C14: -0.4632 | D14: -0.4828
A15: LTV | B15: 0.4 | C15: 0.4151 | D15: 0.4338
A16: Dividend Yield (Decretado) | B16: 0.0607 | C16: 0.0602 | D16: 0.0944
A17: NAV por CBDI | B17: 50.02 | C17: 49.26 | D17: 46.35
A18: ROE Tangible | B18: 0.1131 | C18: 0.1056 | D18: 0.1086

Sheet FUNO11_DIV
A1: Fecha de pago | B1: Importe
A2: 9 de mayo de 2023 | B2: MXN $0.389133 | C2: =VALUE(SUBSTITUTE(SUBSTITUTE(B2,"MXN $",""),"","")) -> 0.389133 | D2: =SUBSTITUTE(SUBSTITUTE(A2,"de",""),"","") -> 9 mayo 2023 | E2: =IF(IF(ROUNDUP(MONTH(D2)/3,0)-1=0,4,ROUNDUP(MONTH(D2)/3,0)-1)=4,YEAR(D2)-1,YEAR(D2)) & " Q" & IF(ROUNDUP(MONTH(D2)/3,0)-1=0,4,ROUNDUP(MONTH(D2)/3,0)-1) -> 2023 Q1 | F2: Resultado Fiscal
A3: 15 de marzo de 2023 | B3: MXN $0.155412 | C3: =VALUE(SUBSTITUTE(SUBSTITUTE(B3,"MXN $",""),"","")) -> 0.155412 | D3: =SUBSTITUTE(SUBSTITUTE(A3,"de",""),"","") -> 15 marzo 2023 | E3: =IF(IF(ROUNDUP(MONTH(D3)/3,0)-1=0,4,ROUNDUP(MONTH(D3)/3,0)-1)=4,YEAR(D3)-1,YEAR(D3)) & " Q" & IF(ROUNDUP(MONTH(D3)/3,0)-1=0,4,ROUNDUP(MONTH(D3)/3,0)-1) -> 2022 Q4 | F3: Resultado Fiscal
A4: 10 de febrero de 2023 | B4: MXN $0.951366 | C4: =VALUE(SUBSTITUTE(SUBSTITUTE(B4,"MXN $",""),"","")) -> 0.951366 | D4: =SUBSTITUTE(SUBSTITUTE(A4,"de",""),"","") -> 10 febrero 2023 | E4: =IF(IF(ROUNDUP(MONTH(D4)/3,0)-1=0,4,ROUNDUP(MONTH(D4)/3,0)-1)=4,YEAR(D4)-1,YEAR(D4)) & " Q" & IF(ROUNDUP(MONTH(D4)/3,0)-1=0,4,ROUNDUP(MONTH(D4)/3,0)-1) -> 2022 Q4 | F4: Resultado Fiscal
A5: 9 de noviembre de 2022 | B5: MXN $0.5659 | C5: =VALUE(SUBSTITUTE(SUBSTITUTE(B5,"MXN $",""),"","")) -> 0.5659 | D5: =SUBSTITUTE(SUBSTITUTE(A5,"de",""),"","") -> 9 noviembre 2022 | E5: =IF(IF(ROUNDUP(MONTH(D5)/3,0)-1=0,4,ROUNDUP(MONTH(D5)/3,0)-1)=4,YEAR(D5)-1,YEAR(D5)) & " Q" & IF(ROUNDUP(MONTH(D5)/3,0)-1=0,4,ROUNDUP(MONTH(D5)/3,0)-1) -> 2022 Q3
A6: 9 de agosto de 2022 | B6: MXN $0.523632 | C6: =VALUE(SUBSTITUTE(SUBSTITUTE(B6,"MXN $",""),"","")) -> 0.523632 | D6: =SUBSTITUTE(SUBSTITUTE(A6,"de",""),"","") -> 9 agosto 2022 | E6: =IF(IF(ROUNDUP(MONTH(D6)/3,0)-1=0,4,ROUNDUP(MONTH(D6)/3,0)-1)=4,YEAR(D6)-1,YEAR(D6)) & " Q" & IF(ROUNDUP(MONTH(D6)/3,0)-1=0,4,ROUNDUP(MONTH(D6)/3,0)-1) -> 2022 Q2
A7: 9 de mayo de 2022 | B7: MXN $0.50488 | C7: =VALUE(SUBSTITUTE(SUBSTITUTE(B7,"MXN $",""),"","")) -> 0.50488 | D7: =SUBSTITUTE(SUBSTITUTE(A7,"de",""),"","") -> 9 mayo 2022 | E7: =IF(IF(ROUNDUP(MONTH(D7)/3,0)-1=0,4,ROUNDUP(MONTH(D7)/3,0)-1)=4,YEAR(D7)-1,YEAR(D7)) & " Q" & IF(ROUNDUP(MONTH(D7)/3,0)-1=0,4,ROUNDUP(MONTH(D7)/3,0)-1) -> 2022 Q1
A8: 9 de febrero de 2022 | B8: MXN $0.682855 | C8: =VALUE(SUBSTITUTE(SUBSTITUTE(B8,"MXN $",""),"","")) -> 0.682855 | D8: =SUBSTITUTE(SUBSTITUTE(A8,"de",""),"","") -> 9 febrero 2022 | E8: =IF(IF(ROUNDUP(MONTH(D8)/3,0)-1=0,4,ROUNDUP(MONTH(D8)/3,0)-1)=4,YEAR(D8)-1,YEAR(D8)) & " Q" & IF(ROUNDUP(MONTH(D8)/3,0)-1=0,4,ROUNDUP(MONTH(D8)/3,0)-1) -> 2021 Q4
A9: 9 de noviembre de 2021 | B9: MXN $0.296 | C9: =VALUE(SUBSTITUTE(SUBSTITUTE(B9,"MXN $",""),"","")) -> 0.296 | D9: =SUBSTITUTE(SUBSTITUTE(A9,"de",""),"","") -> 9 noviembre 2021 | E9: =IF(IF(ROUNDUP(MONTH(D9)/3,0)-1=0,4,ROUNDUP(MONTH(D9)/3,0)-1)=4,YEAR(D9)-1,YEAR(D9)) & " Q" & IF(ROUNDUP(MONTH(D9)/3,0)-1=0,4,ROUNDUP(MONTH(D9)/3,0)-1) -> 2021 Q3
A10: 9 de noviembre de 2021 | B10: MXN $0.074 | C10: =VALUE(SUBSTITUTE(SUBSTITUTE(B10,"MXN $",""),"","")) -> 0.074 | D10: =SUBSTITUTE(SUBSTITUTE(A10,"de",""),"","") -> 9 noviembre 2021 | E10: =IF(IF(ROUNDUP(MONTH(D10)/3,0)-1=0,4,ROUNDUP(MONTH(D10)/3,0)-1)=4,YEAR(D10)-1,YEAR(D10)) & " Q" & IF(ROUNDUP(MONTH(D10)/3,0)-1=0,4,ROUNDUP(MONTH(D10)/3,0)-1) -> 2021 Q3
A11: 9 de agosto de 2021 | B11: MXN $0.218526 | C11: =VALUE(SUBSTITUTE(SUBSTITUTE(B11,"MXN $",""),"","")) -> 0.218526 | D11: =SUBSTITUTE(SUBSTITUTE(A11,"de",""),"","") -> 9 agosto 2021 | E11: =IF(IF(ROUNDUP(MONTH(D11)/3,0)-1=0,4,ROUNDUP(MONTH(D11)/3,0)-1)=4,YEAR(D11)-1,YEAR(D11)) & " Q" & IF(ROUNDUP(MONTH(D11)/3,0)-1=0,4,ROUNDUP(MONTH(D11)/3,0)-1) -> 2021 Q2
A12: 9 de agosto de 2021 | B12: MXN $0.112574 | C12: =VALUE(SUBSTITUTE(SUBSTITUTE(B12,"MXN $",""),"","")) -> 0.112574 | D12: =SUBSTITUTE(SUBSTITUTE(A12,"de",""),"","") -> 9 agosto 2021 | E12: =IF(IF(ROUNDUP(MONTH(D12)/3,0)-1=0,4,ROUNDUP(MONTH(D12)/3,0)-1)=4,YEAR(D12)-1,YEAR(D12)) & " Q" & IF(ROUNDUP(MONTH(D12)/3,0)-1=0,4,ROUNDUP(MONTH(D12)/3,0)-1) -> 2021 Q2
A13: 10 de mayo de 2021 | B13: MXN $0.328345 | C13: =VALUE(SUBSTITUTE(SUBSTITUTE(B13,"MXN $",""),"","")) -> 0.328345 | D13: =SUBSTITUTE(SUBSTITUTE(A13,"de",""),"","") -> 10 mayo 2021 | E13: =IF(IF(ROUNDUP(MONTH(D13)/3,0)-1=0,4,ROUNDUP(MONTH(D13)/3,0)-1)=4,YEAR(D13)-1,YEAR(D13)) & " Q" & IF(ROUNDUP(MONTH(D13)/3,0)-1=0,4,ROUNDUP(MONTH(D13)/3,0)-1) -> 2021 Q1
A14: 9 de febrero de 2021 | B14: MXN $0.311912 | C14: =VALUE(SUBSTITUTE(SUBSTITUTE(B14,"MXN $",""),"","")) -> 0.311912 | D14: =SUBSTITUTE(SUBSTITUTE(A14,"de",""),"","") -> 9 febrero 2021 | E14: =IF(IF(ROUNDUP(MONTH(D14)/3,0)-1=0,4,ROUNDUP(MONTH(D14)/3,0)-1)=4,YEAR(D14)-1,YEAR(D14)) & " Q" & IF(ROUNDUP(MONTH(D14)/3,0)-1=0,4,ROUNDUP(MONTH(D14)/3,0)-1) -> 2020 Q4
A15: 10 de noviembre de 2020 | B15: MXN $0.26614 | C15: =VALUE(SUBSTITUTE(SUBSTITUTE(B15,"MXN $",""),"","")) -> 0.26614 | D15: =SUBSTITUTE(SUBSTITUTE(A15,"de",""),"","") -> 10 noviembre 2020 | E15: =IF(IF(ROUNDUP(MONTH(D15)/3,0)-1=0,4,ROUNDUP(MONTH(D15)/3,0)-1)=4,YEAR(D15)-1,YEAR(D15)) & " Q" & IF(ROUNDUP(MONTH(D15)/3,0)-1=0,4,ROUNDUP(MONTH(D15)/3,0)-1) -> 2020 Q3
A16: 10 de noviembre de 2020 | B16: MXN $0.034808 | C16: =VALUE(SUBSTITUTE(SUBSTITUTE(B16,"MXN $",""),"","")) -> 0.034808 | D16: =SUBSTITUTE(SUBSTITUTE(A16,"de",""),"","") -> 10 noviembre 2020 | E16: =IF(IF(ROUNDUP(MONTH(D16)/3,0)-1=0,4,ROUNDUP(MONTH(D16)/3,0)-1)=4,YEAR(D16)-1,YEAR(D16)) & " Q" & IF(ROUNDUP(MONTH(D16)/3,0)-1=0,4,ROUNDUP(MONTH(D16)/3,0)-1) -> 2020 Q3
... A27: 12 de febrero de 2018 | B27: MXN $0.330498 | C27: =VALUE(SUBSTITUTE(SUBSTITUTE(B27,"MXN $",""),"","")) -> 0.330498 | D27: =SUBSTITUTE(SUBSTITUTE(A27,"de",""),"","") -> 12 febrero 2018 | E27: =IF(IF(ROUNDUP(MONTH(D27)/3,0)-1=0,4,ROUNDUP(MONTH(D27)/3,0)-1)=4,YEAR(D27)-1,YEAR(D27)) & " Q" & IF(ROUNDUP(MONTH(D27)/3,0)-1=0,4,ROUNDUP(MONTH(D27)/3,0)-1) -> 2017 Q4

Sheet FMTY14
A1: FMTY14 | B1: 2023 Q1 | C1: 2022 Q4 | D1: 2022 Q3 | E1: 2022 Q2 | F1: 2022 Q1 | G1: 2021 Q4 | H1: 2021 Q3 | I1: 2021 Q2 | J1: 2021 Q1 | K1: 2020 Q4 | L1: 2020 Q3 | M1: 2020 Q2 | N1: 2020 Q1 | O1: 2019 Q4 | P1: 2019 Q3 | Q1: 2019 Q2 | R1: 2019 Q1
A2: Ingresos Rentas | B2: 340864000 | C2: 345111000 | D2: 342806000 | E2: 340685000 | F2: 344337000 | G2: 321976000 | H2: 302230000 | I2: 275107000 | J2: 307636000 | K2: 306250000 | L2: 319157000 | M2: 332654000 | N2: 285999000 | O2: 285894000 | P2: 272976000 | Q2: 267716000 | R2: 268168000
A3: Ingresos Totales | B3: 372588000 | C3: 376966000 | D3: 375103000 | E3: 373826000 | F3: 375298000 | G3: 350980000 | H3: 330490000 | I3: 299732000 | J3: 330420000 | K3: 330173000 | L3: 343141000 | M3: 358874000 | N3: 314774000 | O3: 316090000 | P3: 302454000 | Q3: 296711000 | R3: 296382000
A4: NOI | B4: 330563000 | C4: 326609000 | D4: 326242000 | E4: 332754000 | F4: 339819000 | G4: 314449000 | H4: 293137000 | I4: 271873000 | J4: 300827000 | K4: 300116000 | L4: 314065000 | M4: 329320000 | N4: 284383000 | O4: 285118000 | P4: 271739000 | Q4: 267272000 | R4: 268563000
A5: Margen NOI | B5: 0.8872 | C5: 0.8664 | D5: 0.8697 | E5: 0.8901 | F5: 0.9055 | G5: 0.8959 | H5: 0.887 | I5: 0.9071 | J5: 0.9104 | K5: 0.9073 | L5: 0.9153 | M5: 0.9176 | N5: 0.9035 | O5: 0.902 | P5: 0.8984 | Q5: 0.9008 | R5: 0.9061
A6: FFO | B6: 347783000 | C6: 333251000 | D6: 267700000 | E6: 257126000 | F6: 252030000 | G6: 240253000 | H6: 221000000 | I6: 212967000 | J6: 243545000 | K6: 247346000 | L6: 265284000 | M6: 279156000 | N6: 260730000 | O6: 243408000 | P6: 195882000 | Q6: 197284000 | R6: 180087000
A7: Margen FFO que reporta la FIBRA | B7: 0.9334 | C7: 0.884 | D7: 0.7137 | E7: 0.6878 | F7: 0.6715 | G7: 0.6845 | H7: 0.6687 | I7: 0.7105 | J7: 0.7371 | K7: 0.7491 | L7: 0.7731 | M7: 0.7779 | N7: 0.8283 | O7: 0.7701 | P7: 0.6476 | Q7: 0.6649 | R7: 0.6076
A8: FFO que reporta la FIBRA por CBFI | B8: 0.22 | C8: 0.27 | D8: 0.21 | E8: 0.26 | F8: 0.26 | G8: 0.25 | H8: 0.23 | I8: 0.22 | J8: 0.25 | K8: 0.26 | L8: 0.27 | M8: 0.29 | N8: 0.27 | O8: 0.25 | P8: 0.31 | Q8: 0.31 | R8: 0.28
A9: Dividendos Decretados | B9: 0 | C9: 3.2129229e+08 | D9: 3.13762e+08 | E9: 2.450098e+08 | F9: 2.4014849e+08 | G9: 2.3764378e+08 | H9: 2.162966e+08 | I9: 2.1241684e+08 | J9: 2.017475e+08 | K9: 2.4280612e+08 | L9: 2.5851678e+08 | M9: 2.6002057e+08 | N9: 2.5086597e+08 | O9: 2.5800876e+08 | P9: 1.8686969e+08 | Q9: 1.8687046e+08 | R9: 1.6959146e+08
A10: Dividendos decretados por CBFI | B10: 0 | C10: {=SUMIFS(INDIRECT("'"&A$1&"_DIV'!"&"C:C"),INDIRECT("'"&A$1&"_DIV'!"&"E:E"),C1)} -> 0.308667 | D10: {=SUMIFS(INDIRECT("'"&A$1&"_DIV'!"&"C:C"),INDIRECT("'"&A$1&"_DIV'!"&"E:E"),D1)} -> 0.250301 | E10: {=SUMIFS(INDIRECT("'"&A$1&"_DIV'!"&"C:C"),INDIRECT("'"&A$1&"_DIV'!"&"E:E"),E1)} -> 0.251865 | F10: 0.2519 | G10: 0.24 | H10: 0.22 | I10: 0.22 | J10: 0.21 | K10: 0.25 | L10: 0.27 | M10: 0.27 | N10: 0.26 | O10: 0.27 | P10: 0.29 | Q10: 0.29 | R10: 0.27
A11: CBFIS en Circulación | B11: 1553679660 | C11: 1255047994 | D11: 1255047994 | E11: 972261110 | F11: 972261110 | G11: 969974606 | H11: 969939906 | I11: 969939906 | J11: 969939906 | K11: 967740599 | L11: 966056725 | M11: 961970294 | N11: 961172298 | O11: 964158288 | P11: 638434184 | Q11: 639967331 | R11: 637801637
A12: Cape Rate Implicito | B12: 0.0475 | C12: 0.0737 | D12: 0.0721
A13: Capitalización de Mercado | B13: 1.9250091e+10 | C13: $11.78B | D13: 1.5324136e+10
A14: Descuento o Premium sobre NAV | B14: 0.026 | C14: -0.0645 | D14: -0.0702
A15: LTV | B15: 0.3685 | C15: 0.235 | D15: 0.2413
A16: Dividend Yield (Decretado) | C16: 0.0735 | D16: 0.0819
A17: NAV por CBDI | B17: 12.08 | C17: 13.11 | D17: 13.13
A18: ROE Tangible | B18: -0.2265 | C18: 0.0726 | D18: 0.0747

Sheet FIBRAMQ12
A1: FIBRAMQ12 | B1: 2023 Q1 | C1: 2022 Q4 | D1: 2022 Q3 | E1: 2022 Q2 | F1: 2022 Q1 | G1: 2021 Q4 | H1: 2021 Q3 | I1: 2021 Q2 | J1: 2021 Q1 | K1: 2020 Q4 | L1: 2020 Q3 | M1: 2020 Q2 | N1: 2020 Q1 | O1: 2019 Q4 | P1: 2019 Q3 | Q1: 2019 Q2 | R1: 2019 Q1
A2: Ingresos Rentas | C2: 974720000 | D2: 977307000 | E2: 941629000 | F2: 935211000 | G2: 929280000 | H2: 900253000 | I2: 888368000 | J2: 882497000 | K2: 900986000 | L2: 936129000 | M2: 998389000 | N2: 985000000 | O2: 865755000 | P2: 853500000 | Q2: 843299000 | R2: 833800000
A3: Ingresos Totales | C3: 1050794000 | D3: 1034404000 | E3: 992715000 | F3: 999562000 | G3: 992748000 | H3: 950988000 | I3: 954651000 | J3: 949257000 | K3: 963732000 | L3: 998962000 | M3: 1055583000 | N3: 1065500000 | O3: 932619000 | P3: 979400000 | Q3: 962700000 | R3: 947200000
A4: NOI | C4: 947100000 | D4: 957400000 | E4: 919100000 | F4: 929600000 | G4: 917900000 | H4: 874700000 | I4: 879400000 | J4: 870500000 | K4: 870300000 | L4: 906900000 | M4: 963900000 | N4: 951600000 | O4: 858700000 | P4: 869900000 | Q4: 845500000 | R4: 829400000
A5: Margen NOI | C5: 0.9013 | D5: 0.9256 | E5: 0.9258 | F5: 0.93 | G5: 0.9246 | H5: 0.9198 | I5: 0.9212 | J5: 0.917 | K5: 0.8187 | L5: 0.9078 | M5: 0.9131 | N5: 0.8931 | O5: 0.9207 | P5: 0.8882 | Q5: 0.8783 | R5: 0.8756
A6: FFO | C6: 631600000 | D6: 645900000 | E6: 619300000 | F6: 624500000 | G6: 604800000 | H6: 575200000 | I6: 577500000 | J6: 567500000 | K6: 559600000 | L6: 576300000 | M6: 608700000 | N6: 654900000 | O6: 571600000 | P6: 591700000 | Q6: 575800000 | R6: 564600000
A7: Margen FFO que reporta la FIBRA | C7: 0.6011 | D7: 0.6244 | E7: 0.6238 | F7: 0.6248 | G7: 0.6092 | H7: 0.6048 | I7: 0.6049 | J7: 0.5978 | K7: 0.5807 | L7: 0.5769 | M7: 0.5766 | N7: 0.6146 | O7: 0.6129 | P7: 0.6041 | Q7: 0.5981 | R7: 0.5961
A8: FFO que reporta la FIBRA por CBFI | C8: 0.83 | D8: 0.85 | E8: 0.79 | F8: 0.89 | G8: 0.79 | H8: 0.76 | I8: 0.76 | J8: 0.75 | K8: 0.73 | L8: 0.76 | M8: 0.8 | N8: 0.86 | O8: 0.75 | P8: 0.77 | Q8: 0.75 | R8: 0.73
A9: Dividendos Decretados | C9: 380644500 | D9: 3.7934586e+08 | E9: 3.9075774e+08 | F9: 3.5191068e+08 | G9: 361612275 | H9: 361611800 | I9: 361611800 | J9: 361770925 | K9: 3.6177116e+08 | L9: 3.6177116e+08 | M9: 3.6177116e+08 | N9: 3.6177116e+08 | O9: 348393500 | P9: 348393500 | Q9: 342650000 | R9: 327250000
A10: Dividendos decretados por CBFI | B10: {=IF(SUMIFS(INDIRECT("'"&A$1&"_DIV'!"&"C:C"),INDIRECT("'"&A$1&"_DIV'!"&"E:E"),B1)=0,"",SUMIFS(INDIRECT("'"&A$1&"_DIV'!"&"C:C"),INDIRECT("'"&A$1&"_DIV'!"&"E:E"),B1))} -> 0.525 | C10: {=SUMIFS(INDIRECT("'"&A$1&"_DIV'!"&"C:C"),INDIRECT("'"&A$1&"_DIV'!"&"E:E"),C1)} -> 1.878824 | D10: {=SUMIFS(INDIRECT("'"&A$1&"_DIV'!"&"C:C"),INDIRECT("'"&A$1&"_DIV'!"&"E:E"),D1)} -> 0 | E10: {=SUMIFS(INDIRECT("'"&A$1&"_DIV'!"&"C:C"),INDIRECT("'"&A$1&"_DIV'!"&"E:E"),E1)} -> 0.5 | F10: {=SUMIFS(INDIRECT("'"&A$1&"_DIV'!"&"C:C"),INDIRECT("'"&A$1&"_DIV'!"&"E:E"),F1)} -> 0.5 | G10: {=SUMIFS(INDIRECT("'"&A$1&"_DIV'!"&"C:C"),INDIRECT("'"&A$1&"_DIV'!"&"E:E"),G1)} -> 0.95 | H10: {=SUMIFS(INDIRECT("'"&A$1&"_DIV'!"&"C:C"),INDIRECT("'"&A$1&"_DIV'!"&"E:E"),H1)} -> 0 | I10: {=SUMIFS(INDIRECT("'"&A$1&"_DIV'!"&"C:C"),INDIRECT("'"&A$1&"_DIV'!"&"E:E"),I1)} -> 0.475 | J10: 0.47 | K10: 0.47 | L10: 0.47 | M10: 0.47 | N10: 0.47 | O10: 0.46 | P10: 0.46 | Q10: 0.45 | R10: 0.42
A11: CBFIS en Circulación | C11: 761289000 | D11: 7.5869173e+08 | E11: 7.8151548e+08 | F11: 7.0382136e+08 | G11: 761289000 | H11: 761288000 | I11: 761288000 | J11: 761623000 | K11: 761623497 | L11: 761623497 | M11: 761623497 | N11: 761623497 | O11: 765700000 | P11: 765700000 | Q11: 770000000 | R11: 770000000
A12: Cape Rate Implicito | C12: 0.0693 | D12: 0.0686
A13: Capitalización de Mercado | C13: 22488447520 | D13: 2.1129565e+10
A14: Descuento o Premium sobre NAV | C14: -0.3079 | D14: -0.3976
A15: LTV | C15: 0.3167 | D15: 0.3203
A16: Dividend Yield (Decretado) | C16: 0.0643 | D16: 0.0718
A17: NAV por CBDI | C17: 45.39 | D17: 46.23
A18: ROE Tangible | C18: 0.0948 | D18: 0.0946
E23: {=SUMIFS(INDIRECT("'"&D$1&"_DIV'!"&"C:C"),INDIRECT("'"&D$1&"_DIV'!"&"E:E"),E16)} -> #N/A

Sheet FIBRAMQ12_DIV
A1: Fecha de pago | B1: Importe
A2: 15 de junio de 2023 | B2: MXN $0.525 | C2: =VALUE(SUBSTITUTE(SUBSTITUTE(B2,"MXN $",""),"","")) -> 0.525 | D2: =SUBSTITUTE(SUBSTITUTE(A2,"de",""),"","") -> 15 junio 2023 | E2: =IF(IF(ROUNDUP(MONTH(D2)/3,0)-1=0,4,ROUNDUP(MONTH(D2)/3,0)-1)=4,YEAR(D2)-1,YEAR(D2)) & " Q" & IF(ROUNDUP(MONTH(D2)/3,0)-1=0,4,ROUNDUP(MONTH(D2)/3,0)-1) -> 2023 Q1 | F2: ?
A3: 10 de marzo de 2023 | B3: MXN $0.878824 | C3: =VALUE(SUBSTITUTE(SUBSTITUTE(B3,"MXN $",""),"","")) -> 0.878824 | D3: =SUBSTITUTE(SUBSTITUTE(A3,"de",""),"","") -> 10 marzo 2023 | E3: =IF(IF(ROUNDUP(MONTH(D3)/3,0)-1=0,4,ROUNDUP(MONTH(D3)/3,0)-1)=4,YEAR(D3)-1,YEAR(D3)) & " Q" & IF(ROUNDUP(MONTH(D3)/3,0)-1=0,4,ROUNDUP(MONTH(D3)/3,0)-1) -> 2022 Q4 | F3: Resultado Fiscal
A4: 3 de marzo de 2023 | B4: MXN $0.50 | C4: =VALUE(SUBSTITUTE(SUBSTITUTE(B4,"MXN $",""),"","")) -> 0.5 | D4: =SUBSTITUTE(SUBSTITUTE(A4,"de",""),"","") -> 3 marzo 2023 | E4: =IF(IF(ROUNDUP(MONTH(D4)/3,0)-1=0,4,ROUNDUP(MONTH(D4)/3,0)-1)=4,YEAR(D4)-1,YEAR(D4)) & " Q" & IF(ROUNDUP(MONTH(D4)/3,0)-1=0,4,ROUNDUP(MONTH(D4)/3,0)-1) -> 2022 Q4 | F4: Resultado Fiscal
A5: 30 de enero de 2023 | B5: MXN $0.50 | C5: =VALUE(SUBSTITUTE(SUBSTITUTE(B5,"MXN $",""),"","")) -> 0.5 | D5: =SUBSTITUTE(SUBSTITUTE(A5,"de",""),"","") -> 30 enero 2023 | E5: =IF(IF(ROUNDUP(MONTH(D5)/3,0)-1=0,4,ROUNDUP(MONTH(D5)/3,0)-1)=4,YEAR(D5)-1,YEAR(D5)) & " Q" & IF(ROUNDUP(MONTH(D5)/3,0)-1=0,4,ROUNDUP(MONTH(D5)/3,0)-1) -> 2022 Q4 | F5: Resultado Fiscal
A6: 28 de septiembre de 2022 | B6: MXN $0.50 | C6: =VALUE(SUBSTITUTE(SUBSTITUTE(B6,"MXN $",""),"","")) -> 0.5 | D6: =SUBSTITUTE(SUBSTITUTE(A6,"de",""),"","") -> 28 septiembre 2022 | E6: =IF(IF(ROUNDUP(MONTH(D6)/3,0)-1=0,4,ROUNDUP(MONTH(D6)/3,0)-1)=4,YEAR(D6)-1,YEAR(D6)) & " Q" & IF(ROUNDUP(MONTH(D6)/3,0)-1=0,4,ROUNDUP(MONTH(D6)/3,0)-1) -> 2022 Q2
A7: 16 de junio de 2022 | B7: MXN $0.50 | C7: =VALUE(SUBSTITUTE(SUBSTITUTE(B7,"MXN $",""),"","")) -> 0.5 | D7: =SUBSTITUTE(SUBSTITUTE(A7,"de",""),"","") -> 16 junio 2022 | E7: =IF(IF(ROUNDUP(MONTH(D7)/3,0)-1=0,4,ROUNDUP(MONTH(D7)/3,0)-1)=4,YEAR(D7)-1,YEAR(D7)) & " Q" & IF(ROUNDUP(MONTH(D7)/3,0)-1=0,4,ROUNDUP(MONTH(D7)/3,0)-1) -> 2022 Q1
A8: 11 de marzo de 2022 | B8: MXN $0.475 | C8: =VALUE(SUBSTITUTE(SUBSTITUTE(B8,"MXN $",""),"","")) -> 0.475 | D8: =SUBSTITUTE(SUBSTITUTE(A8,"de",""),"","") -> 11 marzo 2022 | E8: =IF(IF(ROUNDUP(MONTH(D8)/3,0)-1=0,4,ROUNDUP(MONTH(D8)/3,0)-1)=4,YEAR(D8)-1,YEAR(D8)) & " Q" & IF(ROUNDUP(MONTH(D8)/3,0)-1=0,4,ROUNDUP(MONTH(D8)/3,0)-1) -> 2021 Q4
A9: 28 de enero de 2022 | B9: MXN $0.475 | C9: =VALUE(SUBSTITUTE(SUBSTITUTE(B9,"MXN $",""),"","")) -> 0.475 | D9: =SUBSTITUTE(SUBSTITUTE(A9,"de",""),"","") -> 28 enero 2022 | E9: =IF(IF(ROUNDUP(MONTH(D9)/3,0)-1=0,4,ROUNDUP(MONTH(D9)/3,0)-1)=4,YEAR(D9)-1,YEAR(D9)) & " Q" & IF(ROUNDUP(MONTH(D9)/3,0)-1=0,4,ROUNDUP(MONTH(D9)/3,0)-1) -> 2021 Q4
A10: 27 de septiembre de 2021 | B10: MXN $0.475 | C10: =VALUE(SUBSTITUTE(SUBSTITUTE(B10,"MXN $",""),"","")) -> 0.475 | D10: =SUBSTITUTE(SUBSTITUTE(A10,"de",""),"","") -> 27 septiembre 2021 | E10: =IF(IF(ROUNDUP(MONTH(D10)/3,0)-1=0,4,ROUNDUP(MONTH(D10)/3,0)-1)=4,YEAR(D10)-1,YEAR(D10)) & " Q" & IF(ROUNDUP(MONTH(D10)/3,0)-1=0,4,ROUNDUP(MONTH(D10)/3,0)-1) -> 2021 Q2
A11: 15 de junio de 2021 | B11: MXN $0.475 | C11: =VALUE(SUBSTITUTE(SUBSTITUTE(B11,"MXN $",""),"","")) -> 0.475 | D11: =SUBSTITUTE(SUBSTITUTE(A11,"de",""),"","") -> 15 junio 2021 | E11: =IF(IF(ROUNDUP(MONTH(D11)/3,0)-1=0,4,ROUNDUP(MONTH(D11)/3,0)-1)=4,YEAR(D11)-1,YEAR(D11)) & " Q" & IF(ROUNDUP(MONTH(D11)/3,0)-1=0,4,ROUNDUP(MONTH(D11)/3,0)-1) -> 2021 Q1
A12: 12 de marzo de 2021 | B12: MXN $0.475 | C12: =VALUE(SUBSTITUTE(SUBSTITUTE(B12,"MXN $",""),"","")) -> 0.475 | D12: =SUBSTITUTE(SUBSTITUTE(A12,"de",""),"","") -> 12 marzo 2021 | E12: =IF(IF(ROUNDUP(MONTH(D12)/3,0)-1=0,4,ROUNDUP(MONTH(D12)/3,0)-1)=4,YEAR(D12)-1,YEAR(D12)) & " Q" & IF(ROUNDUP(MONTH(D12)/3,0)-1=0,4,ROUNDUP(MONTH(D12)/3,0)-1) -> 2020 Q4
A13: 28 de enero de 2021 | B13: MXN $0.008171 | C13: =VALUE(SUBSTITUTE(SUBSTITUTE(B13,"MXN $",""),"","")) -> 0.008171 | D13: =SUBSTITUTE(SUBSTITUTE(A13,"de",""),"","") -> 28 enero 2021 | E13: =IF(IF(ROUNDUP(MONTH(D13)/3,0)-1=0,4,ROUNDUP(MONTH(D13)/3,0)-1)=4,YEAR(D13)-1,YEAR(D13)) & " Q" & IF(ROUNDUP(MONTH(D13)/3,0)-1=0,4,ROUNDUP(MONTH(D13)/3,0)-1) -> 2020 Q4
A14: 28 de enero de 2021 | B14: MXN $0.466829 | C14: =VALUE(SUBSTITUTE(SUBSTITUTE(B14,"MXN $",""),"","")) -> 0.466829 | D14: =SUBSTITUTE(SUBSTITUTE(A14,"de",""),"","") -> 28 enero 2021 | E14: =IF(IF(ROUNDUP(MONTH(D14)/3,0)-1=0,4,ROUNDUP(MONTH(D14)/3,0)-1)=4,YEAR(D14)-1,YEAR(D14)) & " Q" & IF(ROUNDUP(MONTH(D14)/3,0)-1=0,4,ROUNDUP(MONTH(D14)/3,0)-1) -> 2020 Q4
A15: 25 de septiembre de 2020 | B15: MXN $0.11875 | C15: =VALUE(SUBSTITUTE(SUBSTITUTE(B15,"MXN $",""),"","")) -> 0.11875 | D15: =SUBSTITUTE(SUBSTITUTE(A15,"de",""),"","") -> 25 septiembre 2020 | E15: =IF(IF(ROUNDUP(MONTH(D15)/3,0)-1=0,4,ROUNDUP(MONTH(D15)/3,0)-1)=4,YEAR(D15)-1,YEAR(D15)) & " Q" & IF(ROUNDUP(MONTH(D15)/3,0)-1=0,4,ROUNDUP(MONTH(D15)/3,0)-1) -> 2020 Q2
A16: 25 de septiembre de 2020 | B16: MXN $0.35625 | C16: =VALUE(SUBSTITUTE(SUBSTITUTE(B16,"MXN $",""),"","")) -> 0.35625 | D16: =SUBSTITUTE(SUBSTITUTE(A16,"de",""),"","") -> 25 septiembre 2020 | E16: =IF(IF(ROUNDUP(MONTH(D16)/3,0)-1=0,4,ROUNDUP(MONTH(D16)/3,0)-1)=4,YEAR(D16)-1,YEAR(D16)) & " Q" & IF(ROUNDUP(MONTH(D16)/3,0)-1=0,4,ROUNDUP(MONTH(D16)/3,0)-1) -> 2020 Q2
A17: 12 de junio de 2020 | B17: MXN $0.475 | C17: =VALUE(SUBSTITUTE(SUBSTITUTE(B17,"MXN $",""),"","")) -> 0.475 | D17: =SUBSTITUTE(SUBSTITUTE(A17,"de",""),"","") -> 12 junio 2020 | E17: =IF(IF(ROUNDUP(MONTH(D17)/3,0)-1=0,4,ROUNDUP(MONTH(D17)/3,0)-1)=4,YEAR(D17)-1,YEAR(D17)) & " Q" & IF(ROUNDUP(MONTH(D17)/3,0)-1=0,4,ROUNDUP(MONTH(D17)/3,0)-1) -> 2020 Q1
... A29: 9 de marzo de 2018 | B29: MXN $0.375 | C29: =VALUE(SUBSTITUTE(SUBSTITUTE(B29,"MXN $",""),"","")) -> 0.375 | D29: =SUBSTITUTE(SUBSTITUTE(A29,"de",""),"","") -> 9 marzo 2018 | E29: =IF(IF(ROUNDUP(MONTH(D29)/3,0)-1=0,4,ROUNDUP(MONTH(D29)/3,0)-1)=4,YEAR(D29)-1,YEAR(D29)) & " Q" & IF(ROUNDUP(MONTH(D29)/3,0)-1=0,4,ROUNDUP(MONTH(D29)/3,0)-1) -> 2017 Q4

Sheet DANHOS13
A1: DANHOS13 | B1: 2023 Q1 | C1: 2022 Q4 | D1: 2022 Q3 | E1: 2022 Q2 | F1: 2022 Q1 | G1: 2021 Q4 | H1: 2021 Q3 | I1: 2021 Q2 | J1: 2021 Q1 | K1: 2020 Q4 | L1: 2020 Q3 | M1: 2020 Q2 | N1: 2020 Q1 | O1: 2019 Q4 | P1: 2019 Q3 | Q1: 2019 Q2 | R1: 2019 Q1
A2: Ingresos Rentas | C2: 1088111000 | D2: 961567000 | E2: 965600000 | F2: 940720000 | G2: 983325000 | H2: 860913000 | I2: 845503000 | J2: 723650000 | K2: 867967000 | L2: 795123601 | M2: 589411657 | N2: 989278778 | O2: 1063757312 | P2: 993308033 | Q2: 986966079 | R2: 948619033
A3: Ingresos Totales | C3: 1523560000 | D3: 1349098000 | E3: 1338117000 | F3: 1302300000 | G3: 1363553000 | H3: 1199039000 | I3: 1177505000 | J3: 1026081000 | K3: 1241434000 | L3: 1103832698 | M3: 899821035 | N3: 1396624576 | O3: 1540460433 | P3: 1451409184 | Q3: 1439778775 | R3: 1362807279
A4: NOI | C4: 1147200000 | D4: 1067853882 | E4: 1056559181 | F4: 1050331090 | G4: 1072708202 | H4: 969159231 | I4: 949229608 | J4: 846464090 | K4: 979959308 | L4: 890121625 | M4: 732010680 | N4: 1130528529 | O4: 1238019666 | P4: 1180429926 | Q4: 1170200000 | R4: 1112700000
A5: Margen NOI | C5: 0.753 | D5: 0.7915 | E5: 0.7896 | F5: 0.8065 | G5: 0.7867 | H5: 0.8083 | I5: 0.8061 | J5: 0.8249 | K5: 0.8182 | L5: 0.8064 | M5: 0.8135 | N5: 0.8095 | O5: 0.8037 | P5: 0.8133 | Q5: 0.8128 | R5: 0.8165
A6: FFO | C6: 808180068 | D6: 781938607 | E6: 783145623 | F6: 786830176 | G6: 786048342 | H6: 699037722 | I6: 679187810 | J6: 583299253 | K6: 855106733 | L6: 623915956 | M6: 450874541 | N6: 861644104 | O6: 1106239226 | P6: 877476643 | Q6: 898669946 | R6: 846233287
A7: Margen FFO que reporta la FIBRA | C7: 0.5305 | D7: 0.5796 | E7: 0.5853 | F7: 0.6042 | G7: 0.5765 | H7: 0.583 | I7: 0.5768 | J7: 0.5685 | K7: 0.6888 | L7: 0.5652 | M7: 0.5011 | N7: 0.6169 | O7: 0.7181 | P7: 0.6046 | Q7: 0.6242 | R7: 0.6209
A8: FFO que reporta la FIBRA por CBFI | C8: 0.53 | D8: 0.51 | E8: 0.51 | F8: 0.52 | G8: 0.52 | H8: 0.46 | I8: 0.45 | J8: 0.4 | K8: 0.59 | L8: 0.43 | M8: 0.31 | N8: 0.6 | O8: 0.77 | P8: 0.62 | Q8: 0.64 | R8: 0.6
A9: Dividendos Decretados | C9: 9.5388657e+08 | D9: 9.2490536e+08 | E9: 920760306 | F9: 8.8070566e+08 | G9: 8.7670891e+08 | H9: 7.8242192e+08 | I9: 7.4902371e+08 | J9: 5.8510086e+08 | K9: 8.7379692e+08 | L9: 5.79567e+08 | M9: 0 | N9: 0 | O9: 8.9954206e+08 | P9: 8.7962953e+08 | Q9: 8.597719e+08 | R9: 8.5712034e+08
A10: Dividendos decretados por CBFI | B10: {=IF(SUMIFS(INDIRECT("'"&A$1&"_DIV'!"&"C:C"),INDIRECT("'"&A$1&"_DIV'!"&"E:E"),B1)=0,"",SUMIFS(INDIRECT("'"&A$1&"_DIV'!"&"C:C"),INDIRECT("'"&A$1&"_DIV'!"&"E:E"),B1))} -> 0.6 | C10: {=SUMIFS(INDIRECT("'"&A$1&"_DIV'!"&"C:C"),INDIRECT("'"&A$1&"_DIV'!"&"E:E"),C1)} -> 0.62 | D10: {=SUMIFS(INDIRECT("'"&A$1&"_DIV'!"&"C:C"),INDIRECT("'"&A$1&"_DIV'!"&"E:E"),D1)} -> 0.6 | E10: {=SUMIFS(INDIRECT("'"&A$1&"_DIV'!"&"C:C"),INDIRECT("'"&A$1&"_DIV'!"&"E:E"),E1)} -> 0.6 | F10: {=SUMIFS(INDIRECT("'"&A$1&"_DIV'!"&"C:C"),INDIRECT("'"&A$1&"_DIV'!"&"E:E"),F1)} -> 0.58 | G10: 0.58 | H10: 0.52 | I10: 0.5 | J10: 0.4 | K10: 0.6 | L10: 0.4 | M10: 0 | N10: 0 | O10: 0.63 | P10: 0.62 | Q10: 0.61 | R10: 0.61
A11: CBFIS en Circulación | C11: 1538526726 | D11: 1541508931 | E11: 1534600510 | F11: 1518458041 | G11: 1511567093 | H11: 1504657545 | I11: 1498047425 | J11: 1462752158 | K11: 1456328199 | L11: 1448917498 | M11: 1434409737 | N11: 1431127142 | O11: 1427844547 | P11: 1418757304 | Q11: 1409462135 | R11: 1405115317
A12: Cape Rate Implicito | B12: 0.069 | C12: 0.0704 | D12: 0.0659
A13: Capitalización de Mercado | B13: 3.7722891e+10 | C13: 3.5524965e+10 | D13: 36996214344
A14: Descuento o Premium sobre NAV | B14: -0.3866 | C14: -0.3996 | D14: -0.3951
A15: LTV | B15: 0.0926 | C15: 0.0869 | D15: 0.086
A16: Dividend Yield (Decretado) | B16: 0.09 | C16: 0.0871 | D16: 0.1
A17: NAV por CBDI | B17: 39.79 | C17: 39.89 | D17: 39.68
A18: ROE Tangible | B18: 0.0665 | C18: 0.0704 | D18: 0.0667

Sheet DANHOS13_DIV
A1: Fecha de pago | B1: Importe
A2: 10 de mayo de 2023 | B2: MXN $0.240527 | C2: =VALUE(SUBSTITUTE(SUBSTITUTE(B2,"MXN $",""),"","")) -> 0.240527 | D2: =SUBSTITUTE(SUBSTITUTE(A2,"de",""),"","") -> 10 mayo 2023 | E2: =IF(IF(ROUNDUP(MONTH(D2)/3,0)-1=0,4,ROUNDUP(MONTH(D2)/3,0)-1)=4,YEAR(D2)-1,YEAR(D2)) & " Q" & IF(ROUNDUP(MONTH(D2)/3,0)-1=0,4,ROUNDUP(MONTH(D2)/3,0)-1) -> 2023 Q1 | F2: Reembolso de Capital
A3: 10 de mayo de 2023 | B3: MXN $0.359473 | C3: =VALUE(SUBSTITUTE(SUBSTITUTE(B3,"MXN $",""),"","")) -> 0.359473 | D3: =SUBSTITUTE(SUBSTITUTE(A3,"de",""),"","") -> 10 mayo 2023 | E3: =IF(IF(ROUNDUP(MONTH(D3)/3,0)-1=0,4,ROUNDUP(MONTH(D3)/3,0)-1)=4,YEAR(D3)-1,YEAR(D3)) & " Q" & IF(ROUNDUP(MONTH(D3)/3,0)-1=0,4,ROUNDUP(MONTH(D3)/3,0)-1) -> 2023 Q1 | F3: Resultado Fiscal
A4: 8 de marzo de 2023 | B4: MXN $0.245729 | C4: =VALUE(SUBSTITUTE(SUBSTITUTE(B4,"MXN $",""),"","")) -> 0.245729 | D4: =SUBSTITUTE(SUBSTITUTE(A4,"de",""),"","") -> 8 marzo 2023 | E4: =IF(IF(ROUNDUP(MONTH(D4)/3,0)-1=0,4,ROUNDUP(MONTH(D4)/3,0)-1)=4,YEAR(D4)-1,YEAR(D4)) & " Q" & IF(ROUNDUP(MONTH(D4)/3,0)-1=0,4,ROUNDUP(MONTH(D4)/3,0)-1) -> 2022 Q4
A5: 8 de marzo de 2023 | B5: MXN $0.374271 | C5: =VALUE(SUBSTITUTE(SUBSTITUTE(B5,"MXN $",""),"","")) -> 0.374271 | D5: =SUBSTITUTE(SUBSTITUTE(A5,"de",""),"","") -> 8 marzo 2023 | E5: =IF(IF(ROUNDUP(MONTH(D5)/3,0)-1=0,4,ROUNDUP(MONTH(D5)/3,0)-1)=4,YEAR(D5)-1,YEAR(D5)) & " Q" & IF(ROUNDUP(MONTH(D5)/3,0)-1=0,4,ROUNDUP(MONTH(D5)/3,0)-1) -> 2022 Q4
A6: 9 de noviembre de 2022 | B6: MXN $0.26225 | C6: =VALUE(SUBSTITUTE(SUBSTITUTE(B6,"MXN $",""),"","")) -> 0.26225 | D6: =SUBSTITUTE(SUBSTITUTE(A6,"de",""),"","") -> 9 noviembre 2022 | E6: =IF(IF(ROUNDUP(MONTH(D6)/3,0)-1=0,4,ROUNDUP(MONTH(D6)/3,0)-1)=4,YEAR(D6)-1,YEAR(D6)) & " Q" & IF(ROUNDUP(MONTH(D6)/3,0)-1=0,4,ROUNDUP(MONTH(D6)/3,0)-1) -> 2022 Q3
A7: 9 de noviembre de 2022 | B7: MXN $0.33775 | C7: =VALUE(SUBSTITUTE(SUBSTITUTE(B7,"MXN $",""),"","")) -> 0.33775 | D7: =SUBSTITUTE(SUBSTITUTE(A7,"de",""),"","") -> 9 noviembre 2022 | E7: =IF(IF(ROUNDUP(MONTH(D7)/3,0)-1=0,4,ROUNDUP(MONTH(D7)/3,0)-1)=4,YEAR(D7)-1,YEAR(D7)) & " Q" & IF(ROUNDUP(MONTH(D7)/3,0)-1=0,4,ROUNDUP(MONTH(D7)/3,0)-1) -> 2022 Q3
A8: 11 de agosto de 2022 | B8: MXN $0.32361 | C8: =VALUE(SUBSTITUTE(SUBSTITUTE(B8,"MXN $",""),"","")) -> 0.32361 | D8: =SUBSTITUTE(SUBSTITUTE(A8,"de",""),"","") -> 11 agosto 2022 | E8: =IF(IF(ROUNDUP(MONTH(D8)/3,0)-1=0,4,ROUNDUP(MONTH(D8)/3,0)-1)=4,YEAR(D8)-1,YEAR(D8)) & " Q" & IF(ROUNDUP(MONTH(D8)/3,0)-1=0,4,ROUNDUP(MONTH(D8)/3,0)-1) -> 2022 Q2
A9: 11 de agosto de 2022 | B9: MXN $0.27639 | C9: =VALUE(SUBSTITUTE(SUBSTITUTE(B9,"MXN $",""),"","")) -> 0.27639 | D9: =SUBSTITUTE(SUBSTITUTE(A9,"de",""),"","") -> 11 agosto 2022 | E9: =IF(IF(ROUNDUP(MONTH(D9)/3,0)-1=0,4,ROUNDUP(MONTH(D9)/3,0)-1)=4,YEAR(D9)-1,YEAR(D9)) & " Q" & IF(ROUNDUP(MONTH(D9)/3,0)-1=0,4,ROUNDUP(MONTH(D9)/3,0)-1) -> 2022 Q2
A10: 10 de mayo de 2022 | B10: MXN $0.250482 | C10: =VALUE(SUBSTITUTE(SUBSTITUTE(B10,"MXN $",""),"","")) -> 0.250482 | D10: =SUBSTITUTE(SUBSTITUTE(A10,"de",""),"","") -> 10 mayo 2022 | E10: =IF(IF(ROUNDUP(MONTH(D10)/3,0)-1=0,4,ROUNDUP(MONTH(D10)/3,0)-1)=4,YEAR(D10)-1,YEAR(D10)) & " Q" & IF(ROUNDUP(MONTH(D10)/3,0)-1=0,4,ROUNDUP(MONTH(D10)/3,0)-1) -> 2022 Q1
A11: 10 de mayo de 2022 | B11: MXN $0.329518 | C11: =VALUE(SUBSTITUTE(SUBSTITUTE(B11,"MXN $",""),"","")) -> 0.329518 | D11: =SUBSTITUTE(SUBSTITUTE(A11,"de",""),"","") -> 10 mayo 2022 | E11: =IF(IF(ROUNDUP(MONTH(D11)/3,0)-1=0,4,ROUNDUP(MONTH(D11)/3,0)-1)=4,YEAR(D11)-1,YEAR(D11)) & " Q" & IF(ROUNDUP(MONTH(D11)/3,0)-1=0,4,ROUNDUP(MONTH(D11)/3,0)-1) -> 2022 Q1
A12: 9 de marzo de 2022 | B12: MXN $0.271285 | C12: =VALUE(SUBSTITUTE(SUBSTITUTE(B12,"MXN $",""),"","")) -> 0.271285 | D12: =SUBSTITUTE(SUBSTITUTE(A12,"de",""),"","") -> 9 marzo 2022 | E12: =IF(IF(ROUNDUP(MONTH(D12)/3,0)-1=0,4,ROUNDUP(MONTH(D12)/3,0)-1)=4,YEAR(D12)-1,YEAR(D12)) & " Q" & IF(ROUNDUP(MONTH(D12)/3,0)-1=0,4,ROUNDUP(MONTH(D12)/3,0)-1) -> 2021 Q4
A13: 9 de marzo de 2022 | B13: MXN $0.308715 | C13: =VALUE(SUBSTITUTE(SUBSTITUTE(B13,"MXN $",""),"","")) -> 0.308715 | D13: =SUBSTITUTE(SUBSTITUTE(A13,"de",""),"","") -> 9 marzo 2022 | E13: =IF(IF(ROUNDUP(MONTH(D13)/3,0)-1=0,4,ROUNDUP(MONTH(D13)/3,0)-1)=4,YEAR(D13)-1,YEAR(D13)) & " Q" & IF(ROUNDUP(MONTH(D13)/3,0)-1=0,4,ROUNDUP(MONTH(D13)/3,0)-1) -> 2021 Q4
A14: 10 de noviembre de 2021 | B14: MXN $0.251119 | C14: =VALUE(SUBSTITUTE(SUBSTITUTE(B14,"MXN $",""),"","")) -> 0.251119 | D14: =SUBSTITUTE(SUBSTITUTE(A14,"de",""),"","") -> 10 noviembre 2021 | E14: =IF(IF(ROUNDUP(MONTH(D14)/3,0)-1=0,4,ROUNDUP(MONTH(D14)/3,0)-1)=4,YEAR(D14)-1,YEAR(D14)) & " Q" & IF(ROUNDUP(MONTH(D14)/3,0)-1=0,4,ROUNDUP(MONTH(D14)/3,0)-1) -> 2021 Q3
A15: 10 de noviembre de 2021 | B15: MXN $0.268881 | C15: =VALUE(SUBSTITUTE(SUBSTITUTE(B15,"MXN $",""),"","")) -> 0.268881 | D15: =SUBSTITUTE(SUBSTITUTE(A15,"de",""),"","") -> 10 noviembre 2021 | E15: =IF(IF(ROUNDUP(MONTH(D15)/3,0)-1=0,4,ROUNDUP(MONTH(D15)/3,0)-1)=4,YEAR(D15)-1,YEAR(D15)) & " Q" & IF(ROUNDUP(MONTH(D15)/3,0)-1=0,4,ROUNDUP(MONTH(D15)/3,0)-1) -> 2021 Q3
... A39: 13 de marzo de 2018 | B39: MXN $0.397763 | C39: =VALUE(SUBSTITUTE(SUBSTITUTE(B39,"MXN $",""),"","")) -> 0.397763 | D39: =SUBSTITUTE(SUBSTITUTE(A39,"de",""),"","") -> 13 marzo 2018 | E39: =IF(IF(ROUNDUP(MONTH(D39)/3,0)-1=0,4,ROUNDUP(MONTH(D39)/3,0)-1)=4,YEAR(D39)-1,YEAR(D39)) & " Q" & IF(ROUNDUP(MONTH(D39)/3,0)-1=0,4,ROUNDUP(MONTH(D39)/3,0)-1) -> 2017 Q4

Sheet FIBRAUP18
A1: Variable | B1: 2023 Q1 | C1: 2022 Q4 | D1: 2022 Q3 | E1: 2022 Q2 | F1: 2022 Q1 | G1: 2021 Q4 | H1: 2021 Q3 | I1: 2021 Q2 | J1: 2021 Q1 | K1: 2020 Q4 | L1: 2020 Q3 | M1: 2020 Q2 | N1: 2020 Q1 | O1: 2019 Q4 | P1: 2019 Q3 | Q1: 2019 Q2 | R1: 2019 Q1
A2: Ingresos Rentas | C2: 37085000 | D2: 31804000 | E2: 29409000 | F2: 19818000 | G2: 23564000 | H2: 19731000 | I2: 15729000 | J2: 15549000 | K2: 16224000 | L2: 17751516 | M2: 9548261 | N2: 5207320 | O2: 0 | P2: - | Q2: - | R2: -
A3: Ingresos Totales | C3: 37085000 | D3: 31804000 | E3: 29409000 | F3: 19818000 | G3: 23564000 | H3: 19731000 | I3: 15729000 | J3: 15549000 | K3: 16224000 | L3: 17751516 | M3: 9548261 | N3: 5207320 | O3: 0 | P3: - | Q3: - | R3: -
A4: NOI | C4: 29750931 | D4: 25200235 | E4: 24800295 | F4: 16012980 | G4: 20225382 | H4: 16825065 | I4: 13087579 | J4: 14029745 | K4: 13833496 | L4: - | M4: - | N4: - | O4: 0 | P4: - | Q4: 0 | R4: 0
A5: Margen NOI | C5: 0.8022 | D5: 0.7924 | E5: 0.8433 | F5: 0.808 | G5: 0.8583 | H5: 0.8527 | I5: 0.8321 | J5: 0.9023 | K5: 1 | L5: 0 | M5: 0 | N5: 0 | O5: 0 | P5: 0 | Q5: 0 | R5: 0
A6: FFO | C6: 6046986 | D6: -90691247 | E6: -9062672 | F6: -5512767 | G6: 6291659 | H6: 5119428 | I6: 4304030 | J6: 7007825 | K6: - | L6: - | M6: - | N6: - | O6: 0 | P6: - | Q6: - | R6: -
A7: Margen FFO que reporta la FIBRA | C7: 0.1631 | D7: -2.8516 | E7: -0.3082 | F7: -0.2782 | G7: 0.267 | H7: 0.2595 | I7: 0.2736 | J7: 0.4507 | K7: 0 | L7: 0 | M7: 0 | N7: 0 | O7: 0 | P7: 0 | Q7: 0 | R7: 0
A8: FFO que reporta la FIBRA por CBFI | C8: 0.11 | D8: -1.61 | E8: -0.16 | F8: -0.1 | G8: 0.11 | H8: 0.09 | I8: 0.08 | J8: 0.12 | K8: 0 | L8: 0 | M8: 0 | N8: 0 | O8: 0 | P8: 0 | Q8: 0 | R8: 0
A9: Dividendos Decretados | C9: 0 | D9: 0 | E9: 0 | F9: 0 | G9: 0 | H9: 0 | I9: 0 | J9: 0 | K9: 0 | L9: 0 | M9: 0 | N9: 0 | O9: 0 | P9: 0 | Q9: 0 | R9: 0
A10: Dividendos decretados por CBFI | C10: 0 | D10: 0 | E10: 0 | F10: 0 | G10: 0 | H10: 0 | I10: 0 | J10: 0 | K10: 0 | L10: 0 | M10: 0 | N10: 0 | O10: 0 | P10: - | Q10: - | R10: -
A11: CBFIS en Circulación | C11: 56257000 | D11: 56257000 | E11: 56257000 | F11: 56257000 | G11: 56257000 | H11: 56257365 | I11: 56257365 | J11: 56257365 | K11: 56257365 | L11: 56257365 | M11: 29108445 | N11: 29108445 | O11: 32399312 | P11: 32399312 | Q11: 32399312 | R11: 32399312
A12: Cape Rate Implicito | C12: 0.0427 | D12: 0.0391
A13: Capitalización de Mercado | C13: 1.7608555e+09 | D13: 1800224000
A14: Descuento o Premium sobre NAV | C14: -0.4166 | D14: -0.3918
A15: LTV | C15: 0.2454 | D15: 0.2561
A16: Dividend Yield (Decretado) | C16: 0 | D16: 0
A17: NAV por CBDI | C17: 53.82 | D17: 52.61
A18: ROE Tangible | C18: -0.0225 | D18: -0.0249

Sheet FNOVA17
A1: FNOVA17 | B1: 2023 Q1 | C1: 2022 Q4 | D1: 2022 Q3 | E1: 2022 Q2 | F1: 2022 Q1 | G1: 2021 Q4 | H1: 2021 Q3 | I1: 2021 Q2 | J1: 2021 Q1 | K1: 2020 Q4 | L1: 2020 Q3 | M1: 2020 Q2 | N1: 2020 Q1 | O1: 2019 Q4 | P1: 2019 Q3 | Q1: 2019 Q2 | R1: 2019 Q1
A2: Ingresos Rentas | B2: 252040000 | C2: 256623000 | D2: 256105000 | E2: 237270000 | F2: 229630000 | G2: 221138000 | H2: 154456000 | I2: 148727000 | J2: 143034000 | K2: 141641000 | L2: 142309000 | M2: 143619000 | N2: 129282000 | O2: 117739000 | P2: 116931000 | Q2: 117499000 | R2: 117696000
A3: Ingresos Totales | B3: 260117000 | C3: 263660000 | D3: 263037000 | E3: 243514000 | F3: 235178000 | G3: 231587000 | H3: 161753000 | I3: 153099000 | J3: 144088000 | K3: 142672000 | L3: 143831000 | M3: 144439000 | N3: 130233000 | O3: 118836000 | P3: 117436000 | Q3: 117847000 | R3: 118206000
A4: NOI | B4: 253018000 | C4: 256163000 | D4: 255600000 | E4: 236398000 | F4: 228357000 | G4: 226122000 | H4: 156614000 | I4: 148802000 | J4: 139878000 | K4: 138895000 | L4: 139564000 | M4: 140303000 | N4: 126457000 | O4: 114751000 | P4: 114026000 | Q4: 114472000 | R4: 114644000
A5: Margen NOI | B5: 0.9727 | C5: 0.9716 | D5: 0.9717 | E5: 0.9708 | F5: 0.971 | G5: 0.9764 | H5: 0.9682 | I5: 0.9719 | J5: 0.9708 | K5: 0.9735 | L5: 0.9703 | M5: 0.9714 | N5: 0.971 | O5: 0.9656 | P5: 0.971 | Q5: 0.9714 | R5: 0.9699
A6: FFO | B6: 210800000 | C6: 210300000 | D6: 205400000 | E6: 201123000 | F6: 196102000 | G6: 185830000 | H6: 132831000 | I6: 121802000 | J6: 116811000 | K6: 111750000 | L6: 113120000 | M6: 113570000 | N6: 106689000 | O6: 104757000 | P6: 101390000 | Q6: 100275000 | R6: 96232000
A7: Margen FFO que reporta la FIBRA | B7: 0.8104 | C7: 0.7976 | D7: 0.7809 | E7: 0.8259 | F7: 0.8338 | G7: 0.8024 | H7: 0.8212 | I7: 0.7956 | J7: 0.8107 | K7: 0.7833 | L7: 0.7865 | M7: 0.7863 | N7: 0.8192 | O7: 0.8815 | P7: 0.6972 | Q7: 0.8509 | R7: 0.8608
A8: FFO que reporta la FIBRA por CBFI | B8: 0.63 | C8: 0.63 | D8: 0.61 | E8: 0.6 | F8: 0.58 | G8: 0.55 | H8: 0.4 | I8: 0.36 | J8: 0.48 | K8: 0.46 | L8: 0.47 | M8: 0.47 | N8: 0.44 | O8: 0.43 | P8: 0.34 | Q8: 0.41 | R8: 0.42
A9: Dividendos Decretados | B9: 1.942895e+08 | C9: 1.9480822e+08 | D9: 1.9383451e+08 | E9: 1.9063271e+08 | F9: 1.9059213e+08 | G9: 1.797165e+08 | H9: 1.5526602e+08 | I9: 1.5525215e+08 | J9: 1.1174523e+08 | K9: 1.1174523e+08 | L9: 1.1356916e+08 | M9: 1.0669019e+08 | N9: 1.047951e+08 | O9: 1.0139317e+08 | P9: 1.0138542e+08 | Q9: 1.0075675e+08 | R9: 96228124
A10: Dividendos decretados por CBFI | B10: {=IF(SUMIFS(INDIRECT("'"&A$1&"_DIV'!"&"C:C"),INDIRECT("'"&A$1&"_DIV'!"&"E:E"),B1)=0,"",SUMIFS(INDIRECT("'"&A$1&"_DIV'!"&"C:C"),INDIRECT("'"&A$1&"_DIV'!"&"E:E"),B1))} -> 0.5797 | C10: {=SUMIFS(INDIRECT("'"&A$1&"_DIV'!"&"C:C"),INDIRECT("'"&A$1&"_DIV'!"&"E:E"),C1)} -> 0.580578 | D10: {=SUMIFS(INDIRECT("'"&A$1&"_DIV'!"&"C:C"),INDIRECT("'"&A$1&"_DIV'!"&"E:E"),D1)} -> 0.55953 | E10: {=SUMIFS(INDIRECT("'"&A$1&"_DIV'!"&"C:C"),INDIRECT("'"&A$1&"_DIV'!"&"E:E"),E1)} -> 0.577344 | F10: {=SUMIFS(INDIRECT("'"&A$1&"_DIV'!"&"C:C"),INDIRECT("'"&A$1&"_DIV'!"&"E:E"),F1)} -> 0 | G10: 0.54 | H10: 0.46 | I10: 0.46 | J10: 0.46 | K10: 0.46 | L10: 0.47 | M10: 0.44 | N10: 0.43 | O10: 0.42 | P10: 0.42 | Q10: 0.4 | R10: 0.39
A11: CBFIS en Circulación | B11: 335560456 | C11: 335760456 | D11: 335760456 | E11: 335739184 | F11: 335667723 | G11: 335667723 | H11: 335637733 | I11: 335607770 | J11: 241715825 | K11: 241715825 | L11: 241893855 | M11: 241873024 | N11: 241853455 | O11: 241815338 | P11: 241796858 | Q11: 241796858 | R11: 241779207
A12: Cape Rate Implicito | B12: 0.0762 | C12: 0.0764 | D12: 0.0779
A13: Capitalización de Mercado | B13: 1.0284928e+10 | C13: 1.0908226e+10 | D13: 9.6799739e+09
A14: Descuento o Premium sobre NAV | B14: 0.5016 | C14: 0.4124 | D14: 0.3079
A15: LTV | B15: 0.4783 | C15: 0.4627 | D15: 0.4391
A16: Dividend Yield (Decretado) | B16: 0.0756 | C16: 0.0569 | D16: 0.0801
A17: NAV por CBDI | B17: 20.41 | C17: 21.59 | D17: 22.04
A18: ROE Tangible | B18: 0.273 | C18: 0.1372 | D18: 0.1229

Sheet FNOVA17_DIV
A1: Fecha de pago | B1: Importe
A2: 11 de mayo de 2023 | B2: MXN $0.5797 | C2: =VALUE(SUBSTITUTE(SUBSTITUTE(B2,"MXN $",""),"","")) -> 0.5797 | D2: =SUBSTITUTE(SUBSTITUTE(A2,"de",""),"","") -> 11 mayo 2023 | E2: =IF(IF(ROUNDUP(MONTH(D2)/3,0)-1=0,4,ROUNDUP(MONTH(D2)/3,0)-1)=4,YEAR(D2)-1,YEAR(D2)) & " Q" & IF(ROUNDUP(MONTH(D2)/3,0)-1=0,4,ROUNDUP(MONTH(D2)/3,0)-1) -> 2023 Q1 | F2: Reembolso de Capital
A3: 21 de febrero de 2023 | B3: MXN $0.580578 | C3: =VALUE(SUBSTITUTE(SUBSTITUTE(B3,"MXN $",""),"","")) -> 0.580578 | D3: =SUBSTITUTE(SUBSTITUTE(A3,"de",""),"","") -> 21 febrero 2023 | E3: =IF(IF(ROUNDUP(MONTH(D3)/3,0)-1=0,4,ROUNDUP(MONTH(D3)/3,0)-1)=4,YEAR(D3)-1,YEAR(D3)) & " Q" & IF(ROUNDUP(MONTH(D3)/3,0)-1=0,4,ROUNDUP(MONTH(D3)/3,0)-1) -> 2022 Q4 | F3: Reembolso de Capital
A4: 15 de noviembre de 2022 | B4: MXN $0.55953 | C4: =VALUE(SUBSTITUTE(SUBSTITUTE(B4,"MXN $",""),"","")) -> 0.55953 | D4: =SUBSTITUTE(SUBSTITUTE(A4,"de",""),"","") -> 15 noviembre 2022 | E4: =IF(IF(ROUNDUP(MONTH(D4)/3,0)-1=0,4,ROUNDUP(MONTH(D4)/3,0)-1)=4,YEAR(D4)-1,YEAR(D4)) & " Q" & IF(ROUNDUP(MONTH(D4)/3,0)-1=0,4,ROUNDUP(MONTH(D4)/3,0)-1) -> 2022 Q3
A5: 28 de julio de 2022 | B5: MXN $0.577344 | C5: =VALUE(SUBSTITUTE(SUBSTITUTE(B5,"MXN $",""),"","")) -> 0.577344 | D5: =SUBSTITUTE(SUBSTITUTE(A5,"de",""),"","") -> 28 julio 2022 | E5: =IF(IF(ROUNDUP(MONTH(D5)/3,0)-1=0,4,ROUNDUP(MONTH(D5)/3,0)-1)=4,YEAR(D5)-1,YEAR(D5)) & " Q" & IF(ROUNDUP(MONTH(D5)/3,0)-1=0,4,ROUNDUP(MONTH(D5)/3,0)-1) -> 2022 Q2
A6: 10 de marzo de 2022 | B6: MXN $0.53541 | C6: =VALUE(SUBSTITUTE(SUBSTITUTE(B6,"MXN $",""),"","")) -> 0.53541 | D6: =SUBSTITUTE(SUBSTITUTE(A6,"de",""),"","") -> 10 marzo 2022 | E6: =IF(IF(ROUNDUP(MONTH(D6)/3,0)-1=0,4,ROUNDUP(MONTH(D6)/3,0)-1)=4,YEAR(D6)-1,YEAR(D6)) & " Q" & IF(ROUNDUP(MONTH(D6)/3,0)-1=0,4,ROUNDUP(MONTH(D6)/3,0)-1) -> 2021 Q4
A7: 17 de noviembre de 2021 | B7: MXN $0.463032 | C7: =VALUE(SUBSTITUTE(SUBSTITUTE(B7,"MXN $",""),"","")) -> 0.463032 | D7: =SUBSTITUTE(SUBSTITUTE(A7,"de",""),"","") -> 17 noviembre 2021 | E7: =IF(IF(ROUNDUP(MONTH(D7)/3,0)-1=0,4,ROUNDUP(MONTH(D7)/3,0)-1)=4,YEAR(D7)-1,YEAR(D7)) & " Q" & IF(ROUNDUP(MONTH(D7)/3,0)-1=0,4,ROUNDUP(MONTH(D7)/3,0)-1) -> 2021 Q3
A8: 10 de agosto de 2021 | B8: MXN $0.462611 | C8: =VALUE(SUBSTITUTE(SUBSTITUTE(B8,"MXN $",""),"","")) -> 0.462611 | D8: =SUBSTITUTE(SUBSTITUTE(A8,"de",""),"","") -> 10 agosto 2021 | E8: =IF(IF(ROUNDUP(MONTH(D8)/3,0)-1=0,4,ROUNDUP(MONTH(D8)/3,0)-1)=4,YEAR(D8)-1,YEAR(D8)) & " Q" & IF(ROUNDUP(MONTH(D8)/3,0)-1=0,4,ROUNDUP(MONTH(D8)/3,0)-1) -> 2021 Q2
A9: 11 de mayo de 2021 | B9: MXN $0.462256 | C9: =VALUE(SUBSTITUTE(SUBSTITUTE(B9,"MXN $",""),"","")) -> 0.462256 | D9: =SUBSTITUTE(SUBSTITUTE(A9,"de",""),"","") -> 11 mayo 2021 | E9: =IF(IF(ROUNDUP(MONTH(D9)/3,0)-1=0,4,ROUNDUP(MONTH(D9)/3,0)-1)=4,YEAR(D9)-1,YEAR(D9)) & " Q" & IF(ROUNDUP(MONTH(D9)/3,0)-1=0,4,ROUNDUP(MONTH(D9)/3,0)-1) -> 2021 Q1
A10: 17 de marzo de 2021 | B10: MXN $0.46232 | C10: =VALUE(SUBSTITUTE(SUBSTITUTE(B10,"MXN $",""),"","")) -> 0.46232 | D10: =SUBSTITUTE(SUBSTITUTE(A10,"de",""),"","") -> 17 marzo 2021 | E10: =IF(IF(ROUNDUP(MONTH(D10)/3,0)-1=0,4,ROUNDUP(MONTH(D10)/3,0)-1)=4,YEAR(D10)-1,YEAR(D10)) & " Q" & IF(ROUNDUP(MONTH(D10)/3,0)-1=0,4,ROUNDUP(MONTH(D10)/3,0)-1) -> 2020 Q4
A11: 18 de noviembre de 2020 | B11: MXN $0.468028 | C11: =VALUE(SUBSTITUTE(SUBSTITUTE(B11,"MXN $",""),"","")) -> 0.468028 | D11: =SUBSTITUTE(SUBSTITUTE(A11,"de",""),"","") -> 18 noviembre 2020 | E11: =IF(IF(ROUNDUP(MONTH(D11)/3,0)-1=0,4,ROUNDUP(MONTH(D11)/3,0)-1)=4,YEAR(D11)-1,YEAR(D11)) & " Q" & IF(ROUNDUP(MONTH(D11)/3,0)-1=0,4,ROUNDUP(MONTH(D11)/3,0)-1) -> 2020 Q3
A12: 13 de agosto de 2020 | B12: MXN $0.469544 | C12: =VALUE(SUBSTITUTE(SUBSTITUTE(B12,"MXN $",""),"","")) -> 0.469544 | D12: =SUBSTITUTE(SUBSTITUTE(A12,"de",""),"","") -> 13 agosto 2020 | E12: =IF(IF(ROUNDUP(MONTH(D12)/3,0)-1=0,4,ROUNDUP(MONTH(D12)/3,0)-1)=4,YEAR(D12)-1,YEAR(D12)) & " Q" & IF(ROUNDUP(MONTH(D12)/3,0)-1=0,4,ROUNDUP(MONTH(D12)/3,0)-1) -> 2020 Q2
A13: 20 de mayo de 2020 | B13: MXN $0.441131 | C13: =VALUE(SUBSTITUTE(SUBSTITUTE(B13,"MXN $",""),"","")) -> 0.441131 | D13: =SUBSTITUTE(SUBSTITUTE(A13,"de",""),"","") -> 20 mayo 2020 | E13: =IF(IF(ROUNDUP(MONTH(D13)/3,0)-1=0,4,ROUNDUP(MONTH(D13)/3,0)-1)=4,YEAR(D13)-1,YEAR(D13)) & " Q" & IF(ROUNDUP(MONTH(D13)/3,0)-1=0,4,ROUNDUP(MONTH(D13)/3,0)-1) -> 2020 Q1
A14: 29 de noviembre de 2019 | B14: MXN $0.419319 | C14: =VALUE(SUBSTITUTE(SUBSTITUTE(B14,"MXN $",""),"","")) -> 0.419319 | D14: =SUBSTITUTE(SUBSTITUTE(A14,"de",""),"","") -> 29 noviembre 2019 | E14: =IF(IF(ROUNDUP(MONTH(D14)/3,0)-1=0,4,ROUNDUP(MONTH(D14)/3,0)-1)=4,YEAR(D14)-1,YEAR(D14)) & " Q" & IF(ROUNDUP(MONTH(D14)/3,0)-1=0,4,ROUNDUP(MONTH(D14)/3,0)-1) -> 2019 Q3
A15: 28 de agosto de 2019 | B15: MXN $0.416672 | C15: =VALUE(SUBSTITUTE(SUBSTITUTE(B15,"MXN $",""),"","")) -> 0.416672 | D15: =SUBSTITUTE(SUBSTITUTE(A15,"de",""),"","") -> 28 agosto 2019 | E15: =IF(IF(ROUNDUP(MONTH(D15)/3,0)-1=0,4,ROUNDUP(MONTH(D15)/3,0)-1)=4,YEAR(D15)-1,YEAR(D15)) & " Q" & IF(ROUNDUP(MONTH(D15)/3,0)-1=0,4,ROUNDUP(MONTH(D15)/3,0)-1) -> 2019 Q2
... A21: 7 de marzo de 2018 | B21: MXN $0.367326 | C21: =VALUE(SUBSTITUTE(SUBSTITUTE(B21,"MXN $",""),"","")) -> 0.367326 | D21: =SUBSTITUTE(SUBSTITUTE(A21,"de",""),"","") -> 7 marzo 2018 | E21: =IF(IF(ROUNDUP(MONTH(D21)/3,0)-1=0,4,ROUNDUP(MONTH(D21)/3,0)-1)=4,YEAR(D21)-1,YEAR(D21)) & " Q" & IF(ROUNDUP(MONTH(D21)/3,0)-1=0,4,ROUNDUP(MONTH(D21)/3,0)-1) -> 2017 Q4

Sheet FPLUS16
A1: Variable | B1: 2023 Q1 | C1: 2022 Q4 | D1: 2022 Q3 | E1: 2022 Q2 | F1: 2022 Q1 | G1: 2021 Q4 | H1: 2021 Q3 | I1: 2021 Q2 | J1: 2021 Q1 | K1: 2020 Q4 | L1: 2020 Q3 | M1: 2020 Q2 | N1: 2020 Q1 | O1: 2019 Q4 | P1: 2019 Q3 | Q1: 2019 Q2 | R1: 2019 Q1
A2: Ingresos Rentas | C2: 172544000 | D2: 174075000 | E2: 176000000 | F2: 175381000 | G2: 532249000 | H2: 34490000 | I2: 28325000 | J2: 28673000 | K2: 29873000 | L2: 30979000 | M2: 32471000 | N2: 27319000 | O2: 27135000 | P2: 26643000 | Q2: 26160000 | R2: 26787000
A3: Ingresos Totales | C3: 172544000 | D3: 174075000 | E3: 176000000 | F3: 175381000 | G3: 532249000 | H3: 34490000 | I3: 28325000 | J3: 29039000 | K3: 29873000 | L3: 30979000 | M3: 32471000 | N3: 27319000 | O3: 27135000 | P3: 26643000 | Q3: 26160000 | R3: 26787000
A4: NOI | C4: 136907000 | D4: 141265000 | E4: 148487000 | F4: 156209000 | G4: 78069000 | H4: 29832000 | I4: 25043000 | J4: 25599000 | K4: 26501000 | L4: 28850000 | M4: 30550000 | N4: 26089000 | O4: 24151000 | P4: 26605000 | Q4: 25400000 | R4: 25891000
A5: Margen NOI | C5: 0.7935 | D5: 0.8115 | E5: 0.8437 | F5: 0.8907 | G5: 0.1467 | H5: 0.8649 | I5: 0.8841 | J5: 0.8815 | K5: 0.8871 | L5: 0.9313 | M5: 0.9408 | N5: 0.955 | O5: 0.89 | P5: 0.9986 | Q5: 0.9709 | R5: 0.9666
A6: FFO | C6: 48206000 | D6: -34159000 | E6: 60293000 | F6: 115512000 | G6: - | H6: - | I6: - | J6: - | K6: - | L6: - | M6: - | N6: - | O6: - | P6: - | Q6: - | R6: -
A7: Margen FFO que reporta la FIBRA | C7: 0.2794 | D7: -0.1962 | E7: 0.3426 | F7: 0.6586 | G7: - | H7: - | I7: 0 | J7: 0 | K7: 0 | L7: 0 | M7: 0 | N7: 0 | O7: 0 | P7: 0 | Q7: 0 | R7: 0
A8: FFO que reporta la FIBRA por CBFI | C8: 0.08 | D8: -0.05 | E8: 0.1 | F8: 0.23 | G8: - | H8: 0 | I8: 0 | J8: 0 | K8: 0 | L8: 0 | M8: 0 | N8: 0 | O8: 0 | P8: 0 | Q8: 0 | R8: 0
A9: Dividendos Decretados | C9: 0 | D9: 0 | E9: 0 | F9: 0 | G9: 0 | H9: 0 | I9: 0 | J9: 0 | K9: 0 | L9: 0 | M9: 0 | N9: 0 | O9: 0 | P9: 0 | Q9: 0 | R9: 0
A10: Dividendos decretados por CBFI | B10: 0.0868 | C10: 0 | D10: 0 | E10: 0 | F10: 0 | G10: 0 | H10: 0 | I10: 0 | J10: 0 | K10: 0 | L10: 0 | M10: 0 | N10: 0 | O10: 0 | P10: - | Q10: 0 | R10: 0
A11: CBFIS en Circulación | C11: 626321948 | D11: 625412588 | E11: 625412588 | F11: 509111556 | G11: 509873745 | H11: 373526198 | I11: 373023131 | J11: 373526198 | K11: 373526198 | L11: 373766700 | M11: 373766700 | N11: 373766700 | O11: 373023131 | P11: 373023131 | Q11: 373023131 | R11: 373023131
A12: Cape Rate Implicito | C12: 0.0368 | D12: 0.0387
A13: Capitalización de Mercado | C13: 2.2971861e+09 | D13: 4.6280532e+09
A14: Descuento o Premium sobre NAV | C14: -0.5797 | D14: -0.5768
A15: LTV | C15: 0.2454 | D15: 0.2789
A16: Dividend Yield (Decretado) | C16: 0 | D16: 0
A17: NAV por CBDI | C17: 17.49 | D17: 17.48
A18: ROE Tangible | C18: -0.0111 | D18: -0.0223

Sheet FMTY14_DIV
A1: Fecha de pago | B1: Importe
A2: 31 de marzo de 2023 | B2: MXN $0.085 | C2: =VALUE(SUBSTITUTE(SUBSTITUTE(B2,"MXN $",""),"","")) -> 0.085 | D2: =SUBSTITUTE(SUBSTITUTE(A2,"de",""),"","") -> 31 marzo 2023 | E2: =IF(IF(ROUNDUP(MONTH(D2)/3,0)-1=0,4,ROUNDUP(MONTH(D2)/3,0)-1)=4,YEAR(D2)-1,YEAR(D2)) & " Q" & IF(ROUNDUP(MONTH(D2)/3,0)-1=0,4,ROUNDUP(MONTH(D2)/3,0)-1) -> 2022 Q4 | F2: Reembolso de Capital
A3: 24 de febrero de 2023 | B3: MXN $0.138411 | C3: =VALUE(SUBSTITUTE(SUBSTITUTE(B3,"MXN $",""),"","")) -> 0.138411 | D3: =SUBSTITUTE(SUBSTITUTE(A3,"de",""),"","") -> 24 febrero 2023 | E3: =IF(IF(ROUNDUP(MONTH(D3)/3,0)-1=0,4,ROUNDUP(MONTH(D3)/3,0)-1)=4,YEAR(D3)-1,YEAR(D3)) & " Q" & IF(ROUNDUP(MONTH(D3)/3,0)-1=0,4,ROUNDUP(MONTH(D3)/3,0)-1) -> 2022 Q4 | F3: Resultado Fiscal
A4: 31 de enero de 2023 | B4: MXN $0.085256 | C4: =VALUE(SUBSTITUTE(SUBSTITUTE(B4,"MXN $",""),"","")) -> 0.085256 | D4: =SUBSTITUTE(SUBSTITUTE(A4,"de",""),"","") -> 31 enero 2023 | E4: =IF(IF(ROUNDUP(MONTH(D4)/3,0)-1=0,4,ROUNDUP(MONTH(D4)/3,0)-1)=4,YEAR(D4)-1,YEAR(D4)) & " Q" & IF(ROUNDUP(MONTH(D4)/3,0)-1=0,4,ROUNDUP(MONTH(D4)/3,0)-1) -> 2022 Q4 | F4: Resultado Fiscal
A5: 30 de diciembre de 2022 | B5: MXN $0.058403 | C5: =VALUE(SUBSTITUTE(SUBSTITUTE(B5,"MXN $",""),"","")) -> 0.058403 | D5: =SUBSTITUTE(SUBSTITUTE(A5,"de",""),"","") -> 30 diciembre 2022 | E5: =IF(IF(ROUNDUP(MONTH(D5)/3,0)-1=0,4,ROUNDUP(MONTH(D5)/3,0)-1)=4,YEAR(D5)-1,YEAR(D5)) & " Q" & IF(ROUNDUP(MONTH(D5)/3,0)-1=0,4,ROUNDUP(MONTH(D5)/3,0)-1) -> 2022 Q3
A6: 30 de diciembre de 2022 | B6: MXN $0.02503 | C6: =VALUE(SUBSTITUTE(SUBSTITUTE(B6,"MXN $",""),"","")) -> 0.02503 | D6: =SUBSTITUTE(SUBSTITUTE(A6,"de",""),"","") -> 30 diciembre 2022 | E6: =IF(IF(ROUNDUP(MONTH(D6)/3,0)-1=0,4,ROUNDUP(MONTH(D6)/3,0)-1)=4,YEAR(D6)-1,YEAR(D6)) & " Q" & IF(ROUNDUP(MONTH(D6)/3,0)-1=0,4,ROUNDUP(MONTH(D6)/3,0)-1) -> 2022 Q3
A7: 30 de noviembre de 2022 | B7: MXN $0.058404 | C7: =VALUE(SUBSTITUTE(SUBSTITUTE(B7,"MXN $",""),"","")) -> 0.058404 | D7: =SUBSTITUTE(SUBSTITUTE(A7,"de",""),"","") -> 30 noviembre 2022 | E7: =IF(IF(ROUNDUP(MONTH(D7)/3,0)-1=0,4,ROUNDUP(MONTH(D7)/3,0)-1)=4,YEAR(D7)-1,YEAR(D7)) & " Q" & IF(ROUNDUP(MONTH(D7)/3,0)-1=0,4,ROUNDUP(MONTH(D7)/3,0)-1) -> 2022 Q3
A8: 30 de noviembre de 2022 | B8: MXN $0.02503 | C8: =VALUE(SUBSTITUTE(SUBSTITUTE(B8,"MXN $",""),"","")) -> 0.02503 | D8: =SUBSTITUTE(SUBSTITUTE(A8,"de",""),"","") -> 30 noviembre 2022 | E8: =IF(IF(ROUNDUP(MONTH(D8)/3,0)-1=0,4,ROUNDUP(MONTH(D8)/3,0)-1)=4,YEAR(D8)-1,YEAR(D8)) & " Q" & IF(ROUNDUP(MONTH(D8)/3,0)-1=0,4,ROUNDUP(MONTH(D8)/3,0)-1) -> 2022 Q3
A9: 31 de octubre de 2022 | B9: MXN $0.058404 | C9: =VALUE(SUBSTITUTE(SUBSTITUTE(B9,"MXN $",""),"","")) -> 0.058404 | D9: =SUBSTITUTE(SUBSTITUTE(A9,"de",""),"","") -> 31 octubre 2022 | E9: =IF(IF(ROUNDUP(MONTH(D9)/3,0)-1=0,4,ROUNDUP(MONTH(D9)/3,0)-1)=4,YEAR(D9)-1,YEAR(D9)) & " Q" & IF(ROUNDUP(MONTH(D9)/3,0)-1=0,4,ROUNDUP(MONTH(D9)/3,0)-1) -> 2022 Q3
A10: 31 de octubre de 2022 | B10: MXN $0.02503 | C10: =VALUE(SUBSTITUTE(SUBSTITUTE(B10,"MXN $",""),"","")) -> 0.02503 | D10: =SUBSTITUTE(SUBSTITUTE(A10,"de",""),"","") -> 31 octubre 2022 | E10: =IF(IF(ROUNDUP(MONTH(D10)/3,0)-1=0,4,ROUNDUP(MONTH(D10)/3,0)-1)=4,YEAR(D10)-1,YEAR(D10)) & " Q" & IF(ROUNDUP(MONTH(D10)/3,0)-1=0,4,ROUNDUP(MONTH(D10)/3,0)-1) -> 2022 Q3
A11: 12 de septiembre de 2022 | B11: MXN $0.033582 | C11: =VALUE(SUBSTITUTE(SUBSTITUTE(B11,"MXN $",""),"","")) -> 0.033582 | D11: =SUBSTITUTE(SUBSTITUTE(A11,"de",""),"","") -> 12 septiembre 2022 | E11: =IF(IF(ROUNDUP(MONTH(D11)/3,0)-1=0,4,ROUNDUP(MONTH(D11)/3,0)-1)=4,YEAR(D11)-1,YEAR(D11)) & " Q" & IF(ROUNDUP(MONTH(D11)/3,0)-1=0,4,ROUNDUP(MONTH(D11)/3,0)-1) -> 2022 Q2
A12: 12 de septiembre de 2022 | B12: MXN $0.050373 | C12: =VALUE(SUBSTITUTE(SUBSTITUTE(B12,"MXN $",""),"","")) -> 0.050373 | D12: =SUBSTITUTE(SUBSTITUTE(A12,"de",""),"","") -> 12 septiembre 2022 | E12: =IF(IF(ROUNDUP(MONTH(D12)/3,0)-1=0,4,ROUNDUP(MONTH(D12)/3,0)-1)=4,YEAR(D12)-1,YEAR(D12)) & " Q" & IF(ROUNDUP(MONTH(D12)/3,0)-1=0,4,ROUNDUP(MONTH(D12)/3,0)-1) -> 2022 Q2
A13: 31 de agosto de 2022 | B13: MXN $0.033582 | C13: =VALUE(SUBSTITUTE(SUBSTITUTE(B13,"MXN $",""),"","")) -> 0.033582 | D13: =SUBSTITUTE(SUBSTITUTE(A13,"de",""),"","") -> 31 agosto 2022 | E13: =IF(IF(ROUNDUP(MONTH(D13)/3,0)-1=0,4,ROUNDUP(MONTH(D13)/3,0)-1)=4,YEAR(D13)-1,YEAR(D13)) & " Q" & IF(ROUNDUP(MONTH(D13)/3,0)-1=0,4,ROUNDUP(MONTH(D13)/3,0)-1) -> 2022 Q2
A14: 31 de agosto de 2022 | B14: MXN $0.050373 | C14: =VALUE(SUBSTITUTE(SUBSTITUTE(B14,"MXN $",""),"","")) -> 0.050373 | D14: =SUBSTITUTE(SUBSTITUTE(A14,"de",""),"","") -> 31 agosto 2022 | E14: =IF(IF(ROUNDUP(MONTH(D14)/3,0)-1=0,4,ROUNDUP(MONTH(D14)/3,0)-1)=4,YEAR(D14)-1,YEAR(D14)) & " Q" & IF(ROUNDUP(MONTH(D14)/3,0)-1=0,4,ROUNDUP(MONTH(D14)/3,0)-1) -> 2022 Q2
A15: 29 de julio de 2022 | B15: MXN $0.033582 | C15: =VALUE(SUBSTITUTE(SUBSTITUTE(B15,"MXN $",""),"","")) -> 0.033582 | D15: =SUBSTITUTE(SUBSTITUTE(A15,"de",""),"","") -> 29 julio 2022 | E15: =IF(IF(ROUNDUP(MONTH(D15)/3,0)-1=0,4,ROUNDUP(MONTH(D15)/3,0)-1)=4,YEAR(D15)-1,YEAR(D15)) & " Q" & IF(ROUNDUP(MONTH(D15)/3,0)-1=0,4,ROUNDUP(MONTH(D15)/3,0)-1) -> 2022 Q2
A16: 29 de julio de 2022 | B16: MXN $0.050373 | C16: =VALUE(SUBSTITUTE(SUBSTITUTE(B16,"MXN $",""),"","")) -> 0.050373 | D16: =SUBSTITUTE(SUBSTITUTE(A16,"de",""),"","") -> 29 julio 2022 | E16: =IF(IF(ROUNDUP(MONTH(D16)/3,0)-1=0,4,ROUNDUP(MONTH(D16)/3,0)-1)=4,YEAR(D16)-1,YEAR(D16)) & " Q" & IF(ROUNDUP(MONTH(D16)/3,0)-1=0,4,ROUNDUP(MONTH(D16)/3,0)-1) -> 2022 Q2
... A68: 28 de febrero de 2018 | B68: MXN $0.259865 | C68: =VALUE(SUBSTITUTE(SUBSTITUTE(B68,"MXN $",""),"","")) -> 0.259865 | D68: =SUBSTITUTE(SUBSTITUTE(A68,"de",""),"","") -> 28 febrero 2018 | E68: =IF(IF(ROUNDUP(MONTH(D68)/3,0)-1=0,4,ROUNDUP(MONTH(D68)/3,0)-1)=4,YEAR(D68)-1,YEAR(D68)) & " Q" & IF(ROUNDUP(MONTH(D68)/3,0)-1=0,4,ROUNDUP(MONTH(D68)/3,0)-1) -> 2017 Q4

Sheet FIBRAPL14
A1: Variable | B1: 2023 Q1 | C1: 2022 Q4 | D1: 2022 Q3 | E1: 2022 Q2 | F1: 2022 Q1 | G1: 2021 Q4 | H1: 2021 Q3 | I1: 2021 Q2 | J1: 2021 Q1 | K1: 2020 Q4 | L1: 2020 Q3 | M1: 2020 Q2 | N1: 2020 Q1 | O1: 2019 Q4 | P1: 2019 Q3 | Q1: 2019 Q2 | R1: 2019 Q1
A2: Ingresos Rentas | B2: 1401661000 | C2: 1393143000 | D2: 1385749000 | E2: 1348415000 | F2: 1371613000 | G2: 1266203000 | H2: 1207757000 | I2: 1187223000 | J2: 1198093000 | K2: 1207276000 | L2: 1099178000 | M2: 1096055000 | N2: 848876000 | O2: 841959000 | P2: 838379000 | Q2: 831282000 | R2: 871486000
A3: Ingresos Totales | B3: 1421097000 | C3: 1409563000 | D3: 1396908000 | E3: 1350328000 | F3: 1386220000 | G3: 1273805000 | H3: 1221182000 | I3: 1202880000 | J3: 1208550000 | K3: 1223651000 | L3: 1236406000 | M3: 1223139000 | N3: 978626000 | O3: 950553000 | P3: 943481000 | Q3: 938813000 | R3: 991918000
A4: NOI | B4: 1230281000 | C4: 1209516000 | D4: 1215033000 | E4: 1173884000 | F4: 1219446000 | G4: 1103701000 | H4: 1057149000 | I4: 1038743000 | J4: 1063945000 | K4: 1066494000 | L4: 1089151000 | M4: 1065795000 | N4: 837013000 | O4: 831042000 | P4: 791108000 | Q4: 817517000 | R4: 861501000
A5: Margen NOI | B5: 0.8657 | C5: 0.8581 | D5: 0.8698 | E5: 0.8693 | F5: 0.8797 | G5: 0.8665 | H5: 0.8657 | I5: 0.8635 | J5: 0.8803 | K5: 0.8716 | L5: 0.8809 | M5: 0.8714 | N5: 0.8553 | O5: 0.8743 | P5: 0.8385 | Q5: 0.8708 | R5: 0.8685
A6: FFO | B6: 927490000 | C6: 823843000 | D6: 819404000 | E6: 761692140 | F6: 826998000 | G6: 743988000 | H6: 726273000 | I6: 732438000 | J6: 737189000 | K6: 693313000 | L6: 823584000 | M6: 775408000 | N6: 610140000 | O6: 484622000 | P6: 502518000 | Q6: 364053000 | R6: 561989000
A7: Margen FFO que reporta la FIBRA | B7: 0.6527 | C7: 0.5845 | D7: 0.5866 | E7: 0.5641 | F7: 0.5966 | G7: 0.5841 | H7: 0.5947 | I7: 0.6089 | J7: 0.61 | K7: 0.5666 | L7: 0.6661 | M7: 0.6454 | N7: 0.6235 | O7: 0.5098 | P7: 0.5326 | Q7: 0.3878 | R7: 0.5666
A8: FFO que reporta la FIBRA por CBFI | B8: 0.91 | C8: 0.81 | D8: 0.96 | E8: 0.89 | F8: 0.97 | G8: 0.87 | H8: 0.86 | I8: 0.86 | J8: 0.87 | K8: 0.82 | L8: 0.97 | M8: 0.93 | N8: 0.72 | O8: 0.75 | P8: 0.78 | Q8: 0.56 | R8: 0.87
A9: Dividendos Decretados | D9: 4.7025995e+08 | E9: 5.2772569e+08 | F9: 5.111968e+08 | G9: 4.6957481e+08 | H9: 4.6560842e+08 | I9: 4.5762607e+08 | J9: 3.7550983e+08 | K9: 3.6379107e+08 | L9: 3.6379107e+08 | M9: 3.8366202e+08 | N9: 1073880001 | O9: 3.8749883e+08 | P9: 3.8003522e+08 | Q9: 3.7739206e+08 | R9: 3.8448347e+08
A10: Dividendos decretados por CBFI | B10: 0.85 | C10: 0.6 | D10: 0.55 | E10: 0.62 | F10: 0.6 | G10: 0.55 | H10: 0.55 | I10: 0.54 | J10: 0.44 | K10: 0.43 | L10: 0.43 | M10: 0.45 | N10: 1.26 | O10: 0.6 | P10: 0.59 | Q10: 0.59 | R10: 0.6
A11: CBFIS en Circulación | B11: 1021869492 | C11: 1021869492 | D11: 856419497 | E11: 856419497 | F11: 856419497 | G11: 856419497 | H11: 849185514 | I11: 849185514 | J11: 849185514 | K11: 849185514 | L11: 849185514 | M11: 849185514 | N11: 849185514 | O11: 649185514 | P11: 644673822 | Q11: 644673822 | R11: 644673822
A12: Cape Rate Implicito | B12: 0.0707 | C12: 0.0647 | D12: 0.0633
A13: Capitalización de Mercado | B13: 6.6482829e+10 | C13: 5.4526202e+10 | D13: 4.8867296e+10
A14: Descuento o Premium sobre NAV | B14: 0.1936 | C14: 0.1262 | D14: -0.1037
A15: LTV | B15: 0.2278 | C15: 0.2265 | D15: 0.2692
A16: Dividend Yield (Decretado) | B16: 0.035 | C16: 0.0342 | D16: 0.0385
A17: NAV por CBDI | B17: 54.51 | C17: 58.71 | D17: 63.66
A18: ROE Tangible | B18: 0.0696 | C18: 0.0578 | D18: 0.0569

Sheet TERRA13
A1: Variable | B1: 2023 Q1 | C1: 2022 Q4 | D1: 2022 Q3 | E1: 2022 Q2 | F1: 2022 Q1 | G1: 2021 Q4 | H1: 2021 Q3 | I1: 2021 Q2 | J1: 2021 Q1 | K1: 2020 Q4 | L1: 2020 Q3 | M1: 2020 Q2 | N1: 2020 Q1 | O1: 2019 Q4 | P1: 2019 Q3 | Q1: 2019 Q2 | R1: 2019 Q1
A2: Ingresos Rentas | B2: 0 | C2: 1007282000 | D2: 1000356000 | E2: 987717000 | F2: 1010867000 | G2: 984677000 | H2: 938900000 | I2: 946865000 | J2: 959952000 | K2: 943713000 | L2: 1103600000 | M2: 1175200000 | N2: 1010482000 | O2: 931500000 | P2: 945800000 | Q2: 905700000 | R2: 900100000
A3: Ingresos Totales | B3: 967230000 | C3: 1028371000 | D3: 1018998000 | E3: 1006428000 | F3: 1030942000 | G3: 1029189000 | H3: 967583000 | I3: 982742000 | J3: 995591000 | K3: 987920000 | L3: 1142100000 | M3: 1205200000 | N3: 1038115000 | O3: 1002500000 | P3: 1022000000 | Q3: 982000000 | R3: 1036000000
A4: NOI | B4: 899200000 | C4: 945500000 | D4: 947700000 | E4: 926061000 | F4: 965900000 | G4: 946100000 | H4: 906800000 | I4: 904000000 | J4: 935500000 | K4: 992200000 | L4: 1063400000 | M4: 1045200000 | N4: 937100000 | O4: 926000000 | P4: 955600000 | Q4: 903400000 | R4: 879800000
A5: Margen NOI | B5: 0.9297 | C5: 0.9194 | D5: 0.93 | E5: 0.9201 | F5: 0.9369 | G5: 0.9193 | H5: 0.9372 | I5: 0.9199 | J5: 0.9396 | K5: 0.8216 | L5: 0.9311 | M5: 0.8672 | N5: 0.9027 | O5: 0.9237 | P5: 0.935 | Q5: 0.92 | R5: 0.8492
A6: FFO | B6: 572000000 | C6: 598000000 | D6: 609400000 | E6: 618696000 | F6: 652200000 | G6: 617700000 | H6: 597300000 | I6: 596300000 | J6: 622200000 | K6: 662800000 | L6: 690000000 | M6: 615700000 | N6: 596600000 | O6: 584700000 | P6: 614600000 | Q6: 564900000 | R6: 546900000
A7: Margen FFO que reporta la FIBRA | B7: 0.5914 | C7: 0.5815 | D7: 0.598 | E7: 0.6147 | F7: 0.6326 | G7: 0.6002 | H7: 0.6173 | I7: 0.6068 | J7: 0.625 | K7: 0.6709 | L7: 0.6042 | M7: 0.5109 | N7: 0.5747 | O7: 0.5832 | P7: 0.6014 | Q7: 0.5753 | R7: 0.5279
A8: FFO que reporta la FIBRA por CBFI | B8: 0.73 | C8: 0.77 | D8: 0.79 | E8: 0.75 | F8: 0.89 | G8: 0.87 | H8: 0.76 | I8: 0.75 | J8: 0.79 | K8: 0.84 | L8: 0.87 | M8: 0.78 | N8: 0.75 | O8: 0.74 | P8: 0.78 | Q8: 0.71 | R8: 0.69
A9: Dividendos Decretados | B9: 3.6880203e+08 | C9: 3.2261489e+08 | D9: 3.6703803e+08 | E9: 4.0760372e+08 | F9: 3.766488e+08 | G9: 3.2294229e+08 | H9: 337269960 | I9: 363438820 | J9: 4.7641725e+08 | K9: 4.7791939e+08 | L9: 4.894622e+08 | M9: 4.6289794e+08 | N9: 4.3736147e+08 | O9: 4.9910755e+08 | P9: 5.5097109e+08 | Q9: 4.8092369e+08 | R9: 4.6526975e+08
A10: Dividendos decretados por CBFI | B10: 0.47 | C10: 0.42 | D10: 0.47 | E10: 0.49 | F10: 0.51 | G10: 0.46 | H10: 0.43 | I10: 0.46 | J10: 0.6 | K10: 0.6 | L10: 0.62 | M10: 0.59 | N10: 0.55 | O10: 0.63 | P10: 0.7 | Q10: 0.61 | R10: 0.59
A11: CBFIS en Circulación | B11: 7.8888134e+08 | C11: 7.7180595e+08 | D11: 7.7303714e+08 | E11: 8.2661471e+08 | F11: 7.3306501e+08 | G11: 7.092956e+08 | H11: 790600000 | I11: 790600000 | J11: 790602803 | K11: 790602803 | L11: 790602803 | M11: 790602803 | N11: 790602803 | O11: 790602803 | P11: 790602803 | Q11: 790602803 | R11: 790602803
A12: Cape Rate Implicito | B12: 0.0774 | C12: 0.0624 | D12: 0.0625
A13: Capitalización de Mercado | B13: 25638643712 | C13: 26698562000 | D13: 2.1544545e+10
A14: Descuento o Premium sobre NAV | B14: -0.2558 | C14: -0.2746 | D14: -0.4438
A15: LTV | B15: 0.3123 | C15: 0.3143 | D15: 0.3014
A16: Dividend Yield (Decretado) | B16: 0.0575 | C16: 0.0505 | D16: 0.0681
A17: NAV por CBDI | B17: 43.67 | C17: 47.42 | D17: 50.11
A18: ROE Tangible | B18: 0.0919 | C18: 0.0729 | D18: 0.0685

Sheet FIHO12
A1: FIHO12 | B1: 2023 Q1 | C1: 2022 Q4 | D1: 2022 Q3 | E1: 2022 Q2 | F1: 2022 Q1 | G1: 2021 Q4 | H1: 2021 Q3 | I1: 2021 Q2 | J1: 2021 Q1 | K1: 2020 Q4 | L1: 2020 Q3 | M1: 2020 Q2 | N1: 2020 Q1 | O1: 2019 Q4 | P1: 2019 Q3 | Q1: 2019 Q2 | R1: 2019 Q1
A2: Ingresos Rentas | C2: 1094480000 | D2: 984664000 | E2: 988652000 | F2: 797386000 | G2: 804313000 | H2: 665362000 | I2: 611734000 | J2: 470561000 | K2: 453257000 | L2: - | M2: - | N2: - | O2: 79463000 | P2: 80500000 | Q2: 113000000 | R2: 112714000
A3: Ingresos Totales | C3: 1335733000 | D3: 1209544000 | E3: 1200173000 | F3: 950895000 | G3: 997967000 | H3: 811305000 | I3: 743063000 | J3: 556795000 | K3: 545420000 | L3: 375755000 | M3: 71663000 | N3: 948813000 | O3: 1130832000 | P3: 1073663000 | Q3: 1125532000 | R3: 1041943000
A4: NOI | C4: 482618000 | D4: 417576000 | E4: 418202000 | F4: 201578000 | G4: 309310000 | H4: 221487000 | I4: 201578000 | J4: 134706000 | K4: 111020000 | L4: 29930000 | M4: -225218000 | N4: 276953000 | O4: 351834000 | P4: 323670000 | Q4: 368873000 | R4: 343418000
A5: Margen NOI | C5: 0.3613 | D5: 0.3452 | E5: 0.3485 | F5: 0.212 | G5: 0.3099 | H5: 0.273 | I5: 0.2713 | J5: 0.2419 | K5: 0.2199 | L5: 0.0797 | M5: -3.1427 | N5: 0.2919 | O5: 0.3111 | P5: 0.3015 | Q5: 0.3277 | R5: 0.3296
A6: FFO | C6: 282932000 | D6: 243973000 | E6: 250970000 | F6: 52932000 | G6: 146895000 | H6: 69753000 | I6: 52900000 | J6: -8053000 | K6: -38195000 | L6: -115323000 | M6: -371575000 | N6: 77691000 | O6: 218064000 | P6: 176867000 | Q6: 194996000 | R6: 215783000
A7: Margen FFO que reporta la FIBRA | C7: 0.2118 | D7: 0.2017 | E7: 0.2091 | F7: 0.0557 | G7: 0.1472 | H7: 0.086 | I7: 0.0712 | J7: -0.0145 | K7: -0.07 | L7: -0.3069 | M7: -5.185 | N7: 0.0819 | O7: 0.1928 | P7: 0.1647 | Q7: 0.1732 | R7: 0.2071
A8: FFO que reporta la FIBRA por CBFI | C8: 0.34 | D8: 0.31 | E8: 0.29 | F8: 0.06 | G8: 0.18 | H8: 0.08 | I8: 0.06 | J8: -0.01 | K8: -0.05 | L8: -0.15 | M8: -0.47 | N8: 0.1 | O8: 0.28 | P8: 0.23 | Q8: 0.25 | R8: 0.27
A9: Dividendos Decretados | C9: 0 | D9: 0 | E9: 0 | F9: 0 | G9: 0 | H9: 0 | I9: 0 | J9: 0 | K9: 0 | L9: 0 | M9: 0 | N9: 0 | O9: 1.5808698e+08 | P9: 1.3443679e+08 | Q9: 1.6295845e+08 | R9: 165629897
A10: Dividendos decretados por CBFI | B10: {=IF(SUMIFS(INDIRECT("'"&A$1&"_DIV'!"&"C:C"),INDIRECT("'"&A$1&"_DIV'!"&"E:E"),B1)=0,"",SUMIFS(INDIRECT("'"&A$1&"_DIV'!"&"C:C"),INDIRECT("'"&A$1&"_DIV'!"&"E:E"),B1))} -> 0.125 | C10: {=SUMIFS(INDIRECT("'"&A$1&"_DIV'!"&"C:C"),INDIRECT("'"&A$1&"_DIV'!"&"E:E"),C1)} -> 0 | D10: {=SUMIFS(INDIRECT("'"&A$1&"_DIV'!"&"C:C"),INDIRECT("'"&A$1&"_DIV'!"&"E:E"),D1)} -> 0 | E10: {=SUMIFS(INDIRECT("'"&A$1&"_DIV'!"&"C:C"),INDIRECT("'"&A$1&"_DIV'!"&"E:E"),E1)} -> 0 | F10: {=SUMIFS(INDIRECT("'"&A$1&"_DIV'!"&"C:C"),INDIRECT("'"&A$1&"_DIV'!"&"E:E"),F1)} -> 0 | G10: 0 | H10: 0 | I10: 0 | J10: 0 | K10: 0 | L10: 0 | M10: 0 | N10: 0 | O10: 0.2 | P10: 0.17 | Q10: 0.21 | R10: 0.21
A11: CBFIS en Circulación | C11: 833947220 | D11: 785814214 | E11: 8.6071344e+08 | F11: 833947220 | G11: 833947220 | H11: 833947220 | I11: 833947220 | J11: 833947220 | K11: 833947220 | L11: 783456458 | M11: 783456458 | N11: 783456458 | O11: 785720574 | P11: 785720574 | Q11: 785720574 | R11: 785720574
A12: Cape Rate Implicito | C12: 0.1174 | D12: 0.1051
A13: Capitalización de Mercado | C13: 9923971918 | D13: 6.5536905e+09
A14: Descuento o Premium sobre NAV | C14: -0.2429 | D14: -0.4388
A15: LTV | C15: 0.2574 | D15: 0.2783
A16: Dividend Yield (Decretado) | B16: 0.0105 | C16: 0 | D16: 0
A17: NAV por CBDI | C17: 14.79 | D17: 14.86
A18: ROE Tangible | C18: 0.1028 | D18: 0.0964

Sheet FIHO12_DIV
A1: Fecha de pago | B1: Importe
A2: 13 de mayo de 2023 | B2: MXN $0.1250 | C2: =VALUE(SUBSTITUTE(SUBSTITUTE(B2,"MXN $",""),"","")) -> 0.125 | D2: =SUBSTITUTE(SUBSTITUTE(A2,"de",""),"","") -> 13 mayo 2023 | E2: =IF(IF(ROUNDUP(MONTH(D2)/3,0)-1=0,4,ROUNDUP(MONTH(D2)/3,0)-1)=4,YEAR(D2)-1,YEAR(D2)) & " Q" & IF(ROUNDUP(MONTH(D2)/3,0)-1=0,4,ROUNDUP(MONTH(D2)/3,0)-1) -> 2023 Q1 | F2: Reembolso de Capital
A3: 13 de marzo de 2020 | B3: MXN $0.058805 | C3: =VALUE(SUBSTITUTE(SUBSTITUTE(B3,"MXN $",""),"","")) -> 0.058805 | D3: =SUBSTITUTE(SUBSTITUTE(A3,"de",""),"","") -> 13 marzo 2020 | E3: =IF(IF(ROUNDUP(MONTH(D3)/3,0)-1=0,4,ROUNDUP(MONTH(D3)/3,0)-1)=4,YEAR(D3)-1,YEAR(D3)) & " Q" & IF(ROUNDUP(MONTH(D3)/3,0)-1=0,4,ROUNDUP(MONTH(D3)/3,0)-1) -> 2019 Q4
A4: 13 de marzo de 2020 | B4: MXN $0.14291 | C4: =VALUE(SUBSTITUTE(SUBSTITUTE(B4,"MXN $",""),"","")) -> 0.14291 | D4: =SUBSTITUTE(SUBSTITUTE(A4,"de",""),"","") -> 13 marzo 2020 | E4: =IF(IF(ROUNDUP(MONTH(D4)/3,0)-1=0,4,ROUNDUP(MONTH(D4)/3,0)-1)=4,YEAR(D4)-1,YEAR(D4)) & " Q" & IF(ROUNDUP(MONTH(D4)/3,0)-1=0,4,ROUNDUP(MONTH(D4)/3,0)-1) -> 2019 Q4
A5: 8 de noviembre de 2019 | B5: MXN $0.171107 | C5: =VALUE(SUBSTITUTE(SUBSTITUTE(B5,"MXN $",""),"","")) -> 0.171107 | D5: =SUBSTITUTE(SUBSTITUTE(A5,"de",""),"","") -> 8 noviembre 2019 | E5: =IF(IF(ROUNDUP(MONTH(D5)/3,0)-1=0,4,ROUNDUP(MONTH(D5)/3,0)-1)=4,YEAR(D5)-1,YEAR(D5)) & " Q" & IF(ROUNDUP(MONTH(D5)/3,0)-1=0,4,ROUNDUP(MONTH(D5)/3,0)-1) -> 2019 Q3
A6: 2 de agosto de 2019 | B6: MXN $0.204149 | C6: =VALUE(SUBSTITUTE(SUBSTITUTE(B6,"MXN $",""),"","")) -> 0.204149 | D6: =SUBSTITUTE(SUBSTITUTE(A6,"de",""),"","") -> 2 agosto 2019 | E6: =IF(IF(ROUNDUP(MONTH(D6)/3,0)-1=0,4,ROUNDUP(MONTH(D6)/3,0)-1)=4,YEAR(D6)-1,YEAR(D6)) & " Q" & IF(ROUNDUP(MONTH(D6)/3,0)-1=0,4,ROUNDUP(MONTH(D6)/3,0)-1) -> 2019 Q2
A7: 2 de agosto de 2019 | B7: MXN $0.022248 | C7: =VALUE(SUBSTITUTE(SUBSTITUTE(B7,"MXN $",""),"","")) -> 0.022248 | D7: =SUBSTITUTE(SUBSTITUTE(A7,"de",""),"","") -> 2 agosto 2019 | E7: =IF(IF(ROUNDUP(MONTH(D7)/3,0)-1=0,4,ROUNDUP(MONTH(D7)/3,0)-1)=4,YEAR(D7)-1,YEAR(D7)) & " Q" & IF(ROUNDUP(MONTH(D7)/3,0)-1=0,4,ROUNDUP(MONTH(D7)/3,0)-1) -> 2019 Q2
A8: 17 de mayo de 2019 | B8: MXN $0.111074 | C8: =VALUE(SUBSTITUTE(SUBSTITUTE(B8,"MXN $",""),"","")) -> 0.111074 | D8: =SUBSTITUTE(SUBSTITUTE(A8,"de",""),"","") -> 17 mayo 2019 | E8: =IF(IF(ROUNDUP(MONTH(D8)/3,0)-1=0,4,ROUNDUP(MONTH(D8)/3,0)-1)=4,YEAR(D8)-1,YEAR(D8)) & " Q" & IF(ROUNDUP(MONTH(D8)/3,0)-1=0,4,ROUNDUP(MONTH(D8)/3,0)-1) -> 2019 Q1
A9: 17 de mayo de 2019 | B9: MXN $0.099762 | C9: =VALUE(SUBSTITUTE(SUBSTITUTE(B9,"MXN $",""),"","")) -> 0.099762 | D9: =SUBSTITUTE(SUBSTITUTE(A9,"de",""),"","") -> 17 mayo 2019 | E9: =IF(IF(ROUNDUP(MONTH(D9)/3,0)-1=0,4,ROUNDUP(MONTH(D9)/3,0)-1)=4,YEAR(D9)-1,YEAR(D9)) & " Q" & IF(ROUNDUP(MONTH(D9)/3,0)-1=0,4,ROUNDUP(MONTH(D9)/3,0)-1) -> 2019 Q1
A10: 8 de marzo de 2019 | B10: MXN $0.262211 | C10: =VALUE(SUBSTITUTE(SUBSTITUTE(B10,"MXN $",""),"","")) -> 0.262211 | D10: =SUBSTITUTE(SUBSTITUTE(A10,"de",""),"","") -> 8 marzo 2019 | E10: =IF(IF(ROUNDUP(MONTH(D10)/3,0)-1=0,4,ROUNDUP(MONTH(D10)/3,0)-1)=4,YEAR(D10)-1,YEAR(D10)) & " Q" & IF(ROUNDUP(MONTH(D10)/3,0)-1=0,4,ROUNDUP(MONTH(D10)/3,0)-1) -> 2018 Q4
A11: 5 de noviembre de 2018 | B11: MXN $0.097852 | C11: =VALUE(SUBSTITUTE(SUBSTITUTE(B11,"MXN $",""),"","")) -> 0.097852 | D11: =SUBSTITUTE(SUBSTITUTE(A11,"de",""),"","") -> 5 noviembre 2018 | E11: =IF(IF(ROUNDUP(MONTH(D11)/3,0)-1=0,4,ROUNDUP(MONTH(D11)/3,0)-1)=4,YEAR(D11)-1,YEAR(D11)) & " Q" & IF(ROUNDUP(MONTH(D11)/3,0)-1=0,4,ROUNDUP(MONTH(D11)/3,0)-1) -> 2018 Q3
A12: 5 de noviembre de 2018 | B12: MXN $0.109591 | C12: =VALUE(SUBSTITUTE(SUBSTITUTE(B12,"MXN $",""),"","")) -> 0.109591 | D12: =SUBSTITUTE(SUBSTITUTE(A12,"de",""),"","") -> 5 noviembre 2018 | E12: =IF(IF(ROUNDUP(MONTH(D12)/3,0)-1=0,4,ROUNDUP(MONTH(D12)/3,0)-1)=4,YEAR(D12)-1,YEAR(D12)) & " Q" & IF(ROUNDUP(MONTH(D12)/3,0)-1=0,4,ROUNDUP(MONTH(D12)/3,0)-1) -> 2018 Q3
A13: 27 de julio de 2018 | B13: MXN $0.141257 | C13: =VALUE(SUBSTITUTE(SUBSTITUTE(B13,"MXN $",""),"","")) -> 0.141257 | D13: =SUBSTITUTE(SUBSTITUTE(A13,"de",""),"","") -> 27 julio 2018 | E13: =IF(IF(ROUNDUP(MONTH(D13)/3,0)-1=0,4,ROUNDUP(MONTH(D13)/3,0)-1)=4,YEAR(D13)-1,YEAR(D13)) & " Q" & IF(ROUNDUP(MONTH(D13)/3,0)-1=0,4,ROUNDUP(MONTH(D13)/3,0)-1) -> 2018 Q2
A14: 27 de julio de 2018 | B14: MXN $0.148851 | C14: =VALUE(SUBSTITUTE(SUBSTITUTE(B14,"MXN $",""),"","")) -> 0.148851 | D14: =SUBSTITUTE(SUBSTITUTE(A14,"de",""),"","") -> 27 julio 2018 | E14: =IF(IF(ROUNDUP(MONTH(D14)/3,0)-1=0,4,ROUNDUP(MONTH(D14)/3,0)-1)=4,YEAR(D14)-1,YEAR(D14)) & " Q" & IF(ROUNDUP(MONTH(D14)/3,0)-1=0,4,ROUNDUP(MONTH(D14)/3,0)-1) -> 2018 Q2
... A18: 9 de marzo de 2018 | B18: MXN $0.050283 | C18: =VALUE(SUBSTITUTE(SUBSTITUTE(B18,"MXN $",""),"","")) -> 0.050283 | D18: =SUBSTITUTE(SUBSTITUTE(A18,"de",""),"","") -> 9 marzo 2018 | E18: =IF(IF(ROUNDUP(MONTH(D18)/3,0)-1=0,4,ROUNDUP(MONTH(D18)/3,0)-1)=4,YEAR(D18)-1,YEAR(D18)) & " Q" & IF(ROUNDUP(MONTH(D18)/3,0)-1=0,4,ROUNDUP(MONTH(D18)/3,0)-1) -> 2017 Q4

Sheet FINN13
A1: FINN13 | B1: 2023 Q1 | C1: 2022 Q4 | D1: 2022 Q3 | E1: 2022 Q2 | F1: 2022 Q1 | G1: 2021 Q4 | H1: 2021 Q3 | I1: 2021 Q2 | J1: 2021 Q1 | K1: 2020 Q4 | L1: 2020 Q3 | M1: 2020 Q2 | N1: 2020 Q1 | O1: 2019 Q4 | P1: 2019 Q3 | Q1: 2019 Q2 | R1: 2019 Q1
A2: Ingresos Rentas | B2: 531980000 | C2: 544021000 | D2: 505493000 | E2: 485587000 | F2: 377598000 | G2: 393106000 | H2: 324941000 | I2: 279741000 | J2: 185981000 | K2: 156444000 | L2: 9000000 | M2: 4858000 | N2: 17260000 | O2: 24370000 | P2: 25100000 | Q2: 24700000 | R2: 23700000
A3: Ingresos Totales | B3: 531980000 | C3: 544021000 | D3: 505493000 | E3: 485587000 | F3: 377598000 | G3: 393106000 | H3: 324941000 | I3: 279741000 | J3: 185981000 | K3: 156444000 | L3: 137467000 | M3: 55331000 | N3: 357025000 | O3: 468476000 | P3: 487300000 | Q3: 484300000 | R3: 480100000
A4: NOI | B4: 178700000 | C4: 188600000 | D4: 164400000 | E4: 162500000 | F4: 114994000 | G4: 117638000 | H4: 73800000 | I4: 56800000 | J4: 9182000 | K4: -1398000 | L4: -24408000 | M4: -86900000 | N4: 69211000 | O4: 146239000 | P4: 154281000 | Q4: 150071000 | R4: 166700000
A5: Margen NOI | B5: 0.3359 | C5: 0.3467 | D5: 0.3252 | E5: 0.3346 | F5: 0.3045 | G5: 0.2993 | H5: 0.2271 | I5: 0.203 | J5: 0.0494 | K5: 0.0624 | L5: -0.1776 | M5: -1.5705 | N5: 0.1939 | O5: 0.3122 | P5: 0.3166 | Q5: 0.3099 | R5: 0.3472
A6: FFO | B6: 45300000 | C6: 51900000 | D6: 39300000 | E6: 36900000 | F6: -4414000 | G6: -4029000 | H6: -54500000 | I6: -46200000 | J6: -96900000 | K6: -117055000 | L6: -125104000 | M6: -184848000 | N6: 39336000 | O6: 79960000 | P6: 79500000 | Q6: 92800000 | R6: 97900000
A7: Margen FFO que reporta la FIBRA | B7: 0.0852 | C7: 0.0954 | D7: 0.0777 | E7: 0.076 | F7: -0.0117 | G7: -0.0102 | H7: -0.1677 | I7: -0.1652 | J7: -0.521 | K7: -0.7482 | L7: -0.9101 | M7: -3.3408 | N7: 0.1102 | O7: 0.1707 | P7: 0.1631 | Q7: 0.1916 | R7: 0.2039
A8: FFO que reporta la FIBRA por CBFI | B8: 0.09 | C8: 0.1 | D8: 0.08 | E8: 0.07 | F8: -0.01 | G8: -0.01 | H8: -0.11 | I8: -0.09 | J8: -0.19 | K8: -0.24 | L8: -0.25 | M8: -0.38 | N8: 0.08 | O8: 0.16 | P8: 0.15 | Q8: 0.18 | R8: 0.19
A9: Dividendos Decretados | B9: 21101806 | C9: 21555066 | D9: 21555066 | E9: 0 | F9: 0 | G9: 0 | H9: 0 | I9: 0 | J9: 0 | K9: 0 | L9: 0 | M9: 0 | N9: 0 | O9: 63566848 | P9: 66312957 | Q9: 38920523 | R9: 82758993
A10: Dividendos decretados por CBFI | B10: 0.04 | C10: {=SUMIFS(INDIRECT("'"&A$1&"_DIV'!"&"C:C"),INDIRECT("'"&A$1&"_DIV'!"&"E:E"),C1)} -> 0.042845 | D10: {=SUMIFS(INDIRECT("'"&A$1&"_DIV'!"&"C:C"),INDIRECT("'"&A$1&"_DIV'!"&"E:E"),D1)} -> 0.042845 | E10: {=SUMIFS(INDIRECT("'"&A$1&"_DIV'!"&"C:C"),INDIRECT("'"&A$1&"_DIV'!"&"E:E"),E1)} -> 0 | F10: {=SUMIFS(INDIRECT("'"&A$1&"_DIV'!"&"C:C"),INDIRECT("'"&A$1&"_DIV'!"&"E:E"),F1)} -> 0 | G10: 0 | H10: 0 | I10: 0 | J10: 0 | K10: 0 | L10: 0 | M10: 0 | N10: 0 | O10: 0.13 | P10: 0.13 | Q10: 0.07 | R10: 0.16
A11: CBFIS en Circulación | B11: 503623046 | C11: 503623046 | D11: 503623046 | E11: 503623046 | F11: 503623046 | G11: 503623046 | H11: 503846946 | I11: 503846946 | J11: 503846946 | K11: 492620026 | L11: 497820188 | M11: 492396126 | N11: 492615026 | O11: 493531428 | P11: 528811458 | Q11: 528811458 | R11: 528811458
A12: Cape Rate Implicito | B12: 0.0748 | C12: 0.0784 | D12: 0.0735
A13: Capitalización de Mercado | B13: 3.2231875e+09 | C13: 2.8719276e+09 | D13: 1.9087313e+09
A14: Descuento o Premium sobre NAV | B14: -0.5828 | C14: -0.6367 | D14: -0.7343
A15: LTV | B15: 0.3353 | C15: 0.333 | D15: 0.3503
A16: Dividend Yield (Decretado) | B16: 0.0262 | C16: 0 | D16: 0.0452
A17: NAV por CBDI | B17: 15.34 | C17: 15.55 | D17: 14.26
A18: ROE Tangible | B18: 0.0525 | C18: 0.0672 | D18: 0.058

Sheet FINN13_DIV
A1: Fecha de pago | B1: Importe
A2: 30 de marzo de 2023 | B2: MXN $0.042845 | C2: =VALUE(SUBSTITUTE(SUBSTITUTE(B2,"MXN $",""),"","")) -> 0.042845 | D2: =SUBSTITUTE(SUBSTITUTE(A2,"de",""),"","") -> 30 marzo 2023 | E2: =IF(IF(ROUNDUP(MONTH(D2)/3,0)-1=0,4,ROUNDUP(MONTH(D2)/3,0)-1)=4,YEAR(D2)-1,YEAR(D2)) & " Q" & IF(ROUNDUP(MONTH(D2)/3,0)-1=0,4,ROUNDUP(MONTH(D2)/3,0)-1) -> 2022 Q4 | F2: Reembolso de Capital
A3: 15 de noviembre de 2022 | B3: MXN $0.042845 | C3: =VALUE(SUBSTITUTE(SUBSTITUTE(B3,"MXN $",""),"","")) -> 0.042845 | D3: =SUBSTITUTE(SUBSTITUTE(A3,"de",""),"","") -> 15 noviembre 2022 | E3: =IF(IF(ROUNDUP(MONTH(D3)/3,0)-1=0,4,ROUNDUP(MONTH(D3)/3,0)-1)=4,YEAR(D3)-1,YEAR(D3)) & " Q" & IF(ROUNDUP(MONTH(D3)/3,0)-1=0,4,ROUNDUP(MONTH(D3)/3,0)-1) -> 2022 Q3
A4: 20 de marzo de 2020 | B4: MXN $0.129033 | C4: =VALUE(SUBSTITUTE(SUBSTITUTE(B4,"MXN $",""),"","")) -> 0.129033 | D4: =SUBSTITUTE(SUBSTITUTE(A4,"de",""),"","") -> 20 marzo 2020 | E4: =IF(IF(ROUNDUP(MONTH(D4)/3,0)-1=0,4,ROUNDUP(MONTH(D4)/3,0)-1)=4,YEAR(D4)-1,YEAR(D4)) & " Q" & IF(ROUNDUP(MONTH(D4)/3,0)-1=0,4,ROUNDUP(MONTH(D4)/3,0)-1) -> 2019 Q4
A5: 15 de noviembre de 2019 | B5: MXN $0.063141 | C5: =VALUE(SUBSTITUTE(SUBSTITUTE(B5,"MXN $",""),"","")) -> 0.063141 | D5: =SUBSTITUTE(SUBSTITUTE(A5,"de",""),"","") -> 15 noviembre 2019 | E5: =IF(IF(ROUNDUP(MONTH(D5)/3,0)-1=0,4,ROUNDUP(MONTH(D5)/3,0)-1)=4,YEAR(D5)-1,YEAR(D5)) & " Q" & IF(ROUNDUP(MONTH(D5)/3,0)-1=0,4,ROUNDUP(MONTH(D5)/3,0)-1) -> 2019 Q3
A6: 16 de agosto de 2019 | B6: MXN $0.073944 | C6: =VALUE(SUBSTITUTE(SUBSTITUTE(B6,"MXN $",""),"","")) -> 0.073944 | D6: =SUBSTITUTE(SUBSTITUTE(A6,"de",""),"","") -> 16 agosto 2019 | E6: =IF(IF(ROUNDUP(MONTH(D6)/3,0)-1=0,4,ROUNDUP(MONTH(D6)/3,0)-1)=4,YEAR(D6)-1,YEAR(D6)) & " Q" & IF(ROUNDUP(MONTH(D6)/3,0)-1=0,4,ROUNDUP(MONTH(D6)/3,0)-1) -> 2019 Q2
A7: 16 de mayo de 2019 | B7: MXN $0.1569 | C7: =VALUE(SUBSTITUTE(SUBSTITUTE(B7,"MXN $",""),"","")) -> 0.1569 | D7: =SUBSTITUTE(SUBSTITUTE(A7,"de",""),"","") -> 16 mayo 2019 | E7: =IF(IF(ROUNDUP(MONTH(D7)/3,0)-1=0,4,ROUNDUP(MONTH(D7)/3,0)-1)=4,YEAR(D7)-1,YEAR(D7)) & " Q" & IF(ROUNDUP(MONTH(D7)/3,0)-1=0,4,ROUNDUP(MONTH(D7)/3,0)-1) -> 2019 Q1
A8: 15 de marzo de 2019 | B8: MXN $0.180606 | C8: =VALUE(SUBSTITUTE(SUBSTITUTE(B8,"MXN $",""),"","")) -> 0.180606 | D8: =SUBSTITUTE(SUBSTITUTE(A8,"de",""),"","") -> 15 marzo 2019 | E8: =IF(IF(ROUNDUP(MONTH(D8)/3,0)-1=0,4,ROUNDUP(MONTH(D8)/3,0)-1)=4,YEAR(D8)-1,YEAR(D8)) & " Q" & IF(ROUNDUP(MONTH(D8)/3,0)-1=0,4,ROUNDUP(MONTH(D8)/3,0)-1) -> 2018 Q4
A9: 14 de noviembre de 2018 | B9: MXN $0.180492 | C9: =VALUE(SUBSTITUTE(SUBSTITUTE(B9,"MXN $",""),"","")) -> 0.180492 | D9: =SUBSTITUTE(SUBSTITUTE(A9,"de",""),"","") -> 14 noviembre 2018 | E9: =IF(IF(ROUNDUP(MONTH(D9)/3,0)-1=0,4,ROUNDUP(MONTH(D9)/3,0)-1)=4,YEAR(D9)-1,YEAR(D9)) & " Q" & IF(ROUNDUP(MONTH(D9)/3,0)-1=0,4,ROUNDUP(MONTH(D9)/3,0)-1) -> 2018 Q3
A10: 15 de agosto de 2018 | B10: MXN $0.210375 | C10: =VALUE(SUBSTITUTE(SUBSTITUTE(B10,"MXN $",""),"","")) -> 0.210375 | D10: =SUBSTITUTE(SUBSTITUTE(A10,"de",""),"","") -> 15 agosto 2018 | E10: =IF(IF(ROUNDUP(MONTH(D10)/3,0)-1=0,4,ROUNDUP(MONTH(D10)/3,0)-1)=4,YEAR(D10)-1,YEAR(D10)) & " Q" & IF(ROUNDUP(MONTH(D10)/3,0)-1=0,4,ROUNDUP(MONTH(D10)/3,0)-1) -> 2018 Q2
A11: 16 de mayo de 2018 | B11: MXN $0.25111 | C11: =VALUE(SUBSTITUTE(SUBSTITUTE(B11,"MXN $",""),"","")) -> 0.25111 | D11: =SUBSTITUTE(SUBSTITUTE(A11,"de",""),"","") -> 16 mayo 2018 | E11: =IF(IF(ROUNDUP(MONTH(D11)/3,0)-1=0,4,ROUNDUP(MONTH(D11)/3,0)-1)=4,YEAR(D11)-1,YEAR(D11)) & " Q" & IF(ROUNDUP(MONTH(D11)/3,0)-1=0,4,ROUNDUP(MONTH(D11)/3,0)-1) -> 2018 Q1
A12: 15 de marzo de 2018 | B12: MXN $0.251818 | C12: =VALUE(SUBSTITUTE(SUBSTITUTE(B12,"MXN $",""),"","")) -> 0.251818 | D12: =SUBSTITUTE(SUBSTITUTE(A12,"de",""),"","") -> 15 marzo 2018 | E12: =IF(IF(ROUNDUP(MONTH(D12)/3,0)-1=0,4,ROUNDUP(MONTH(D12)/3,0)-1)=4,YEAR(D12)-1,YEAR(D12)) & " Q" & IF(ROUNDUP(MONTH(D12)/3,0)-1=0,4,ROUNDUP(MONTH(D12)/3,0)-1) -> 2017 Q4

Sheet EDUCA18
A1: EDUCA18 | B1: 2023 Q1 | C1: 2022 Q4 | D1: 2022 Q3 | E1: 2022 Q2 | F1: 2022 Q1 | G1: 2021 Q4 | H1: 2021 Q3 | I1: 2021 Q2 | J1: 2021 Q1 | K1: 2020 Q4 | L1: 2020 Q3 | M1: 2020 Q2 | N1: 2020 Q1 | O1: 2019 Q4 | P1: 2019 Q3 | Q1: 2019 Q2 | R1: 2019 Q1
A2: Ingresos Rentas | C2: 1005586000 | D2: 1014727000 | E2: 808657000 | F2: 803953000 | G2: 792774000 | H2: 791655000 | I2: 754062000 | J2: 753092000 | K2: 750469000 | L2: 750190000 | M2: 729590000 | N2: 729081000 | O2: 646975000 | P2: 612497000 | Q2: 521100000 | R2: 503678000
A3: Ingresos Totales | C3: 1005586000 | D3: 1014727000 | E3: 808657000 | F3: 803953000 | G3: 792774000 | H3: 791655000 | I3: 754062000 | J3: 753092000 | K3: 750469000 | L3: 750190000 | M3: 729590000 | N3: 729081000 | O3: 646975000 | P3: 612497000 | Q3: 521100000 | R3: 503678000
A4: NOI | C4: 873131000 | D4: 886591000 | E4: 701174000 | F4: 697384000 | G4: 688222000 | H4: 694936000 | I4: 663710000 | J4: 661555000 | K4: 679262000 | L4: 645636000 | M4: 644986000 | N4: 645280000 | O4: 583577000 | P4: 540090000 | Q4: 427224000 | R4: 443507000
A5: Margen NOI | C5: 0.8683 | D5: 0.8737 | E5: 0.8671 | F5: 0.8674 | G5: 0.8681 | H5: 0.8778 | I5: 0.8802 | J5: 0.8785 | K5: 1 | L5: 0.8606 | M5: 0.884 | N5: 0.8851 | O5: 0.902 | P5: 0.8818 | Q5: 0.8199 | R5: 0.8805
A6: FFO | C6: 722945000 | D6: 747659000 | E6: 670897000 | F6: 702812000 | G6: 686436000 | H6: 689377000 | I6: 675827000 | J6: 675178000 | K6: 670767000 | L6: 638657000 | M6: 653919000 | N6: 657210000 | O6: 656573000 | P6: 624838000 | Q6: 602743000 | R6: 598307000
A7: Margen FFO que reporta la FIBRA | C7: 0.7189 | D7: 0.7368 | E7: 0.8296 | F7: 0.8742 | G7: 0.8659 | H7: 0.8708 | I7: 0.8962 | J7: 0.8965 | K7: 0.8938 | L7: 0.8513 | M7: 0.8963 | N7: 0.9014 | O7: 1.0148 | P7: 1.0201 | Q7: 1.1567 | R7: 1.1879
A8: FFO que reporta la FIBRA por CBFI | C8: 0.59 | D8: 0.61 | E8: 0.55 | F8: 0.57 | G8: 0.56 | H8: 0.56 | I8: 0.55 | J8: 0.55 | K8: 0.55 | L8: 0.52 | M8: 0.53 | N8: 0.54 | O8: 0.53 | P8: 0.51 | Q8: 0.49 | R8: 0.49
A9: Dividendos Decretados | C9: 6.9094763e+08 | D9: 7.0690162e+08 | E9: 7.0284786e+08 | F9: 7.0137151e+08 | G9: 7.0037649e+08 | H9: 6.9988125e+08 | I9: 6.8686566e+08 | J9: 6.8366864e+08 | K9: 6.857674e+08 | L9: 6.8375122e+08 | M9: 6.3661867e+08 | N9: 6.3734334e+08 | O9: 6.5648303e+08 | P9: 6.2483745e+08 | Q9: 6.0273362e+08 | R9: 5.9830555e+08
A10: Dividendos decretados por CBFI | B10: {=IF(SUMIFS(INDIRECT("'"&A$1&"_DIV'!"&"C:C"),INDIRECT("'"&A$1&"_DIV'!"&"E:E"),B1)=0,"",SUMIFS(INDIRECT("'"&A$1&"_DIV'!"&"C:C"),INDIRECT("'"&A$1&"_DIV'!"&"E:E"),B1))} -> 0.5702 | C10: {=SUMIFS(INDIRECT("'"&A$1&"_DIV'!"&"C:C"),INDIRECT("'"&A$1&"_DIV'!"&"E:E"),C1)} -> 0.562886 | D10: {=SUMIFS(INDIRECT("'"&A$1&"_DIV'!"&"C:C"),INDIRECT("'"&A$1&"_DIV'!"&"E:E"),D1)} -> 0.575904 | E10: {=SUMIFS(INDIRECT("'"&A$1&"_DIV'!"&"C:C"),INDIRECT("'"&A$1&"_DIV'!"&"E:E"),E1)} -> 0.572638 | F10: {=SUMIFS(INDIRECT("'"&A$1&"_DIV'!"&"C:C"),INDIRECT("'"&A$1&"_DIV'!"&"E:E"),F1)} -> 0.571389 | G10: 0.57 | H10: 0.57 | I10: 0.56 | J10: 0.56 | K10: 0.56 | L10: 0.56 | M10: 0.52 | N10: 0.52 | O10: 0.53 | P10: 0.51 | Q10: 0.49 | R10: 0.49
A11: CBFIS en Circulación | C11: 1227478470 | D11: 1227472862 | E11: 1227467453 | F11: 1227461509 | G11: 1227438647 | H11: 1227431159 | I11: 1227422551 | J11: 1227412275 | K11: 1227374736 | L11: 1227364432 | M11: 1227353940 | N11: 1227312411 | O11: 1227300488 | P11: 1227286744 | Q11: 1227263448 | R11: 1227248116
A12: Cape Rate Implicito | C12: 0.1141 | D12: 0.1199
A13: Capitalización de Mercado | C13: 61371557950 | D13: 6.2723863e+10
A14: Descuento o Premium sobre NAV | C14: 1.0945 | D14: 1.1119
A15: LTV | C15: 0.1529 | D15: 0.1583
A16: Dividend Yield (Decretado) | C16: 0.0456 | D16: 0.0451
A17: NAV por CBDI | C17: 25.3 | D17: 24.2
A18: ROE Tangible | C18: 0.0923 | D18: 0.0854

Sheet EDUCA18_DIV
A1: Fecha de pago | B1: Importe
A2: 15 de mayo de 2023 | B2: MXN $0.3344 | C2: =VALUE(SUBSTITUTE(SUBSTITUTE(B2,"MXN $",""),"","")) -> 0.3344 | D2: =SUBSTITUTE(SUBSTITUTE(A2,"de",""),"","") -> 15 mayo 2023 | E2: =IF(IF(ROUNDUP(MONTH(D2)/3,0)-1=0,4,ROUNDUP(MONTH(D2)/3,0)-1)=4,YEAR(D2)-1,YEAR(D2)) & " Q" & IF(ROUNDUP(MONTH(D2)/3,0)-1=0,4,ROUNDUP(MONTH(D2)/3,0)-1) -> 2023 Q1 | F2: Resultado Fiscal
A3: 15 de mayo de 2023 | B3: MXN $0.2358 | C3: =VALUE(SUBSTITUTE(SUBSTITUTE(B3,"MXN $",""),"","")) -> 0.2358 | D3: =SUBSTITUTE(SUBSTITUTE(A3,"de",""),"","") -> 15 mayo 2023 | E3: =IF(IF(ROUNDUP(MONTH(D3)/3,0)-1=0,4,ROUNDUP(MONTH(D3)/3,0)-1)=4,YEAR(D3)-1,YEAR(D3)) & " Q" & IF(ROUNDUP(MONTH(D3)/3,0)-1=0,4,ROUNDUP(MONTH(D3)/3,0)-1) -> 2023 Q1 | F3: Reembolso de Capital
A4: 8 de marzo de 2023 | B4: MXN $0.562886 | C4: =VALUE(SUBSTITUTE(SUBSTITUTE(B4,"MXN $",""),"","")) -> 0.562886 | D4: =SUBSTITUTE(SUBSTITUTE(A4,"de",""),"","") -> 8 marzo 2023 | E4: =IF(IF(ROUNDUP(MONTH(D4)/3,0)-1=0,4,ROUNDUP(MONTH(D4)/3,0)-1)=4,YEAR(D4)-1,YEAR(D4)) & " Q" & IF(ROUNDUP(MONTH(D4)/3,0)-1=0,4,ROUNDUP(MONTH(D4)/3,0)-1) -> 2022 Q4
A5: 9 de noviembre de 2022 | B5: MXN $0.575904 | C5: =VALUE(SUBSTITUTE(SUBSTITUTE(B5,"MXN $",""),"","")) -> 0.575904 | D5: =SUBSTITUTE(SUBSTITUTE(A5,"de",""),"","") -> 9 noviembre 2022 | E5: =IF(IF(ROUNDUP(MONTH(D5)/3,0)-1=0,4,ROUNDUP(MONTH(D5)/3,0)-1)=4,YEAR(D5)-1,YEAR(D5)) & " Q" & IF(ROUNDUP(MONTH(D5)/3,0)-1=0,4,ROUNDUP(MONTH(D5)/3,0)-1) -> 2022 Q3
A6: 2 de agosto de 2022 | B6: MXN $0.572638 | C6: =VALUE(SUBSTITUTE(SUBSTITUTE(B6,"MXN $",""),"","")) -> 0.572638 | D6: =SUBSTITUTE(SUBSTITUTE(A6,"de",""),"","") -> 2 agosto 2022 | E6: =IF(IF(ROUNDUP(MONTH(D6)/3,0)-1=0,4,ROUNDUP(MONTH(D6)/3,0)-1)=4,YEAR(D6)-1,YEAR(D6)) & " Q" & IF(ROUNDUP(MONTH(D6)/3,0)-1=0,4,ROUNDUP(MONTH(D6)/3,0)-1) -> 2022 Q2
A7: 13 de mayo de 2022 | B7: MXN $0.571389 | C7: =VALUE(SUBSTITUTE(SUBSTITUTE(B7,"MXN $",""),"","")) -> 0.571389 | D7: =SUBSTITUTE(SUBSTITUTE(A7,"de",""),"","") -> 13 mayo 2022 | E7: =IF(IF(ROUNDUP(MONTH(D7)/3,0)-1=0,4,ROUNDUP(MONTH(D7)/3,0)-1)=4,YEAR(D7)-1,YEAR(D7)) & " Q" & IF(ROUNDUP(MONTH(D7)/3,0)-1=0,4,ROUNDUP(MONTH(D7)/3,0)-1) -> 2022 Q1
A8: 8 de marzo de 2022 | B8: MXN $0.570638 | C8: =VALUE(SUBSTITUTE(SUBSTITUTE(B8,"MXN $",""),"","")) -> 0.570638 | D8: =SUBSTITUTE(SUBSTITUTE(A8,"de",""),"","") -> 8 marzo 2022 | E8: =IF(IF(ROUNDUP(MONTH(D8)/3,0)-1=0,4,ROUNDUP(MONTH(D8)/3,0)-1)=4,YEAR(D8)-1,YEAR(D8)) & " Q" & IF(ROUNDUP(MONTH(D8)/3,0)-1=0,4,ROUNDUP(MONTH(D8)/3,0)-1) -> 2021 Q4
A9: 9 de noviembre de 2021 | B9: MXN $0.570193 | C9: =VALUE(SUBSTITUTE(SUBSTITUTE(B9,"MXN $",""),"","")) -> 0.570193 | D9: =SUBSTITUTE(SUBSTITUTE(A9,"de",""),"","") -> 9 noviembre 2021 | E9: =IF(IF(ROUNDUP(MONTH(D9)/3,0)-1=0,4,ROUNDUP(MONTH(D9)/3,0)-1)=4,YEAR(D9)-1,YEAR(D9)) & " Q" & IF(ROUNDUP(MONTH(D9)/3,0)-1=0,4,ROUNDUP(MONTH(D9)/3,0)-1) -> 2021 Q3
A10: 5 de agosto de 2021 | B10: MXN $0.559565 | C10: =VALUE(SUBSTITUTE(SUBSTITUTE(B10,"MXN $",""),"","")) -> 0.559565 | D10: =SUBSTITUTE(SUBSTITUTE(A10,"de",""),"","") -> 5 agosto 2021 | E10: =IF(IF(ROUNDUP(MONTH(D10)/3,0)-1=0,4,ROUNDUP(MONTH(D10)/3,0)-1)=4,YEAR(D10)-1,YEAR(D10)) & " Q" & IF(ROUNDUP(MONTH(D10)/3,0)-1=0,4,ROUNDUP(MONTH(D10)/3,0)-1) -> 2021 Q2
A11: 13 de mayo de 2021 | B11: MXN $0.557003 | C11: =VALUE(SUBSTITUTE(SUBSTITUTE(B11,"MXN $",""),"","")) -> 0.557003 | D11: =SUBSTITUTE(SUBSTITUTE(A11,"de",""),"","") -> 13 mayo 2021 | E11: =IF(IF(ROUNDUP(MONTH(D11)/3,0)-1=0,4,ROUNDUP(MONTH(D11)/3,0)-1)=4,YEAR(D11)-1,YEAR(D11)) & " Q" & IF(ROUNDUP(MONTH(D11)/3,0)-1=0,4,ROUNDUP(MONTH(D11)/3,0)-1) -> 2021 Q1
A12: 4 de marzo de 2021 | B12: MXN $0.558709 | C12: =VALUE(SUBSTITUTE(SUBSTITUTE(B12,"MXN $",""),"","")) -> 0.558709 | D12: =SUBSTITUTE(SUBSTITUTE(A12,"de",""),"","") -> 4 marzo 2021 | E12: =IF(IF(ROUNDUP(MONTH(D12)/3,0)-1=0,4,ROUNDUP(MONTH(D12)/3,0)-1)=4,YEAR(D12)-1,YEAR(D12)) & " Q" & IF(ROUNDUP(MONTH(D12)/3,0)-1=0,4,ROUNDUP(MONTH(D12)/3,0)-1) -> 2020 Q4
